Workbook

Sheet 🌿 Herb Lookup
A2: 🌿 The Greenman Magical Herb Oracle 🌿
A4: 🌿 Select Herb: | C4: LEMONGRASS
A6: 🌿 IDENTITY
A7: =IFERROR("🌿 "&VLOOKUP($C$4,_d_herbs!$A:$BL,2,0),"")
A8: =IFERROR("( "&VLOOKUP($C$4,_d_herbs!$A:$BL,1,0)&" )","")
A9: =IFERROR("✦ "&VLOOKUP($C$4,_d_herbs!$A:$BL,3,0),"")
A11: 🔮 MAGICAL USES
B12: MAGICAL USES | C12: =IFERROR(VLOOKUP($C$4,_d_herbs!$A:$BL,4,0),"")
A14: 💫 SPIRITUAL & POWERS
B15: POWERS | C15: =IFERROR(VLOOKUP($C$4,_d_herbs!$A:$BL,13,0),"")
B16: SPIRITUAL USES | C16: =IFERROR(VLOOKUP($C$4,_d_herbs!$A:$BL,14,0),"")
A18: 📖 CORRESPONDENCES
B19: ASSOCIATION | C19: =IFERROR(VLOOKUP($C$4,_d_herbs!$A:$BL,5,0),"")
B20: ELEMENT | C20: =IFERROR(VLOOKUP($C$4,_d_herbs!$A:$BL,7,0),"")
B21: ENERGY | C21: =IFERROR(VLOOKUP($C$4,_d_herbs!$A:$BL,8,0),"")
B22: DAY | C22: =IFERROR(VLOOKUP($C$4,_d_herbs!$A:$BL,9,0),"")
B23: DEITY | C23: =IFERROR(VLOOKUP($C$4,_d_herbs!$A:$BL,10,0),"")
B24: SABBAT | C24: =IFERROR(VLOOKUP($C$4,_d_herbs!$A:$BL,11,0),"")
B25: PLANET | C25: =IFERROR(VLOOKUP($C$4,_d_herbs!$A:$BL,6,0),"")
B26: ZODIAC SIGN | C26: =IFERROR(VLOOKUP($C$4,_d_herbs!$A:$BL,63,0),"")
A28: ◈ ASSOCIATED CRYSTALS
B29: CRYSTAL 1 | C29: =IFERROR(VLOOKUP($C$4,_d_herbs!$A:$BL,39,0),"")
B30: USES | C30: =IFERROR(VLOOKUP($C$4,_d_herbs!$A:$BL,40,0),"")
B31: POWERS | C31: =IFERROR(VLOOKUP($C$4,_d_herbs!$A:$BL,41,0),"")
B33: CRYSTAL 2 | C33: =IFERROR(VLOOKUP($C$4,_d_herbs!$A:$BL,42,0),"")
B34: USES | C34: =IFERROR(VLOOKUP($C$4,_d_herbs!$A:$BL,43,0),"")
B35: POWERS | C35: =IFERROR(VLOOKUP($C$4,_d_herbs!$A:$BL,44,0),"")
B37: CRYSTAL 3 | C37: =IFERROR(VLOOKUP($C$4,_d_herbs!$A:$BL,45,0),"")
B38: USES | C38: =IFERROR(VLOOKUP($C$4,_d_herbs!$A:$BL,46,0),"")
B39: POWERS | C39: =IFERROR(VLOOKUP($C$4,_d_herbs!$A:$BL,47,0),"")
B41: CRYSTAL 4 | C41: =IFERROR(VLOOKUP($C$4,_d_herbs!$A:$BL,48,0),"")
B42: USES | C42: =IFERROR(VLOOKUP($C$4,_d_herbs!$A:$BL,49,0),"")
B43: POWERS | C43: =IFERROR(VLOOKUP($C$4,_d_herbs!$A:$BL,50,0),"")
A46: 🫙 ASSOCIATED OILS
B47: OIL 1 | C47: =IFERROR(VLOOKUP($C$4,_d_herbs!$A:$BL,51,0),"")
B48: USES | C48: =IFERROR(VLOOKUP($C$4,_d_herbs!$A:$BL,52,0),"")
B49: SPIRITUAL | C49: =IFERROR(VLOOKUP($C$4,_d_herbs!$A:$BL,53,0),"")
B51: OIL 2 | C51: =IFERROR(VLOOKUP($C$4,_d_herbs!$A:$BL,55,0),"")
B52: USES | C52: =IFERROR(VLOOKUP($C$4,_d_herbs!$A:$BL,56,0),"")
B53: SPIRITUAL | C53: =IFERROR(VLOOKUP($C$4,_d_herbs!$A:$BL,57,0),"")
B55: OIL 3 | C55: =IFERROR(VLOOKUP($C$4,_d_herbs!$A:$BL,59,0),"")
B56: USES | C56: =IFERROR(VLOOKUP($C$4,_d_herbs!$A:$BL,60,0),"")
B57: SPIRITUAL | C57: =IFERROR(VLOOKUP($C$4,_d_herbs!$A:$BL,61,0),"")
A60: ᚛ ASSOCIATED RUNES
B61: RUNE 1 | C61: =IFERROR(IF(VLOOKUP($C$4,_d_herbs!$A:$BL,19,0)="","",VLOOKUP($C$4,_d_herbs!$A:$BL,19,0)&" ("&VLOOKUP($C$4,_d_herbs!$A:$BL,20,0)&")"),"")
B62: USES | C62: =IFERROR(VLOOKUP($C$4,_d_herbs!$A:$BL,21,0),"")
B63: POWERS | C63: =IFERROR(VLOOKUP($C$4,_d_herbs!$A:$BL,22,0),"")
B64: COLOR | C64: =IFERROR(VLOOKUP($C$4,_d_herbs!$A:$BL,23,0),"")
B66: RUNE 2 | C66: =IFERROR(IF(VLOOKUP($C$4,_d_herbs!$A:$BL,24,0)="","",VLOOKUP($C$4,_d_herbs!$A:$BL,24,0)&" ("&VLOOKUP($C$4,_d_herbs!$A:$BL,25,0)&")"),"")
B67: USES | C67: =IFERROR(VLOOKUP($C$4,_d_herbs!$A:$BL,26,0),"")
B68: POWERS | C68: =IFERROR(VLOOKUP($C$4,_d_herbs!$A:$BL,27,0),"")
B69: COLOR | C69: =IFERROR(VLOOKUP($C$4,_d_herbs!$A:$BL,28,0),"")
B71: RUNE 3 | C71: =IFERROR(IF(VLOOKUP($C$4,_d_herbs!$A:$BL,29,0)="","",VLOOKUP($C$4,_d_herbs!$A:$BL,29,0)&" ("&VLOOKUP($C$4,_d_herbs!$A:$BL,30,0)&")"),"")
B72: USES | C72: =IFERROR(VLOOKUP($C$4,_d_herbs!$A:$BL,31,0),"")
B73: POWERS | C73: =IFERROR(VLOOKUP($C$4,_d_herbs!$A:$BL,32,0),"")
B74: COLOR | C74: =IFERROR(VLOOKUP($C$4,_d_herbs!$A:$BL,33,0),"")
A77: 📜 DESCRIPTION, FOLKLORE & GEOLOGY
B78: DESCRIPTION | C78: =IFERROR(VLOOKUP($C$4,_d_herbs!$A:$BL,15,0),"")
B80: FOLK LORE | C80: =IFERROR(VLOOKUP($C$4,_d_herbs!$A:$BL,12,0),"")
B82: GEOLOGY | C82: =IFERROR(VLOOKUP($C$4,_d_herbs!$A:$BL,17,0),"")
A84: ⚠ WARNING
B85: WARNING | C85: =IFERROR(IF(VLOOKUP($C$4,_d_herbs!$A:$BL,18,0)="","No warnings recorded.",VLOOKUP($C$4,_d_herbs!$A:$BL,18,0)),"")
A87: The Greenman Magical Database ✦ 47 entries

Sheet ◈ Crystal Lookup
A2: ◈ The Greenman Crystal Oracle ◈
A4: ◈ Select Crystal: | C4: Apache Tears
A6: ◈ IDENTITY
A7: =IFERROR("◈ "&VLOOKUP($C$4,_d_crystals!$A:$AZ,1,0),"")
A8: =IFERROR("( "&VLOOKUP($C$4,_d_crystals!$A:$AZ,2,0)&" )","")
A9: =IFERROR("✦ "&VLOOKUP($C$4,_d_crystals!$A:$AZ,3,0),"")
A11: 🔮 MAGICAL USES
B12: MAGICAL USES | C12: =IFERROR(VLOOKUP($C$4,_d_crystals!$A:$AZ,4,0),"")
A14: 💫 SPIRITUAL & POWERS
B15: POWERS | C15: =IFERROR(VLOOKUP($C$4,_d_crystals!$A:$AZ,13,0),"")
B16: SPIRITUAL USES | C16: =IFERROR(VLOOKUP($C$4,_d_crystals!$A:$AZ,14,0),"")
A18: 📖 CORRESPONDENCES
B19: ASSOCIATION | C19: =IFERROR(VLOOKUP($C$4,_d_crystals!$A:$AZ,5,0),"")
B20: ELEMENT | C20: =IFERROR(VLOOKUP($C$4,_d_crystals!$A:$AZ,7,0),"")
B21: ENERGY | C21: =IFERROR(VLOOKUP($C$4,_d_crystals!$A:$AZ,8,0),"")
B22: DAY | C22: =IFERROR(VLOOKUP($C$4,_d_crystals!$A:$AZ,9,0),"")
B23: DEITY | C23: =IFERROR(VLOOKUP($C$4,_d_crystals!$A:$AZ,10,0),"")
B24: SABBAT | C24: =IFERROR(VLOOKUP($C$4,_d_crystals!$A:$AZ,11,0),"")
B25: PLANET | C25: =IFERROR(VLOOKUP($C$4,_d_crystals!$A:$AZ,6,0),"")
A27: 🌿 ASSOCIATED HERBS
B28: HERB 1 | C28: =IFERROR(VLOOKUP($C$4,_d_crystals!$A:$AZ,19,0),"")
B29: MAGICAL USES | C29: =IFERROR(VLOOKUP($C$4,_d_crystals!$A:$AZ,20,0),"")
B31: HERB 2 | C31: =IFERROR(VLOOKUP($C$4,_d_crystals!$A:$AZ,21,0),"")
B32: MAGICAL USES | C32: =IFERROR(VLOOKUP($C$4,_d_crystals!$A:$AZ,22,0),"")
B34: HERB 3 | C34: =IFERROR(VLOOKUP($C$4,_d_crystals!$A:$AZ,23,0),"")
B35: MAGICAL USES | C35: =IFERROR(VLOOKUP($C$4,_d_crystals!$A:$AZ,24,0),"")
B37: HERB 4 | C37: =IFERROR(VLOOKUP($C$4,_d_crystals!$A:$AZ,25,0),"")
B38: MAGICAL USES | C38: =IFERROR(VLOOKUP($C$4,_d_crystals!$A:$AZ,26,0),"")
A41: 🫙 ASSOCIATED OILS
B42: OIL 1 | C42: =IFERROR(VLOOKUP($C$4,_d_crystals!$A:$AZ,43,0),"")
B43: USES | C43: =IFERROR(VLOOKUP($C$4,_d_crystals!$A:$AZ,44,0),"")
B44: SPIRITUAL | C44: =IFERROR(VLOOKUP($C$4,_d_crystals!$A:$AZ,45,0),"")
B46: OIL 2 | C46: =IFERROR(VLOOKUP($C$4,_d_crystals!$A:$AZ,46,0),"")
B47: USES | C47: =IFERROR(VLOOKUP($C$4,_d_crystals!$A:$AZ,47,0),"")
B48: SPIRITUAL | C48: =IFERROR(VLOOKUP($C$4,_d_crystals!$A:$AZ,48,0),"")
B50: OIL 3 | C50: =IFERROR(VLOOKUP($C$4,_d_crystals!$A:$AZ,49,0),"")
B51: USES | C51: =IFERROR(VLOOKUP($C$4,_d_crystals!$A:$AZ,50,0),"")
B52: SPIRITUAL | C52: =IFERROR(VLOOKUP($C$4,_d_crystals!$A:$AZ,51,0),"")
A55: ᚛ ASSOCIATED RUNES
B56: RUNE 1 | C56: =IFERROR(IF(VLOOKUP($C$4,_d_crystals!$A:$AZ,27,0)="","",VLOOKUP($C$4,_d_crystals!$A:$AZ,27,0)&" ("&VLOOKUP($C$4,_d_crystals!$A:$AZ,28,0)&")"),"")
B57: USES | C57: =IFERROR(VLOOKUP($C$4,_d_crystals!$A:$AZ,29,0),"")
B58: POWERS | C58: =IFERROR(VLOOKUP($C$4,_d_crystals!$A:$AZ,30,0),"")
B60: RUNE 2 | C60: =IFERROR(IF(VLOOKUP($C$4,_d_crystals!$A:$AZ,31,0)="","",VLOOKUP($C$4,_d_crystals!$A:$AZ,31,0)&" ("&VLOOKUP($C$4,_d_crystals!$A:$AZ,32,0)&")"),"")
B61: USES | C61: =IFERROR(VLOOKUP($C$4,_d_crystals!$A:$AZ,33,0),"")
B62: POWERS | C62: =IFERROR(VLOOKUP($C$4,_d_crystals!$A:$AZ,34,0),"")
B64: RUNE 3 | C64: =IFERROR(IF(VLOOKUP($C$4,_d_crystals!$A:$AZ,35,0)="","",VLOOKUP($C$4,_d_crystals!$A:$AZ,35,0)&" ("&VLOOKUP($C$4,_d_crystals!$A:$AZ,36,0)&")"),"")
B65: USES | C65: =IFERROR(VLOOKUP($C$4,_d_crystals!$A:$AZ,37,0),"")
B66: POWERS | C66: =IFERROR(VLOOKUP($C$4,_d_crystals!$A:$AZ,38,0),"")
A69: 📜 DESCRIPTION, FOLKLORE & GEOLOGY
B70: DESCRIPTION | C70: =IFERROR(VLOOKUP($C$4,_d_crystals!$A:$AZ,15,0),"")
B72: FOLK LORE | C72: =IFERROR(VLOOKUP($C$4,_d_crystals!$A:$AZ,12,0),"")
B74: GEOLOGY | C74: =IFERROR(VLOOKUP($C$4,_d_crystals!$A:$AZ,17,0),"")
A76: ⚠ WARNING
B77: WARNING | C77: =IFERROR(IF(VLOOKUP($C$4,_d_crystals!$A:$AZ,18,0)="","No warnings recorded.",VLOOKUP($C$4,_d_crystals!$A:$AZ,18,0)),"")
A79: The Greenman Magical Database ✦ 65 entries

Sheet 🫙 Oil Lookup
A2: 🫙 The Greenman Oil Oracle 🫙
A4: 🫙 Select Oil: | C4: Frankincense
A6: 🫙 IDENTITY
A7: =IFERROR("🫙 "&VLOOKUP($C$4,_d_oils!$A:$AR,1,0),"")
A8: =IFERROR("( "&VLOOKUP($C$4,_d_oils!$A:$AR,2,0)&" )","")
A9: =IFERROR("✦ "&VLOOKUP($C$4,_d_oils!$A:$AR,3,0),"")
A11: 🔮 MAGICAL USES
B12: MAGICAL USES | C12: =IFERROR(VLOOKUP($C$4,_d_oils!$A:$AR,4,0),"")
A14: 💫 SPIRITUAL & POWERS
B15: POWERS | C15: =IFERROR(VLOOKUP($C$4,_d_oils!$A:$AR,13,0),"")
B16: SPIRITUAL USES | C16: =IFERROR(VLOOKUP($C$4,_d_oils!$A:$AR,14,0),"")
A18: 📖 CORRESPONDENCES
B19: ASSOCIATION | C19: =IFERROR(VLOOKUP($C$4,_d_oils!$A:$AR,5,0),"")
B20: ELEMENT | C20: =IFERROR(VLOOKUP($C$4,_d_oils!$A:$AR,7,0),"")
B21: ENERGY | C21: =IFERROR(VLOOKUP($C$4,_d_oils!$A:$AR,8,0),"")
B22: DAY | C22: =IFERROR(VLOOKUP($C$4,_d_oils!$A:$AR,9,0),"")
B23: DEITY | C23: =IFERROR(VLOOKUP($C$4,_d_oils!$A:$AR,10,0),"")
B24: SABBAT | C24: =IFERROR(VLOOKUP($C$4,_d_oils!$A:$AR,11,0),"")
B25: PLANET | C25: =IFERROR(VLOOKUP($C$4,_d_oils!$A:$AR,6,0),"")
A27: 🌿 ASSOCIATED HERBS
B28: HERB 1 | C28: =IFERROR(VLOOKUP($C$4,_d_oils!$A:$AR,19,0),"")
B29: MAGICAL USES | C29: =IFERROR(VLOOKUP($C$4,_d_oils!$A:$AR,20,0),"")
B31: HERB 2 | C31: =IFERROR(VLOOKUP($C$4,_d_oils!$A:$AR,21,0),"")
B32: MAGICAL USES | C32: =IFERROR(VLOOKUP($C$4,_d_oils!$A:$AR,22,0),"")
B34: HERB 3 | C34: =IFERROR(VLOOKUP($C$4,_d_oils!$A:$AR,23,0),"")
B35: MAGICAL USES | C35: =IFERROR(VLOOKUP($C$4,_d_oils!$A:$AR,24,0),"")
B37: HERB 4 | C37: =IFERROR(VLOOKUP($C$4,_d_oils!$A:$AR,25,0),"")
B38: MAGICAL USES | C38: =IFERROR(VLOOKUP($C$4,_d_oils!$A:$AR,26,0),"")
A41: ◈ ASSOCIATED CRYSTALS
B42: CRYSTAL 1 | C42: =IFERROR(VLOOKUP($C$4,_d_oils!$A:$AR,27,0),"")
B43: POWERS | C43: =IFERROR(VLOOKUP($C$4,_d_oils!$A:$AR,28,0),"")
B45: CRYSTAL 2 | C45: =IFERROR(VLOOKUP($C$4,_d_oils!$A:$AR,29,0),"")
B46: POWERS | C46: =IFERROR(VLOOKUP($C$4,_d_oils!$A:$AR,30,0),"")
B48: CRYSTAL 3 | C48: =IFERROR(VLOOKUP($C$4,_d_oils!$A:$AR,31,0),"")
B49: POWERS | C49: =IFERROR(VLOOKUP($C$4,_d_oils!$A:$AR,32,0),"")
B51: CRYSTAL 4 | C51: =IFERROR(VLOOKUP($C$4,_d_oils!$A:$AR,33,0),"")
B52: POWERS | C52: =IFERROR(VLOOKUP($C$4,_d_oils!$A:$AR,34,0),"")
A55: ᚛ ASSOCIATED RUNES
B56: RUNE 1 | C56: =IFERROR(IF(VLOOKUP($C$4,_d_oils!$A:$AR,35,0)="","",VLOOKUP($C$4,_d_oils!$A:$AR,35,0)&" ("&VLOOKUP($C$4,_d_oils!$A:$AR,36,0)&")"),"")
B57: USES | C57: =IFERROR(VLOOKUP($C$4,_d_oils!$A:$AR,37,0),"")
B59: RUNE 2 | C59: =IFERROR(IF(VLOOKUP($C$4,_d_oils!$A:$AR,38,0)="","",VLOOKUP($C$4,_d_oils!$A:$AR,38,0)&" ("&VLOOKUP($C$4,_d_oils!$A:$AR,39,0)&")"),"")
B60: USES | C60: =IFERROR(VLOOKUP($C$4,_d_oils!$A:$AR,40,0),"")
B62: RUNE 3 | C62: =IFERROR(IF(VLOOKUP($C$4,_d_oils!$A:$AR,41,0)="","",VLOOKUP($C$4,_d_oils!$A:$AR,41,0)&" ("&VLOOKUP($C$4,_d_oils!$A:$AR,42,0)&")"),"")
B63: USES | C63: =IFERROR(VLOOKUP($C$4,_d_oils!$A:$AR,43,0),"")
A66: 📜 DESCRIPTION, FOLKLORE & GEOLOGY
B67: DESCRIPTION | C67: =IFERROR(VLOOKUP($C$4,_d_oils!$A:$AR,15,0),"")
B69: FOLK LORE | C69: =IFERROR(VLOOKUP($C$4,_d_oils!$A:$AR,12,0),"")
B71: GEOLOGY | C71: =IFERROR(VLOOKUP($C$4,_d_oils!$A:$AR,17,0),"")
A73: ⚠ WARNING
B74: WARNING | C74: =IFERROR(IF(VLOOKUP($C$4,_d_oils!$A:$AR,18,0)="","No warnings recorded.",VLOOKUP($C$4,_d_oils!$A:$AR,18,0)),"")
A76: The Greenman Magical Database ✦ 29 entries

Sheet ᚛ Rune Lookup
A2: ᚛ The Greenman Runic Oracle ᚛
A4: ᚛ Select Rune: | C4: KAUNO
A6: ᚛ IDENTITY
A7: =IFERROR(VLOOKUP($C$4,_d_runes!$A:$BA,1,0)&" ᚛ "&VLOOKUP($C$4,_d_runes!$A:$BA,3,0),"")
A8: =IFERROR(VLOOKUP($C$4,_d_runes!$A:$BA,2,0),"")
A9: =IFERROR("Pronunciation: "&VLOOKUP($C$4,_d_runes!$A:$BA,4,0)&" · Number: "&VLOOKUP($C$4,_d_runes!$A:$BA,16,0),"")
A11: 🔮 MAGICAL USES
B12: MAGICAL USES | C12: =IFERROR(VLOOKUP($C$4,_d_runes!$A:$BA,5,0),"")
A14: 💫 SPIRITUAL & POWERS
B15: POWERS | C15: =IFERROR(VLOOKUP($C$4,_d_runes!$A:$BA,14,0),"")
B16: SPIRITUAL USES | C16: =IFERROR(VLOOKUP($C$4,_d_runes!$A:$BB,54,0),"")
A18: 📖 CORRESPONDENCES
B19: ASSOCIATION | C19: =IFERROR(VLOOKUP($C$4,_d_runes!$A:$BA,6,0),"")
B20: ELEMENT | C20: =IFERROR(VLOOKUP($C$4,_d_runes!$A:$BA,8,0),"")
B21: ENERGY | C21: =IFERROR(VLOOKUP($C$4,_d_runes!$A:$BA,9,0),"")
B22: DAY | C22: =IFERROR(VLOOKUP($C$4,_d_runes!$A:$BA,10,0),"")
B23: DEITY | C23: =IFERROR(VLOOKUP($C$4,_d_runes!$A:$BA,11,0),"")
B24: SABBAT | C24: =IFERROR(VLOOKUP($C$4,_d_runes!$A:$BA,12,0),"")
B25: PLANET | C25: =IFERROR(VLOOKUP($C$4,_d_runes!$A:$BA,7,0),"")
B26: COLOR | C26: =IFERROR(VLOOKUP($C$4,_d_runes!$A:$BA,17,0),"")
B27: TREE | C27: =IFERROR(VLOOKUP($C$4,_d_runes!$A:$BA,18,0),"")
A29: 🌿 ASSOCIATED HERBS
B30: HERB 1 | C30: =IFERROR(VLOOKUP($C$4,_d_runes!$A:$BA,21,0),"")
B31: MAGICAL USES | C31: =IFERROR(VLOOKUP($C$4,_d_runes!$A:$BA,22,0),"")
B33: HERB 2 | C33: =IFERROR(VLOOKUP($C$4,_d_runes!$A:$BA,23,0),"")
B34: MAGICAL USES | C34: =IFERROR(VLOOKUP($C$4,_d_runes!$A:$BA,24,0),"")
B36: HERB 3 | C36: =IFERROR(VLOOKUP($C$4,_d_runes!$A:$BA,25,0),"")
B37: MAGICAL USES | C37: =IFERROR(VLOOKUP($C$4,_d_runes!$A:$BA,26,0),"")
B39: HERB 4 | C39: =IFERROR(VLOOKUP($C$4,_d_runes!$A:$BA,27,0),"")
B40: MAGICAL USES | C40: =IFERROR(VLOOKUP($C$4,_d_runes!$A:$BA,28,0),"")
A43: ◈ ASSOCIATED CRYSTALS
B44: CRYSTAL 1 | C44: =IFERROR(VLOOKUP($C$4,_d_runes!$A:$BA,33,0),"")
B45: POWERS | C45: =IFERROR(VLOOKUP($C$4,_d_runes!$A:$BA,34,0),"")
B47: CRYSTAL 2 | C47: =IFERROR(VLOOKUP($C$4,_d_runes!$A:$BA,35,0),"")
B48: POWERS | C48: =IFERROR(VLOOKUP($C$4,_d_runes!$A:$BA,36,0),"")
B50: CRYSTAL 3 | C50: =IFERROR(VLOOKUP($C$4,_d_runes!$A:$BA,37,0),"")
B51: POWERS | C51: =IFERROR(VLOOKUP($C$4,_d_runes!$A:$BA,38,0),"")
B53: CRYSTAL 4 | C53: =IFERROR(VLOOKUP($C$4,_d_runes!$A:$BA,39,0),"")
B54: POWERS | C54: =IFERROR(VLOOKUP($C$4,_d_runes!$A:$BA,40,0),"")
A57: 🫙 ASSOCIATED OILS
B58: OIL 1 | C58: =IFERROR(VLOOKUP($C$4,_d_runes!$A:$BA,45,0),"")
B59: USES | C59: =IFERROR(VLOOKUP($C$4,_d_runes!$A:$BA,46,0),"")
B61: OIL 2 | C61: =IFERROR(VLOOKUP($C$4,_d_runes!$A:$BA,47,0),"")
B62: USES | C62: =IFERROR(VLOOKUP($C$4,_d_runes!$A:$BA,48,0),"")
B64: OIL 3 | C64: =IFERROR(VLOOKUP($C$4,_d_runes!$A:$BA,49,0),"")
B65: USES | C65: =IFERROR(VLOOKUP($C$4,_d_runes!$A:$BA,50,0),"")
A68: 📜 DESCRIPTION, FOLKLORE & GEOLOGY
B69: DESCRIPTION | C69: =IFERROR(VLOOKUP($C$4,_d_runes!$A:$BA,15,0),"")
B71: FOLK LORE | C71: =IFERROR(VLOOKUP($C$4,_d_runes!$A:$BA,13,0),"")
A74: The Greenman Magical Database ✦ 24 entries

Sheet ☽ Deity Lookup
A2: ☽ The Greenman Deity Oracle ☽
A4: ☽ Select Deity: | C4: AMBERELLA
A6: ☽ IDENTITY
A7: =IFERROR("☽ "&VLOOKUP($C$4,_d_deities!$A:$BD,1,0)&" ☽","")
A8: =IFERROR(VLOOKUP($C$4,_d_deities!$A:$BD,2,0)&" · "&VLOOKUP($C$4,_d_deities!$A:$BD,3,0)&" · "&VLOOKUP($C$4,_d_deities!$A:$BD,7,0),"")
A10: 📖 DESCRIPTION
B11: DESCRIPTION | C11: =IFERROR(VLOOKUP($C$4,_d_deities!$A:$BD,10,0),"")
A13: 🔮 MAGICAL USES
B14: MAGICAL USES | C14: =IFERROR(VLOOKUP($C$4,_d_deities!$A:$BD,8,0),"")
A16: 🌿 GREEN ENERGY
B17: GREEN ENERGY | C17: =IFERROR(VLOOKUP($C$4,_d_deities!$A:$BD,12,0),"")
A19: 📖 ASSOCIATIONS
B20: ELEMENT | C20: =IFERROR(VLOOKUP($C$4,_d_deities!$A:$BD,4,0),"")
B21: PLANET | C21: =IFERROR(VLOOKUP($C$4,_d_deities!$A:$BD,5,0),"")
B22: SACRED DAY | C22: =IFERROR(VLOOKUP($C$4,_d_deities!$A:$BD,6,0),"")
B23: SEASON | C23: =IFERROR(VLOOKUP($C$4,_d_deities!$A:$BD,7,0),"")
B24: POLARITY | C24: =IFERROR(VLOOKUP($C$4,_d_deities!$A:$BD,3,0),"")
B25: TYPE | C25: =IFERROR(VLOOKUP($C$4,_d_deities!$A:$BD,2,0),"")
A27: 🌿 ASSOCIATED HERBS
B28: HERB 1 | C28: =IFERROR(VLOOKUP($C$4,_d_deities!$A:$BD,13,0),"")
B29: MAGICAL USES | C29: =IFERROR(VLOOKUP($C$4,_d_deities!$A:$BD,14,0),"")
B31: HERB 2 | C31: =IFERROR(VLOOKUP($C$4,_d_deities!$A:$BD,15,0),"")
B32: MAGICAL USES | C32: =IFERROR(VLOOKUP($C$4,_d_deities!$A:$BD,16,0),"")
B34: HERB 3 | C34: =IFERROR(VLOOKUP($C$4,_d_deities!$A:$BD,17,0),"")
B35: MAGICAL USES | C35: =IFERROR(VLOOKUP($C$4,_d_deities!$A:$BD,18,0),"")
B37: HERB 4 | C37: =IFERROR(VLOOKUP($C$4,_d_deities!$A:$BD,19,0),"")
B38: MAGICAL USES | C38: =IFERROR(VLOOKUP($C$4,_d_deities!$A:$BD,20,0),"")
B40: HERB 5 | C40: =IFERROR(VLOOKUP($C$4,_d_deities!$A:$BD,21,0),"")
B41: MAGICAL USES | C41: =IFERROR(VLOOKUP($C$4,_d_deities!$A:$BD,22,0),"")
B43: HERB 6 | C43: =IFERROR(VLOOKUP($C$4,_d_deities!$A:$BD,23,0),"")
B44: MAGICAL USES | C44: =IFERROR(VLOOKUP($C$4,_d_deities!$A:$BD,24,0),"")
A47: ◈ ASSOCIATED CRYSTALS
B48: CRYSTALS | C48: =IFERROR(VLOOKUP($C$4,_d_deities!$A:$BD,53,0),"")
A50: 🫙 ASSOCIATED OILS
B51: OILS | C51: =IFERROR(VLOOKUP($C$4,_d_deities!$A:$BD,54,0),"")
A53: ᚛ ASSOCIATED RUNES
B54: RUNE 1 | C54: =IFERROR(IF(VLOOKUP($C$4,_d_deities!$A:$BD,41,0)="","",VLOOKUP($C$4,_d_deities!$A:$BD,41,0)&" ("&VLOOKUP($C$4,_d_deities!$A:$BD,42,0)&")"),"")
B55: MAGICAL USES | C55: =IFERROR(VLOOKUP($C$4,_d_deities!$A:$BD,43,0),"")
B57: RUNE 2 | C57: =IFERROR(IF(VLOOKUP($C$4,_d_deities!$A:$BD,44,0)="","",VLOOKUP($C$4,_d_deities!$A:$BD,44,0)&" ("&VLOOKUP($C$4,_d_deities!$A:$BD,45,0)&")"),"")
B58: MAGICAL USES | C58: =IFERROR(VLOOKUP($C$4,_d_deities!$A:$BD,46,0),"")
B60: RUNE 3 | C60: =IFERROR(IF(VLOOKUP($C$4,_d_deities!$A:$BD,47,0)="","",VLOOKUP($C$4,_d_deities!$A:$BD,47,0)&" ("&VLOOKUP($C$4,_d_deities!$A:$BD,48,0)&")"),"")
B61: MAGICAL USES | C61: =IFERROR(VLOOKUP($C$4,_d_deities!$A:$BD,49,0),"")
B63: RUNE 4 | C63: =IFERROR(IF(VLOOKUP($C$4,_d_deities!$A:$BD,50,0)="","",VLOOKUP($C$4,_d_deities!$A:$BD,50,0)&" ("&VLOOKUP($C$4,_d_deities!$A:$BD,51,0)&")"),"")
B64: MAGICAL USES | C64: =IFERROR(VLOOKUP($C$4,_d_deities!$A:$BD,52,0),"")
A67: ✨ FAMOUS MAGIC & MYTHOLOGY
B68: FAMOUS MAGIC | C68: =IFERROR(VLOOKUP($C$4,_d_deities!$A:$BD,11,0),"")
A70: The Greenman Magical Database ✦ 105 deities & entities

Sheet 📋 How To Use
A2: ✦ The Greenman Magical Database ✦
A4: 📋 How To Use
A6: Use the dropdown on each sheet to select an entry. All fields update instantly.
A8: Contents
A9: 🌿 Herb Lookup — 106 herbs · magical uses · correspondences · oils, crystals & runes linked
A11: ◈ Crystal Lookup — 65 crystals · powers & spiritual uses · linked herbs & runes · geology
A13: 🫙 Oil Lookup — 29 oils · magical & spiritual uses · linked herbs & crystals · folk lore
A15: ᚛ Rune Lookup — 24 runes · all correspondences · every linked herb, crystal & oil
A18: ✦ The Greenman Magical Database

Sheet Index
A1: The Greenman Magic — Workbook Index
A2: A complete magical reference database — herbs, crystals, oils, runes, deities, elements, candles, numerology, planetary hours
A3: Sheet Name | B3: Purpose | C3: Rows of Data | D3: Key Columns | E3: Notes
A4: Index | B4: Navigation overview of entire workbook | C4: — | D4: Sheet Name, Purpose, Key Columns, Notes | E4: You are here
A5: Spell Types | B5: 60 spell and charm types with moon phase guidance | C5: 60 | D5: Category, Spell/Charm Type, Moon Phase | E5: Anchor list for spell builder logic
A6: Herbs | B6: 106 herbs with full magical, folkloric and elemental profiles | C6: 106 | D6: Name, Ye Olde Name, Latin Name, Magical Uses, Association, Planet, Element, Energy, Day, Deity, Sabbat, Folk Lore, Powers, Spiritual Uses, Description, Oil Name, Geology, Warning | E6: Core ingredient database. Warnings highlighted in amber.
A7: Crystals | B7: 65 crystals with magical properties, deity links and spiritual uses | C7: 65 | D7: Name, Ye Olde Name, Latin Name, Magical Uses, Association, Planet, Element, Energy, Day, Deity, Sabbat, Folk Lore, Powers, Spiritual Uses, Description, Oil Name, Geology, Warning | E7: Shares column structure with Herbs
A8: Oils | B8: 29 magical oils with planetary, deity and sabbat correspondences | C8: 29 | D8: Name, Ye Olde Name, Latin Name, Magical Uses, Association, Planet, Element, Energy, Day, Deity, Sabbat, Folklore, Powers, Spiritual Uses, Description, Oil Name, Geology, Warning | E8: Selected separately in spell construction
A9: Runes | B9: 24 runes with full runic profile, associated herbs and crystals | C9: 24 | D9: Name, Ye Olde Name, Letter, Pronunciation, Magical Uses, Association, Planet, Element, Energy, Day, Deity, Sabbat, Folk Lore, Powers, Description, Runic Number, Color, Tree, Associated Herbs, Associated Crystals | E9: Cross-reference columns link to herbs and crystals
A10: Deities | B10: 87 deities with magical profile, green energy and sacred associations | C10: 87 | D10: Name/Entity, Type, Polarity, Element, Planet, Sacred Day, Season, Magical Uses, Associated Herbs, Description, Famous Magic, Green Energy | E10: Master deity reference
A11: Elements | B11: 4 classical elements with direction, gender, energy and colours | C11: 4 | D11: Element, Gender, Direction, Energy, Colors | E11: Reference for elemental herb filtering
A12: Candles | B12: 13 candle colours with magical purpose and intention | C12: 13 | D12: Color, Magical Purpose | E12: Match candle colour to spell intention
A13: Numerology | B13: 9 numerological numbers with planetary and elemental links | C13: 9 | D13: Number, Planet, Element, Letters, Energies | E13: Links numbers to planets and elements
A14: Planets | B14: 168 planetary hour entries — ruling planet by day and hour | C14: 168 | D14: Day, Description, Planet | E14: Full 7-day planetary hour table from sunrise

Sheet Spell Types
A1: Category | B1: Spell/Charm Type | C1: Moon Phase | D1: Element | E1: Planet | F1: Sacred Day | G1: Candle Colour | H1: Elemental Direction | I1: Elemental Energy | J1: Elemental Colors | K1: Numerology Number | L1: Numerology Energies | M1: Herb Count | N1: Matching Herbs | O1: Herb Count Total | P1: Matching Crystals | Q1: Crystal Count | R1: Matching Oils | S1: Oil Count | T1: Matching Runes | U1: Rune Count | V1: Matching Deities | W1: Deity Count | X1: Greenman Energy Mode | Y1: Secondary Energy Hint | Z1: Recommended Spell Method | AA1: Jar Allowed | AB1: Smoke and Flame Allowed | AC1: Charm Bag Allowed | AD1: Wording Focus | AE1: Instruction Notes | AF1: Primary Placement | AG1: Other Placements
A2: Over 18 🔞 | B2: Aphrodisiac | C2: Waxing | D2: Fire | E2: Mars | F2: Tuesday | G2: Red | H2: South | I2: Projective | J2: Red, gold, crimson, orange, white | K2: 9 | L2: Aggression, conflict, dominance | M2: 1, 3 or 7 | N2: ACORN, BLACKBERRY LEAVES, CALAMUS ROOT, CARAWAY, CLOVER RED, GINGER ROOT, HIBISCUS, LADIES MANTLE, MUSTARD SEED WHITE, VIOLET LEAVES | O2: 10 | P2: Carnelian, Garnet, Lodestone, Red Jasper, Ruby, Unakite | Q2: 6 | R2: Vanilla, Ylang Ylang, Patchouli | S2: 3 | T2: FEHU, URUZ, GEBO, BERKANAN | U2: 4 | V2: AESCULAPUS, ALL GODDESSES, AMBERELLA, APHRODITE, ARADIA, ASTARTE, ATTIS, BALDUR & HATHOR, BONA DEA, CEBELE, CUPID, CYBELE, EROS, HATHOR, HECATE, JANA, JUPITER, KWAI-YIN, KWAN-YIN AND BUDDHA, LUNA | W2: 29 | X2: Over 18 | Y2: Draw | Z2: All Three / User Choice | AA2: Yes | AB2: Yes | AC2: Yes | AD2: Adult / serious working: let the user choose Jar, Smoke and Flame, or Charm after reading the method notes. | AE2: App should pull this row's Greenman Energy Mode from the main item sheets. Use Secondary Energy Hint only if a serious/adult spell still needs a Draw/Hold/Release/Open/Transform flavour. | AF2: Carry it close on your person | AG2: Gift to the intended | Place where it can be seen
A3: Attraction, Love & Relationships | B3: Attraction | C3: Waxing | D3: Water | E3: Venus | F3: Friday | G3: Pink | H3: West | I3: Receptive | J3: Blue, turquoise, green, grey, indigo, black | K3: 6 | L3: Emotions, magnetism, gods/goddesses, cats | M3: 1, 3 or 7 | N3: GOLDENROD, GOLDENSEAL ROOT, JASMINE, ROSE BUDS RED, ROSE PETALS, RUE | O3: 6 | P3: quartz Rose, Moonstone, Carnelian, Lapis Lazuli | Q3: 4 | R3: Clove Bud, Cinnamon | S3: 2 | T3: FEHU, GEBO | U3: 2 | V3: AESCULAPUS, ALL GODDESSES, AMBERELLA, APHRODITE, ARADIA, ASTARTE, ATTIS, BALDUR & HATHOR, BONA DEA, CEBELE, CUPID, CYBELE, EROS, HATHOR, HECATE, JANA, JUPITER, KWAI-YIN, KWAN-YIN AND BUDDHA, LUNA | W3: 28 | X3: Draw | Y3: Draw | Z3: Spell Jar | AA3: Yes | AB3: Maybe | AC3: Yes | AD3: Draw, grow, sweeten, settle or carry relationship energy. | AE3: App should pull this row's Greenman Energy Mode from the main item sheets. Use Secondary Energy Hint only if a serious/adult spell still needs a Draw/Hold/Release/Open/Transform flavour. | AF3: Carry it close on your person | AG3: Gift to the intended | Place where it can be seen | Hang it in the home
A4: Attraction, Love & Relationships | B4: Exploring feelings | C4: Waxing | D4: Water | E4: Moon | F4: Monday | G4: Blue | H4: West | I4: Receptive | J4: Blue, turquoise, green, grey, indigo, black | K4: 2 | L4: Duality, balance, couples, partnerships | M4: 1, 3 or 7 | N4: LAVENDER FLOWERS, CHAMOMILE, VIOLET LEAVES, LEMON BALM, ROSE PETALS, YARROW, HEARTSEASE | O4: 7 | P4: Moonstone, Amethyst, Rhodocrosite, Lepidolite | Q4: 4 | R4: Lavender, Rose, Melissa, Geranium | S4: 4 | T4: LAGUZ, PERTH, MANNAZ, ANSUZ | U4: 4 | V4: SELENE, LUNA, PERSEPHONE, ISIS, ODIN, MERCURY, SATURN, PLUTO | W4: 8 | X4: Open / Reveal | Y4: Open / Reveal | Z4: Spell Jar | AA4: Yes | AB4: Maybe | AC4: Yes | AD4: Draw, grow, sweeten, settle or carry relationship energy. | AE4: App should pull this row's Greenman Energy Mode from the main item sheets. Use Secondary Energy Hint only if a serious/adult spell still needs a Draw/Hold/Release/Open/Transform flavour. | AF4: Carry it close on your person | AG4: Place where it can be seen | Hang it in the home
A5: Over 18 🔞 | B5: Fertility | C5: Waxing | D5: Earth | E5: Moon | F5: Monday | G5: Green | H5: North | I5: Receptive | J5: Black, green, yellow, brown | K5: 2 | L5: Duality, balance, couples, partnerships | M5: 1, 3 or 7 | N5: ACORN, ANISE, BASIL, BENZOIN, BLACK TEA, BLACKBERRY LEAVES, CARAWAY, CHAMOMILE, CINNAMON STICKS, CLOVER, CLOVER RED, CLOVES, COLTSFOOT, COMFREY, DILL, FENNEL (SEED), GARLIC POWDER, GOLDENSEAL ROOT, JASMINE, LADIES MANTLE, LAVENDER FLOWERS, LEMON BALM, LINSEED, MUSTARD SEED WHITE, NUTMEG POWDER, OAK MOSS, OAKBARK RED, PARSLEY, PEPPERMINT, PINE NUT, RUE, SAGE, THYME, VIOLET LEAVES, VIOLET | O5: 35 | P5: agate Botswana , agate Moss , Amazonite, Aventurine, Calcite, chrysophase, Citrine, Goldstone, Jade (jadeite), Lodestone, Pyrite (Fool's Gold), Rhodocrosite, Ruby, Sapphire, Serpentine, Topaz, Tourmalinee Black , Yellow Aventurine | Q5: 18 | R5: Bergamot, Cedarwood, Clove Bud, Geranium, Honeysuckle, Marjoram, Melissa, Neroli, Orange Bitter, Pine, Vanilla, Cinnamon, Ginger, Patchouli | S5: 14 | T5: FEHU, URUZ, WUNJO, JERA, SOWILO, BERKANAN, INGWAZ, OTHILA, DAGAZ | U5: 9 | V5: ALL GODDESSES, ALL LUNAR GODDESSES, ALLAT, AMATERASU, ARADIA, ARIANRHOD, ASTARTE, ATTIS, BAAL, BALDUR & HATHOR, BONA DEA, CERES, CERRIDWEN, CRONOS, CUPRA, EROS, FILDIAS, GAIA, GOD AND GODDESS IN BALANCE, GREAT GODDESS. MANASA | W5: 34 | X5: Over 18 | Y5: Draw | Z5: All Three / User Choice | AA5: Yes | AB5: Yes | AC5: Yes | AD5: Adult / serious working: let the user choose Jar, Smoke and Flame, or Charm after reading the method notes. | AE5: App should pull this row's Greenman Energy Mode from the main item sheets. Use Secondary Energy Hint only if a serious/adult spell still needs a Draw/Hold/Release/Open/Transform flavour. | AF5: Carry it close on your person | AG5: Bury in the earth | Place at a shrine or altar
A6: Attraction, Love & Relationships | B6: Fidelity | C6: Waxing | D6: Earth | E6: Venus | F6: Friday | G6: Pink | H6: North | I6: Receptive | J6: Black, green, yellow, brown | K6: 6 | L6: Emotions, magnetism, gods/goddesses, cats | M6: 1, 3 or 7 | N6: BASIL, CARAWAY, CLOVER, CLOVER RED, COMFREY, HIBISCUS, ORRIS ROOT POWDER, ROSEMARY, VIOLET LEAVES, VIOLET | O6: 10 | P6: Emerald, Lodestone, quartz Rose | Q6: 3 | R6: Lavender, Rose, Ylang Ylang | S6: 3 | T6: EHWAZ | U6: 1 | V6: VENUS, APHRODITE, HATHOR, FRIGG, FREY, JUPITER, ODIN | W6: 7 | X6: Hold | Y6: Hold | Z6: Spell Jar | AA6: Yes | AB6: Maybe | AC6: Yes | AD6: Draw, grow, sweeten, settle or carry relationship energy. | AE6: App should pull this row's Greenman Energy Mode from the main item sheets. Use Secondary Energy Hint only if a serious/adult spell still needs a Draw/Hold/Release/Open/Transform flavour. | AF6: Keep it hidden and safe | AG6: Hang it in the home | Bury in the earth
A7: Attraction, Love & Relationships | B7: Love | C7: Waxing | D7: Water | E7: Venus | F7: Friday | G7: Pink | H7: West | I7: Receptive | J7: Blue, turquoise, green, grey, indigo, black | K7: 6 | L7: Emotions, magnetism, gods/goddesses, cats | M7: 1, 3 or 7 | N7: ANISE, APPLE BLOSSOM, APPLEWOOD CHIPS, BASIL, BAY LAUREL, BENZOIN, BLACK TEA, BLACKBERRY LEAVES, CALAMUS ROOT, CARAWAY, CEDARWOOD (HIMALAYAN), CHAMOMILE, CHRYSANTHEMUM, CINNAMON STICKS, CLOVER, CLOVER RED, CLOVES, COLTSFOOT, COMFREY, DILL, DRAGON'S BLOOD, ELDERFLOWER, FENNEL (SEED), FRANKINCENSE, GARDENIA FRUIT, GINGER ROOT, GOLDENROD, HEARTSEASE, HIBISCUS, HOREHOUND, HYSSOP, JASMINE, JUNIPER BERRIES, LADIES MANTLE, LAVENDER FLOWERS, LEMON BALM, LEMON VERBENA, LEMONGRASS, LINDEN, MEADOW SWEET, HONESTY, MULLEIN, MUSTARD SEED WHITE, MYRRH GUM, NUTMEG POWDER, OAKBARK RED, SWEET MYRRH, OREGANO, ORRIS ROOT POWDER, PARSLEY, PENNYROYAL, PEPPERMINT, PINE NUT, RASPBERRY LEAF, ROSE BUDS PINK, ROSE BUDS RED, ROSE HIP, ROSE PETALS, ROSEMARY, RUE, SAGE, SANDALWOOD RED, SANDALWOOD WHITE, THYME, VALERIAN ROOT, VIOLET LEAVES, VIOLET | O7: 67 | P7: agate Blue Lace , Amethyst, Apache Tears, Calcite, Carnelian, Chrysocolla, Quartz Clear , Copper flakes, Emerald, Flourite, Hematite, Howlite, Jet, Lapis Lazuli, Lepidolite, Lodestone, Moonstone, Peridot, quartz Rose , quartz smokey , quartz snow , Red Jasper, Rhodonite, Ruby, Sapphire, Seraphinite, Serpentine, Sodalite, Tanzanite, Tiger Eye gold, Unakite, Yellow Aventurine | Q7: 32 | R7: Apple, Bergamot, Clove Bud, Frankincense, Geranium, Juniper, Lavender, Lemon, Lemon Grass, Marjoram, Melissa, Neroli, Orange Bitter, Pine, Rose, Rosemary, Thyme, Vanilla, Ylang Ylang, Cinnamon, Ginger, Patchouli, Sandalwood In. | S7: 23 | T7: FEHU, ANSUZ, RAIDO, GEBO, WUNJO, PERTH, SOWILO, TIWAZ, EHWAZ, INGWAZ, OTHILA | U7: 11 | V7: AESCULAPUS, ALL, ALL GODDESSES, ALL LUNAR GODDESSES, ALLAT, AMATERASU, AMBERELLA, APHRODITE, ARADIA, ARES, ARIANRHOD, ARTEMIS, ASTARTE, ATTIS, BAAL, BACCHUS, BALDOR, BALDUR & HATHOR, BEFANA, BONA DEA | W7: 89 | X7: Draw | Y7: Draw | Z7: Spell Jar | AA7: Yes | AB7: Maybe | AC7: Yes | AD7: Draw, grow, sweeten, settle or carry relationship energy. | AE7: App should pull this row's Greenman Energy Mode from the main item sheets. Use Secondary Energy Hint only if a serious/adult spell still needs a Draw/Hold/Release/Open/Transform flavour. | AF7: Place where it can be seen | AG7: Gift to the intended | Bury in the earth | Hang it in the home
A8: Attraction, Love & Relationships | B8: Love rituals | C8: Waxing | D8: Water | E8: Venus | F8: Friday | G8: Pink | H8: West | I8: Receptive | J8: Blue, turquoise, green, grey, indigo, black | K8: 6 | L8: Emotions, magnetism, gods/goddesses, cats | M8: 1, 3 or 7 | N8: ANISE, APPLE BLOSSOM, APPLEWOOD CHIPS, BASIL, BAY LAUREL, BENZOIN, BLACK TEA, BLACKBERRY LEAVES, CALAMUS ROOT, CARAWAY, CEDARWOOD (HIMALAYAN), CHAMOMILE, CHRYSANTHEMUM, CINNAMON STICKS, CLOVER, CLOVER RED, CLOVES, COLTSFOOT, COMFREY, DILL, DRAGON'S BLOOD, ELDERFLOWER, FENNEL (SEED), FRANKINCENSE, GARDENIA FRUIT, GINGER ROOT, GOLDENROD, HEARTSEASE, HIBISCUS, HOREHOUND, HYSSOP, JASMINE, JUNIPER BERRIES, LADIES MANTLE, LAVENDER FLOWERS, LEMON BALM, LEMON VERBENA, LEMONGRASS, LINDEN, MEADOW SWEET, HONESTY, MULLEIN, MUSTARD SEED WHITE, MYRRH GUM, NUTMEG POWDER, OAKBARK RED, SWEET MYRRH, OREGANO, ORRIS ROOT POWDER, PARSLEY, PENNYROYAL, PEPPERMINT, PINE NUT, RASPBERRY LEAF, ROSE BUDS PINK, ROSE BUDS RED, ROSE HIP, ROSE PETALS, ROSEMARY, RUE, SAGE, SANDALWOOD RED, SANDALWOOD WHITE, THYME, VALERIAN ROOT, VIOLET LEAVES, VIOLET, WHEAT GRAINS | O8: 68 | P8: agate Blue Lace , Amethyst, Apache Tears, Calcite, Carnelian, Chrysocolla, Quartz Clear , Copper flakes, Emerald, Flourite, Hematite, Howlite, Jet, Lapis Lazuli, Lepidolite, Lodestone, Moonstone, Peridot, quartz Rose , quartz smokey , quartz snow , Red Jasper, Rhodonite, Ruby, Sapphire, Seraphinite, Serpentine, Sodalite, Tanzanite, Tiger Eye gold, Unakite, Yellow Aventurine | Q8: 32 | R8: Apple, Bergamot, Clove Bud, Frankincense, Geranium, Juniper, Lavender, Lemon, Lemon Grass, Marjoram, Melissa, Neroli, Orange Bitter, Pine, Rose, Rosemary, Thyme, Vanilla, Ylang Ylang, Cinnamon, Ginger, Patchouli, Sandalwood In. | S8: 23 | T8: FEHU, ANSUZ, RAIDO, GEBO, WUNJO, PERTH, SOWILO, TIWAZ, EHWAZ, INGWAZ, OTHILA | U8: 11 | V8: AESCULAPUS, ALL, ALL GODDESSES, ALL LUNAR GODDESSES, ALLAT, AMATERASU, AMBERELLA, APHRODITE, ARADIA, ARES, ARIANRHOD, ARTEMIS, ASTARTE, ATTIS, BAAL, BACCHUS, BALDOR, BALDUR & HATHOR, BEFANA, BONA DEA | W8: 89 | X8: Draw | Y8: Draw | Z8: Spell Jar | AA8: Yes | AB8: Maybe | AC8: Yes | AD8: Draw, grow, sweeten, settle or carry relationship energy. | AE8: App should pull this row's Greenman Energy Mode from the main item sheets. Use Secondary Energy Hint only if a serious/adult spell still needs a Draw/Hold/Release/Open/Transform flavour. | AF8: Place at a shrine or altar | AG8: Place where it can be seen | Gift to the intended | Carry it close on your person
A9: Attraction, Love & Relationships | B9: Love spells | C9: Waxing | D9: Water | E9: Venus | F9: Friday | G9: Pink | H9: West | I9: Receptive | J9: Blue, turquoise, green, grey, indigo, black | K9: 6 | L9: Emotions, magnetism, gods/goddesses, cats | M9: 1, 3 or 7 | N9: ROSE PETALS, LAVENDER FLOWERS, JASMINE, ROSE BUDS RED, ORRIS ROOT POWDER, VIOLET LEAVES, YARROW | O9: 7 | P9: quartz Rose, Moonstone, Emerald, Lapis Lazuli | Q9: 4 | R9: Rose, Ylang Ylang, Neroli, Lavender | S9: 4 | T9: FEHU, GEBO, WUNJO, BERKANAN | U9: 4 | V9: APHRODITE, VENUS, HATHOR, FREYJA, EROS, FREY, CUPID, DIANA | W9: 8 | X9: Draw | Y9: Draw | Z9: Spell Jar | AA9: Yes | AB9: Maybe | AC9: Yes | AD9: Draw, grow, sweeten, settle or carry relationship energy. | AE9: App should pull this row's Greenman Energy Mode from the main item sheets. Use Secondary Energy Hint only if a serious/adult spell still needs a Draw/Hold/Release/Open/Transform flavour. | AF9: Place where it can be seen | AG9: Gift to the intended | Bury in the earth
A10: Protection, Banishing & Warding | B10: Anti-theft | C10: Waning | D10: Earth | E10: Saturn | F10: Saturday | G10: Black | H10: North | I10: Receptive | J10: Black, green, yellow, brown | K10: 8 | L10: Material aspects, travel, protection, discipline | M10: 1, 3 or 7 | N10: BASIL, CARAWAY, COMFREY, DILL, JUNIPER BERRIES, ROSEMARY | O10: 6 | P10: Jet, Obsidian, Onyx, Tiger Eye gold | Q10: 4 | R10: Frankincense, Cedarwood, Rosemary | S10: 3 | T10: FEHU, GEBO | U10: 2 | V10: GREAT GODDESS. MANASA, PLUTO | W10: 2 | X10: Hold | Y10: Hold | Z10: Spell Jar | AA10: Yes | AB10: Maybe | AC10: Yes | AD10: Hold boundaries, guard, ward and keep protection steady. | AE10: App should pull this row's Greenman Energy Mode from the main item sheets. Use Secondary Energy Hint only if a serious/adult spell still needs a Draw/Hold/Release/Open/Transform flavour. | AF10: Keep it hidden and safe | AG10: Hang it in the home | Bury in the earth
A11: Over 18 🔞 | B11: Banishing | C11: Waning/Dark | D11: Fire | E11: Mars | F11: Tuesday | G11: Black | H11: South | I11: Projective | J11: Red, gold, crimson, orange, white | K11: 9 | L11: Aggression, conflict, dominance | M11: 1, 3 or 7 | N11: AGRIMONY, ANISE, BASIL, BAY LAUREL, CAMPHOR SYNTHETIC, CEDARWOOD (HIMALAYAN), CHIVE, CLOVER, CLOVER RED, CLOVES, COMFREY, DEVILS CLAW ROOT, DRAGON'S BLOOD, FRANKINCENSE, GARLIC POWDER, HOREHOUND, HYSSOP, JUNIPER BERRIES, LAVENDER FLOWERS, LEMON VERBENA, LEMONGRASS, MULLEIN, MUSTARD SEED WHITE, MYRRH GUM, OAKLEAF, PENNYROYAL, PEPPERMINT, PINE NUT, ROSE HIP, ROSEMARY, RUE, SAGE, SANDALWOOD RED, SANDALWOOD WHITE, SEA SALT, THYME, VALERIAN ROOT, VERVAIN, VIOLET, WITCH HAZEL LEAVES, BLACK SALT, WORMWOOD | O11: 42 | P11: Aquamarine, Hematite, Lepidolite, Obsidian, quartz smokey , quartz snow , Serpentine, Tourmalinee Black | Q11: 8 | R11: Fir Needle, Frankincense, Lemon Grass, Sandalwood w.i., Tea Tree, Ylang Ylang | S11: 6 | T11: THURISAZ, HAGALAZ, IHWAZ, ALGIZ, LAGUZ | U11: 5 | V11: AMBERELLA, ARTEMIS, BALDOR, CUPRA, DIANA, FLIDAIS, HECATE, HEL, HYGIA, ISIS, JUTERNA, KWAN-YIN AND BUDDHA, LUNA, MARS, SHIVA, THOR, ZEUS | W11: 17 | X11: Over 18 | Y11: Release | Z11: All Three / User Choice | AA11: Yes | AB11: Yes | AC11: Yes | AD11: Adult / serious working: let the user choose Jar, Smoke and Flame, or Charm after reading the method notes. | AE11: App should pull this row's Greenman Energy Mode from the main item sheets. Use Secondary Energy Hint only if a serious/adult spell still needs a Draw/Hold/Release/Open/Transform flavour. | AF11: Bury in the earth | AG11: Burn and release, no remains | Leave in running water
A12: Over 18 🔞 | B12: Exorcism | C12: Waning/Dark | D12: Fire | E12: Mars | F12: Tuesday | G12: Red | H12: South | I12: Projective | J12: Red, gold, crimson, orange, white | K12: 9 | L12: Aggression, conflict, dominance | M12: 1, 3 or 7 | N12: AGRIMONY, ANISE, BASIL, BAY LAUREL, CAMPHOR SYNTHETIC, CEDARWOOD (HIMALAYAN), CHIVE, CLOVER, CLOVER RED, CLOVES, COMFREY, DEVILS CLAW ROOT, DRAGON'S BLOOD, FRANKINCENSE, GARLIC POWDER, HOREHOUND, HYSSOP, JUNIPER BERRIES, LAVENDER FLOWERS, LEMON VERBENA, LEMONGRASS, MULLEIN, MUSTARD SEED WHITE, MYRRH GUM, OAKLEAF, PENNYROYAL, PEPPERMINT, PINE NUT, ROSE HIP, ROSEMARY, RUE, SAGE, SANDALWOOD RED, SANDALWOOD WHITE, SEA SALT, THYME, VALERIAN ROOT, VERVAIN, VIOLET, WITCH HAZEL LEAVES, BLACK SALT | O12: 41 | P12: Aquamarine, Hematite, Lepidolite, Obsidian, quartz smokey , quartz snow , Serpentine, Tourmalinee Black | Q12: 8 | R12: Fir Needle, Frankincense, Lemon Grass, Sandalwood w.i., Tea Tree, Ylang Ylang | S12: 6 | T12: THURISAZ, HAGALAZ, IHWAZ, ALGIZ, LAGUZ | U12: 5 | V12: AMBERELLA, ARTEMIS, BALDOR, CUPRA, DIANA, FLIDAIS, HECATE, HEL, HYGIA, ISIS, JUTERNA, KWAN-YIN AND BUDDHA, LUNA, MARS, SHIVA, THOR, ZEUS | W12: 17 | X12: Over 18 | Y12: Release | Z12: All Three / User Choice | AA12: Yes | AB12: Yes | AC12: Yes | AD12: Adult / serious working: let the user choose Jar, Smoke and Flame, or Charm after reading the method notes. | AE12: App should pull this row's Greenman Energy Mode from the main item sheets. Use Secondary Energy Hint only if a serious/adult spell still needs a Draw/Hold/Release/Open/Transform flavour. | AF12: Burn and release, no remains | AG12: Bury in the earth
A13: Protection, Banishing & Warding | B13: Nightmare prevention | C13: Waning | D13: Air | E13: Moon | F13: Monday | G13: White | H13: East | I13: Projective | J13: Yellow, white, crimson | K13: 2 | L13: Duality, balance, couples, partnerships | M13: 1, 3 or 7 | N13: ANISE, CHAMOMILE, DILL, GARLIC POWDER, JASMINE, LAVENDER FLOWERS, MULLEIN, OAKBARK RED, PEPPERMINT, ROSEMARY, THYME, VALERIAN ROOT | O13: 12 | P13: Lepidolite, Red Jasper, Ruby | Q13: 3 | R13: Cedarwood | S13: 1 | T13: LAGUZ | U13: 1 | V13: SELENE, LUNA, HECATE, DIANA, ODIN, SATURN, MERCURY | W13: 7 | X13: Hold | Y13: Hold | Z13: Spell Jar | AA13: Yes | AB13: Maybe | AC13: Yes | AD13: Hold boundaries, guard, ward and keep protection steady. | AE13: App should pull this row's Greenman Energy Mode from the main item sheets. Use Secondary Energy Hint only if a serious/adult spell still needs a Draw/Hold/Release/Open/Transform flavour. | AF13: Keep it hidden and safe | AG13: Hang it in the home | Carry it close on your person
A14: Protection, Banishing & Warding | B14: Protection | C14: Waning | D14: Fire | E14: Mars | F14: Tuesday | G14: Red | H14: South | I14: Projective | J14: Red, gold, crimson, orange, white | K14: 9 | L14: Aggression, conflict, dominance | M14: 1, 3 or 7 | N14: ACORN, AGRIMONY, ANISE, BASIL, BAY LAUREL, BLACKBERRY LEAVES, CARAWAY, CEDARWOOD (HIMALAYAN), CINNAMON STICKS, CLOVER, CLOVES, DEVILS CLAW ROOT, DILL, ELDERFLOWER, FENNEL (SEED), GARLIC POWDER, HOREHOUND, HYSSOP, JUNIPER BERRIES, LADIES MANTLE, LAVENDER FLOWERS, MULLEIN, MUSTARD SEED WHITE, MYRRH GUM, NETTLE, OAKBARK RED, SWEET MYRRH, OREGANO, PARSLEY, PENNYROYAL, PEPPERMINT, PINE NUT, RASPBERRY LEAF, ROSE BUDS RED, ROSEMARY, RUE, SANDALWOOD RED, SANDALWOOD WHITE, ST JOHN'S WORT, THYME, VALERIAN ROOT, VERVAIN, VIOLET LEAVES, VIOLET, WILLOW BARK, WINTERGREEN, WITCH HAZEL BARK, WITCH HAZEL LEAVES, BLACK SALT | O14: 49 | P14: Amethyst, Apache Tears, Aquamarine, Aventurine, chrysophase, Quartz Clear , Emerald, Garnet, Hematite, Iolite, Jade (jadeite), Jet, Labradorite, Lapis Lazuli, Malachite, Obsidian, obsidian snowflake, Onyx, Opal pink, Peridot, quartz rutilated , quartz smokey , Red Jasper, Ruby, Sodalite, Tiger Eye gold, Tourmalinee Black , Turquoise, Amber | Q14: 29 | R14: Cedarwood, Clove Bud, Fir Needle, Frankincense, Geranium, Honeysuckle, Juniper, Marjoram, Pine, Rose, Rosemary, Sandalwood w.i., Tea Tree, Ylang Ylang, Cinnamon, Sandalwood In. | S14: 16 | T14: URUZ, THURISAZ, HAGALAZ, ISA, IHWAZ, ALGIZ, TIWAZ, OTHILA | U14: 8 | V14: AMBERELLA, ARTEMIS, BALDOR, CUPRA, DIANA, FLIDAIS, HECATE, HYGIA, ISIS, KWAN-YIN AND BUDDHA, LUNA, MARS, SECH, SHIVA, THE GREAT MOTHER, THOR, ZEUS, FRIGG, HOLDA | W14: 19 | X14: Hold | Y14: Hold | Z14: Spell Jar | AA14: Yes | AB14: Maybe | AC14: Yes | AD14: Hold boundaries, guard, ward and keep protection steady. | AE14: App should pull this row's Greenman Energy Mode from the main item sheets. Use Secondary Energy Hint only if a serious/adult spell still needs a Draw/Hold/Release/Open/Transform flavour. | AF14: Carry it close on your person | AG14: Hang it in the home | Keep it hidden and safe | Bury in the earth
A15: Over 18 🔞 | B15: Protection (hexes/evil) | C15: Waning | D15: Fire | E15: Mars | F15: Tuesday | G15: Black | H15: South | I15: Projective | J15: Red, gold, crimson, orange, white | K15: 9 | L15: Aggression, conflict, dominance | M15: 1, 3 or 7 | N15: AGRIMONY, ANISE, BASIL, BAY LAUREL, CHIVE, CLOVES, COLTSFOOT, DILL, DRAGON'S BLOOD, ELDERFLOWER, FENNEL (SEED), GINGER ROOT, HOREHOUND, LAVENDER FLOWERS, LEMONGRASS, LINSEED, MULLEIN, MUSTARD SEED WHITE, MYRRH GUM, OAKLEAF, SWEET MYRRH, PENNYROYAL, PEPPERMINT, PINE NUT, ROSEMARY, RUE, SAGE, SANDALWOOD RED, TANSY, VERVAIN, BLACK SALT | O15: 31 | P15: Obsidian, obsidian snowflake, Tourmalinee Black , Turquoise, Amber | Q15: 5 | R15: Frankincense | S15: 1 | T15: THURISAZ, KAUNO, HAGALAZ, ALGIZ | U15: 4 | V15: AESCULAPUS, AMATERASU, AMBERELLA, ARTEMIS, ASTARTE, BALDOR, BONA DEA, BRIGID, CUPRA, DIANA, DIONYSUS, FLIDAIS, HECATE, HYGIA, ISIS, JUTERNA, KWAI-YIN, KWAN-YIN AND BUDDHA, LUNA, MARS | W15: 28 | X15: Over 18 | Y15: Hold | Z15: All Three / User Choice | AA15: Yes | AB15: Yes | AC15: Yes | AD15: Adult / serious working: let the user choose Jar, Smoke and Flame, or Charm after reading the method notes. | AE15: App should pull this row's Greenman Energy Mode from the main item sheets. Use Secondary Energy Hint only if a serious/adult spell still needs a Draw/Hold/Release/Open/Transform flavour. | AF15: Carry it close on your person | AG15: Hang it in the home | Keep it hidden and safe
A16: Protection, Banishing & Warding | B16: Warding | C16: Waning | D16: Earth | E16: Saturn | F16: Saturday | G16: Black | H16: North | I16: Receptive | J16: Black, green, yellow, brown | K16: 8 | L16: Material aspects, travel, protection, discipline | M16: 1, 3 or 7 | N16: AGRIMONY, ANISE, BASIL, BAY LAUREL, CHIVE, CLOVES, COLTSFOOT, DILL, DRAGON'S BLOOD, ELDERFLOWER, FENNEL (SEED), GINGER ROOT, HOREHOUND, LAVENDER FLOWERS, LEMONGRASS, LINSEED, MULLEIN, MUSTARD SEED WHITE, MYRRH GUM, OAKLEAF, SWEET MYRRH, PENNYROYAL, PEPPERMINT, PINE NUT, ROSEMARY, RUE, SAGE, SANDALWOOD RED, TANSY, VERVAIN, BLACK SALT | O16: 31 | P16: Obsidian, obsidian snowflake, Tourmalinee Black , Turquoise, Amber | Q16: 5 | R16: Frankincense | S16: 1 | T16: THURISAZ, KAUNO, HAGALAZ, ALGIZ | U16: 4 | V16: AESCULAPUS, AMATERASU, AMBERELLA, ARTEMIS, ASTARTE, BALDOR, BONA DEA, BRIGID, CUPRA, DIANA, DIONYSUS, FLIDAIS, HECATE, HYGIA, ISIS, JUTERNA, KWAI-YIN, KWAN-YIN AND BUDDHA, LUNA, MARS | W16: 28 | X16: Hold | Y16: Hold | Z16: Spell Jar | AA16: Yes | AB16: Maybe | AC16: Yes | AD16: Hold boundaries, guard, ward and keep protection steady. | AE16: App should pull this row's Greenman Energy Mode from the main item sheets. Use Secondary Energy Hint only if a serious/adult spell still needs a Draw/Hold/Release/Open/Transform flavour. | AF16: Hang it in the home | AG16: Keep it hidden and safe | Bury in the earth
A17: Divination, Dreams & Psychic Work | B17: Clairvoyance | C17: Waxing/Full | D17: Air | E17: Mercury | F17: Wednesday | G17: Yellow | H17: East | I17: Projective | J17: Yellow, white, crimson | K17: 5 | L17: Communication, fulfilment | M17: 1 or 3 | N17: ANISE, BASIL, BAY LAUREL, CAMPHOR SYNTHETIC, CINNAMON STICKS, CLEAVERS, CLOVES, COLTSFOOT, GARLIC POWDER, GINGER ROOT, JUNIPER BERRIES, LAVENDER FLOWERS, LEMON BALM, NUTMEG POWDER, OAKBARK RED, OREGANO, PARSLEY, PEPPERMINT, ROSE BUDS RED, ROSEMARY, SAGE, SANDALWOOD RED, SANDALWOOD WHITE, SEA SALT, THYME | O17: 25 | P17: agate Blue Lace , agate Moss , Amazonite, Amethyst, Apache Tears, Aquamarine, Calcite, Carnelian, Quartz Clear , Emerald, Flourite, Fuchsite, Howlite, Iolite, Jet, Kyanite, Labradorite, Lapis Lazuli, Moonstone, obsidian snowflake, Opal pink, Peridot, Petrified Wood, quartz rutilated , Sapphire, Seraphinite, Serpentine, Sodalite, Sugilite, Sunstone, Tanzanite, Tiger Eye gold, Topaz, Turquoise, Yellow Aventurine | Q17: 35 | R17: Bergamot, Honeysuckle, Lavender, Neroli, Peppermint, Sandalwood In. | S17: 6 | T17: ANSUZ, PERTH, SOWILO, TIWAZ, LAGUZ, DAGAZ | U17: 6 | V17: ALL GODDESSES, ALL LUNAR GODDESSES, ARADIA, ARES, ARIANRHOD, BEFANA, CUPRA, DIANA, GOD AND GODDESS IN BALANCE, HECATE, KWAI-YIN, LOKI, LUNA, MOTHER GODESS, NUIT, RA, SELENE, SOL, SOPHIA, TITIANA | W17: 26 | X17: Open / Reveal | Y17: Open / Reveal | Z17: Smoke and Flame | AA17: Maybe | AB17: Yes | AC17: Yes | AD17: Open sight, smoke, dream roads and hidden knowledge. | AE17: App should pull this row's Greenman Energy Mode from the main item sheets. Use Secondary Energy Hint only if a serious/adult spell still needs a Draw/Hold/Release/Open/Transform flavour. | AF17: Carry it close on your person | AG17: Place at a shrine or altar | Place in a tree
A18: Divination, Dreams & Psychic Work | B18: Divination | C18: Full | D18: Air | E18: Mercury | F18: Wednesday | G18: Yellow | H18: East | I18: Projective | J18: Yellow, white, crimson | K18: 5 | L18: Communication, fulfilment | M18: 1 or 3 | N18: ANISE, BASIL, BAY LAUREL, BLACK TEA, CINNAMON STICKS, CLOVES, COLTSFOOT, COMFREY, FENNEL (SEED), GARLIC POWDER, GOLDENROD, JASMINE, LAVENDER FLOWERS, NUTMEG POWDER, ORRIS ROOT POWDER, PARSLEY, PEPPERMINT, PINE NUT, ROSE BUDS PINK, ROSE BUDS RED, SAGE, SANDALWOOD WHITE, THYME, VIOLET LEAVES, VIOLET, YARROW | O18: 26 | P18: Emerald, Jet, Moonstone, obsidian snowflake, Onyx, Sapphire, Tanzanite | Q18: 7 | R18: Lemon Grass, Orange Bitter | S18: 2 | T18: ANSUZ, PERTH, LAGUZ | U18: 3 | V18: ALL GODDESSES, ALL LUNAR GODDESSES, ARADIA, ARES, ARIANRHOD, BEFANA, CUPRA, DIANA, GOD AND GODDESS IN BALANCE, HECATE, KWAI-YIN, LUNA, MOTHER GODESS, NUIT, RA, SELENE, SOL, SOPHIA, TITIANA, VAC | W18: 28 | X18: Open / Reveal | Y18: Open / Reveal | Z18: Smoke and Flame | AA18: Maybe | AB18: Yes | AC18: Yes | AD18: Open sight, smoke, dream roads and hidden knowledge. | AE18: App should pull this row's Greenman Energy Mode from the main item sheets. Use Secondary Energy Hint only if a serious/adult spell still needs a Draw/Hold/Release/Open/Transform flavour. | AF18: Place at a shrine or altar | AG18: Carry it close on your person | Place in a tree
A19: Divination, Dreams & Psychic Work | B19: Prophetic dreams | C19: Full | D19: Water | E19: Moon | F19: Monday | G19: Blue | H19: West | I19: Receptive | J19: Blue, turquoise, green, grey, indigo, black | K19: 2 | L19: Duality, balance, couples, partnerships | M19: 1 or 3 | N19: BASIL, BAY LAUREL, CAMPHOR SYNTHETIC, CARAWAY, COLTSFOOT, EYEBRIGHT, GOLDENROD, JASMINE, LAVENDER FLOWERS, LEMON VERBENA, MARIGOLD, MULLEIN, NUTMEG POWDER, OAKBARK RED, ORRIS ROOT POWDER, PEPPERMINT, ROSE BUDS RED, ROSE PETALS, ROSEMARY, THYME, VIOLET LEAVES, VIOLET | O19: 22 | P19: Amethyst, Opal pink, Peridot, Pyrite (Fool's Gold), Sugilite | Q19: 5 | R19: Lavender, Sandalwood In., Juniper, Melissa | S19: 4 | T19: ANSUZ, PERTH, SOWILO, MANNAZ | U19: 4 | V19: ALL GODDESSES, ALL LUNAR GODDESSES, ARADIA, ARES, ARIANRHOD, BEFANA, CUPRA, DIANA, GOD AND GODDESS IN BALANCE, HECATE, JUTERNA, KWAI-YIN, LUNA, MOTHER GODESS, NUIT, RA, SELENE, SOL, SOPHIA, TITIANA | W19: 25 | X19: Open / Reveal | Y19: Open / Reveal | Z19: Smoke and Flame | AA19: Maybe | AB19: Yes | AC19: Yes | AD19: Open sight, smoke, dream roads and hidden knowledge. | AE19: App should pull this row's Greenman Energy Mode from the main item sheets. Use Secondary Energy Hint only if a serious/adult spell still needs a Draw/Hold/Release/Open/Transform flavour. | AF19: Keep it hidden and safe | AG19: Place at a shrine or altar | Carry it close on your person
A20: Divination, Dreams & Psychic Work | B20: Negating dreams | C20: Waning | D20: Water | E20: Moon | F20: Monday | G20: Blue | H20: West | I20: Receptive | J20: Blue, turquoise, green, grey, indigo, black | K20: 2 | L20: Duality, balance, couples, partnerships | M20: 1 or 3 | N20: ANISE, CHAMOMILE, DILL, GARLIC POWDER, JASMINE, LAVENDER FLOWERS, MULLEIN, OAKBARK RED, PEPPERMINT, ROSEMARY, THYME, VALERIAN ROOT | O20: 12 | P20: Lepidolite, Red Jasper, Ruby | Q20: 3 | R20: Cedarwood | S20: 1 | T20: LAGUZ | U20: 1 | V20: SELENE, LUNA, HECATE, DIANA, ODIN, SATURN, MERCURY | W20: 7 | X20: Release | Y20: Release | Z20: Smoke and Flame | AA20: Maybe | AB20: Yes | AC20: Yes | AD20: Open sight, smoke, dream roads and hidden knowledge. | AE20: App should pull this row's Greenman Energy Mode from the main item sheets. Use Secondary Energy Hint only if a serious/adult spell still needs a Draw/Hold/Release/Open/Transform flavour. | AF20: Bury in the earth | AG20: Leave in running water | Burn and release, no remains
A21: Divination, Dreams & Psychic Work | B21: Subconscious work | C21: Dark | D21: Water | E21: Moon | F21: Monday | G21: Black | H21: West | I21: Receptive | J21: Blue, turquoise, green, grey, indigo, black | K21: 2 | L21: Duality, balance, couples, partnerships | M21: 1 or 3 | N21: BASIL, BAY LAUREL, CAMPHOR SYNTHETIC, CARAWAY, COLTSFOOT, EYEBRIGHT, GOLDENROD, JASMINE, LAVENDER FLOWERS, LEMON VERBENA, MARIGOLD, MULLEIN, NUTMEG POWDER, OAKBARK RED, ORRIS ROOT POWDER, PEPPERMINT, ROSE BUDS RED, ROSE PETALS, ROSEMARY, THYME, VIOLET LEAVES, VIOLET | O21: 22 | P21: Amethyst, Opal pink, Peridot, Pyrite (Fool's Gold), Sugilite | Q21: 5 | R21: Sandalwood In., Frankincense, Lavender, Patchouli | S21: 4 | T21: ANSUZ, PERTH, SOWILO, MANNAZ | U21: 4 | V21: ALL GODDESSES, ALL LUNAR GODDESSES, ARADIA, ARES, ARIANRHOD, BEFANA, CUPRA, DIANA, GOD AND GODDESS IN BALANCE, HECATE, JUTERNA, KWAI-YIN, LUNA, MOTHER GODESS, NUIT, RA, SELENE, SOL, SOPHIA, TITIANA | W21: 25 | X21: Open / Reveal | Y21: Open / Reveal | Z21: Smoke and Flame | AA21: Maybe | AB21: Yes | AC21: Yes | AD21: Open sight, smoke, dream roads and hidden knowledge. | AE21: App should pull this row's Greenman Energy Mode from the main item sheets. Use Secondary Energy Hint only if a serious/adult spell still needs a Draw/Hold/Release/Open/Transform flavour. | AF21: Carry it close on your person | AG21: Place at a shrine or altar | Keep it hidden and safe
A22: Cleansing, Purification & Healing | B22: Cleansing | C22: Waning | D22: Water | E22: Moon | F22: Monday | G22: White | H22: West | I22: Receptive | J22: Blue, turquoise, green, grey, indigo, black | K22: 2 | L22: Duality, balance, couples, partnerships | M22: 1, 3 or 7 | N22: AGRIMONY, ANISE, BASIL, BAY LAUREL, CAMPHOR SYNTHETIC, CEDARWOOD (HIMALAYAN), CHIVE, CLOVER, CLOVER RED, CLOVES, COMFREY, DEVILS CLAW ROOT, DRAGON'S BLOOD, FRANKINCENSE, GARLIC POWDER, HOREHOUND, HYSSOP, JUNIPER BERRIES, LAVENDER FLOWERS, LEMON VERBENA, LEMONGRASS, MULLEIN, MUSTARD SEED WHITE, MYRRH GUM, OAKLEAF, PENNYROYAL, PEPPERMINT, PINE NUT, ROSE HIP, ROSEMARY, RUE, SAGE, SANDALWOOD RED, SANDALWOOD WHITE, SEA SALT, THYME, VALERIAN ROOT, VERVAIN, VIOLET, WITCH HAZEL LEAVES, BLACK SALT, WORMWOOD | O22: 42 | P22: Aquamarine, Hematite, Lepidolite, Obsidian, quartz smokey , quartz snow , Serpentine, Tourmalinee Black | Q22: 8 | R22: Fir Needle, Frankincense, Lemon Grass, Sandalwood w.i., Tea Tree, Ylang Ylang | S22: 6 | T22: THURISAZ, HAGALAZ, IHWAZ, ALGIZ, LAGUZ | U22: 5 | V22: AMBERELLA, ARTEMIS, BALDOR, CUPRA, DIANA, FLIDAIS, HECATE, HEL, HYGIA, ISIS, JUTERNA, KWAN-YIN AND BUDDHA, LUNA, MARS, SHIVA, THOR, ZEUS | W22: 17 | X22: Release | Y22: Release | Z22: Smoke and Flame | AA22: Maybe | AB22: Yes | AC22: Yes | AD22: Clear, cleanse, restore or soothe depending on chosen spell. | AE22: App should pull this row's Greenman Energy Mode from the main item sheets. Use Secondary Energy Hint only if a serious/adult spell still needs a Draw/Hold/Release/Open/Transform flavour. | AF22: Burn and release, no remains | AG22: Bury in the earth | Leave in running water
A23: Cleansing, Purification & Healing | B23: Dispelling sickness | C23: Waning | D23: Fire | E23: Sun | F23: Sunday | G23: Orange | H23: South | I23: Projective | J23: Red, gold, crimson, orange, white | K23: 1 | L23: Developing the self, the All, wholeness, unity, beginnings | M23: 1, 3 or 7 | N23: AGRIMONY, ANISE, BASIL, BAY LAUREL, CHIVE, CLOVES, COLTSFOOT, DILL, DRAGON'S BLOOD, ELDERFLOWER, FENNEL (SEED), GINGER ROOT, HOREHOUND, LAVENDER FLOWERS, LEMONGRASS, LINSEED, MULLEIN, MUSTARD SEED WHITE, MYRRH GUM, OAKLEAF, SWEET MYRRH, PENNYROYAL, PEPPERMINT, PINE NUT, ROSEMARY, RUE, SAGE, SANDALWOOD RED, TANSY, VERVAIN, BLACK SALT | O23: 31 | P23: Obsidian, obsidian snowflake, Tourmalinee Black , Turquoise, Amber | Q23: 5 | R23: Frankincense | S23: 1 | T23: THURISAZ, KAUNO, HAGALAZ, ALGIZ | U23: 4 | V23: AESCULAPUS, AMATERASU, AMBERELLA, ARTEMIS, ASTARTE, BALDOR, BONA DEA, BRIGID, CUPRA, DIANA, DIONYSUS, FLIDAIS, HECATE, HYGIA, ISIS, JUTERNA, KWAI-YIN, KWAN-YIN AND BUDDHA, LUNA, MARS | W23: 28 | X23: Release | Y23: Release | Z23: Smoke and Flame | AA23: Maybe | AB23: Yes | AC23: Yes | AD23: Clear, cleanse, restore or soothe depending on chosen spell. | AE23: App should pull this row's Greenman Energy Mode from the main item sheets. Use Secondary Energy Hint only if a serious/adult spell still needs a Draw/Hold/Release/Open/Transform flavour. | AF23: Burn and release, no remains | AG23: Bury in the earth
A24: Cleansing, Purification & Healing | B24: Healing | C24: Waxing | D24: Water | E24: Moon | F24: Monday | G24: Blue | H24: West | I24: Receptive | J24: Blue, turquoise, green, grey, indigo, black | K24: 2 | L24: Duality, balance, couples, partnerships | M24: 1, 3 or 7 | N24: AGRIMONY, BAY LAUREL, BLACK TEA, CALAMUS ROOT, CAMPHOR SYNTHETIC, CINNAMON STICKS, CLEAVERS, COLTSFOOT, COMFREY, GARLIC POWDER, GOLDENSEAL ROOT, HOREHOUND, LAVENDER FLOWERS, LEMON BALM, LINSEED, MUSTARD SEED WHITE, MYRRH GUM, OAKBARK RED, OAKLEAF, SWEET MYRRH, PENNYROYAL, PEPPERMINT, PINE NUT, ROSE BUDS PINK, ROSE BUDS RED, ROSE PETALS, ROSEMARY, RUE, SAGE, SANDALWOOD RED, SANDALWOOD WHITE, ST JOHN'S WORT, THYME, VIOLET LEAVES, VIOLET, WORMWOOD | O24: 36 | P24: agate Blue Lace , agate Botswana , agate Moss , Bloodstone, Calcite, Chrysocolla, Citrine, Quartz Clear , Fuchsite, Howlite, Jade (jadeite), Kyanite, Lepidolite, Lodestone, Peridot, quartz rutilated , quartz snow , Rhodocrosite, Rhodonite, Seraphinite, Yellow Aventurine | Q24: 21 | R24: Fir Needle, Geranium, Juniper, Marjoram, Melissa, Peppermint, Pine, Rosemary, Tea Tree, Thyme, Ginger, Sandalwood In. | S24: 12 | T24: URUZ, KAUNO, NAUDIZ, IHWAZ, SOWILO, BERKANAN, LAGUZ | U24: 7 | V24: AESCULAPUS, AMATERASU, AMBERELLA, ASTARTE, BONA DEA, BRIGID, DIONYSUS, FLIDAIS, GAIA, HECATE, HYGIA, ISIS, JUTERNA, KWAI-YIN, KWAN-YIN AND BUDDHA, MARY MAGDALENE, MINERVA, PLUTO, SECH, SEKHMET | W24: 21 | X24: Hold | Y24: Hold | Z24: Smoke and Flame | AA24: Maybe | AB24: Yes | AC24: Yes | AD24: Clear, cleanse, restore or soothe depending on chosen spell. | AE24: App should pull this row's Greenman Energy Mode from the main item sheets. Use Secondary Energy Hint only if a serious/adult spell still needs a Draw/Hold/Release/Open/Transform flavour. | AF24: Carry it close on your person | AG24: Place at a shrine or altar | Hang it in the home
A25: Cleansing, Purification & Healing | B25: Purification | C25: Waning | D25: Fire | E25: Sun | F25: Sunday | G25: White | H25: South | I25: Projective | J25: Red, gold, crimson, orange, white | K25: 1 | L25: Developing the self, the All, wholeness, unity, beginnings | M25: 1, 3 or 7 | N25: AGRIMONY, ANISE, BASIL, BAY LAUREL, BENZOIN, BLACKBERRY LEAVES, CAMPHOR SYNTHETIC, CARAWAY, CEDARWOOD (HIMALAYAN), CHAMOMILE, CHRYSANTHEMUM, CINNAMON STICKS, CLEAVERS, CLOVER RED, CLOVES, DEVILS CLAW ROOT, DRAGON'S BLOOD, FENNEL (SEED), GARLIC POWDER, HYSSOP, JUNIPER BERRIES, LADIES MANTLE, LAVENDER FLOWERS, MYRRH GUM, MYRRH GUM POWDER, OAKLEAF, SWEET MYRRH, PARSLEY, PENNYROYAL, PEPPERMINT, PINE NUT, ROSE BUDS RED, ROSE HIP, ROSEMARY, RUE, SAGE, SANDALWOOD WHITE, SEA SALT, THYME, TONKA BEANS, VALERIAN ROOT, WITCH HAZEL LEAVES, BLACK SALT | O25: 43 | P25: Aquamarine, Quartz Clear , quartz snow , Seraphinite | Q25: 4 | R25: Cedarwood, Clove Bud, Fir Needle, Lavender, Lemon, Neroli, Peppermint, Pine, Rosemary, Tea Tree, Thyme, Cinnamon, Sandalwood In. | S25: 13 | T25: THURISAZ, ISA, HAGALAZ, ALGIZ | U25: 4 | V25: GAIA, HYGIA, JUTERNA, BALDUR | W25: 4 | X25: Release | Y25: Release | Z25: Smoke and Flame | AA25: Maybe | AB25: Yes | AC25: Yes | AD25: Clear, cleanse, restore or soothe depending on chosen spell. | AE25: App should pull this row's Greenman Energy Mode from the main item sheets. Use Secondary Energy Hint only if a serious/adult spell still needs a Draw/Hold/Release/Open/Transform flavour. | AF25: Burn and release, no remains | AG25: Bury in the earth | Leave in running water
A26: Power, Strength & Confidence | B26: Bolstering spells | C26: Waxing | D26: Fire | E26: Sun | F26: Sunday | G26: Gold | H26: South | I26: Projective | J26: Red, gold, crimson, orange, white | K26: 1 | L26: Developing the self, the All, wholeness, unity, beginnings | M26: 1 or 3 | N26: CALAMUS ROOT, DRAGON'S BLOOD, DRAGON'S BLOOD RESIN, GARLIC POWDER, GOLDENSEAL ROOT, JUNIPER BERRIES, LADIES MANTLE, LAVENDER FLOWERS, SWEET MYRRH, ROSE BUDS PINK, WORMWOOD | O26: 11 | P26: Ametrine, Aragonite, Calcite, Quartz Clear , Flourite, Garnet, Hematite, Iolite, Labradorite, Lapis Lazuli, Malachite, quartz rutilated , Sapphire, Seraphinite, Serpentine, Sugilite, Tourmalinee Black | Q26: 17 | R26: Apple | S26: 1 | T26: URUZ, THURISAZ | U26: 2 | V26: LOKI, SOPHIA, VAC, VAK, ODIN, VERDANDI | W26: 6 | X26: Hold | Y26: Hold | Z26: Charm Bag | AA26: Maybe | AB26: Maybe | AC26: Yes | AD26: Carry courage, strength, focus or confidence close to the body. | AE26: App should pull this row's Greenman Energy Mode from the main item sheets. Use Secondary Energy Hint only if a serious/adult spell still needs a Draw/Hold/Release/Open/Transform flavour. | AF26: Carry it close on your person | AG26: Place at a shrine or altar
A27: Power, Strength & Confidence | B27: Confidence | C27: Waxing | D27: Fire | E27: Sun | F27: Sunday | G27: Gold | H27: South | I27: Projective | J27: Red, gold, crimson, orange, white | K27: 1 | L27: Developing the self, the All, wholeness, unity, beginnings | M27: 1 or 3 | N27: ACORN, BASIL, CALAMUS ROOT, DILL, FENNEL (SEED), GARLIC POWDER, OAKBARK RED, ROSEMARY, THYME | O27: 9 | P27: Aragonite, Bloodstone, Carnelian, Flourite, Goldstone, Kyanite, Malachite, Rhodonite, Ruby, Sunstone, Tiger Eye gold, Topaz, Unakite, Yellow Aventurine, Amber | Q27: 15 | R27: Bergamot, Neroli, Thyme | S27: 3 | T27: FEHU, URUZ, WUNJO, NAUDIZ, TIWAZ | U27: 5 | V27: ALL, ALL GODDESSES, ALL LUNAR GODDESSES, AMATERASU, AMBERELLA, APHRODITE, ARES, ASTARTE, BALDUR & HATHOR, BUDDHA, CUPID, CUPRA, CYBELE, KWAN-YIN AND BUDDHA, LATONA, MAAT, MARS, MINERVA, MOTHER GODDESS, PARVATI | W27: 30 | X27: Hold | Y27: Hold | Z27: Charm Bag | AA27: Maybe | AB27: Maybe | AC27: Yes | AD27: Carry courage, strength, focus or confidence close to the body. | AE27: App should pull this row's Greenman Energy Mode from the main item sheets. Use Secondary Energy Hint only if a serious/adult spell still needs a Draw/Hold/Release/Open/Transform flavour. | AF27: Carry it close on your person | AG27: Place where it can be seen
A28: Power, Strength & Confidence | B28: Magical power | C28: Waxing/Full | D28: Fire | E28: Sun | F28: Sunday | G28: Gold | H28: South | I28: Projective | J28: Red, gold, crimson, orange, white | K28: 1 | L28: Developing the self, the All, wholeness, unity, beginnings | M28: 1 or 3 | N28: CALAMUS ROOT, DRAGON'S BLOOD, DRAGON'S BLOOD RESIN, GARLIC POWDER, GOLDENSEAL ROOT, JUNIPER BERRIES, LADIES MANTLE, LAVENDER FLOWERS, SWEET MYRRH, ROSE BUDS PINK, WORMWOOD | O28: 11 | P28: Ametrine, Aragonite, Calcite, Quartz Clear , Flourite, Garnet, Hematite, Iolite, Labradorite, Lapis Lazuli, Malachite, quartz rutilated , Sapphire, Seraphinite, Serpentine, Sugilite, Tourmalinee Black | Q28: 17 | R28: Apple | S28: 1 | T28: URUZ, THURISAZ | U28: 2 | V28: LOKI, SOPHIA, VAC, VAK, ODIN, VERDANDI | W28: 6 | X28: Hold | Y28: Hold | Z28: Charm Bag | AA28: Maybe | AB28: Maybe | AC28: Yes | AD28: Carry courage, strength, focus or confidence close to the body. | AE28: App should pull this row's Greenman Energy Mode from the main item sheets. Use Secondary Energy Hint only if a serious/adult spell still needs a Draw/Hold/Release/Open/Transform flavour. | AF28: Carry it close on your person | AG28: Place at a shrine or altar
A29: Power, Strength & Confidence | B29: Strength | C29: Waxing | D29: Fire | E29: Mars | F29: Tuesday | G29: Red | H29: South | I29: Projective | J29: Red, gold, crimson, orange, white | K29: 9 | L29: Aggression, conflict, dominance | M29: 1 or 3 | N29: ACORN, BASIL, BLACK TEA, FENNEL (SEED), GARLIC POWDER, MUSTARD SEED WHITE, OAKBARK RED, PINE NUT, ROSEMARY | O29: 9 | P29: agate Blue Lace , agate Botswana , agate Moss , Amazonite, Ametrine, Aragonite, Bloodstone, Carnelian, Chrysocolla, Citrine, Garnet, Goldstone, Hematite, Iolite, Labradorite, Lodestone, Obsidian, Onyx, Petrified Wood, quartz rutilated , quartz smokey , Ruby, Sodalite, Sunstone, Topaz | Q29: 25 | R29: Pine, Tea Tree, Ginger | S29: 3 | T29: URUZ, THURISAZ, HAGALAZ, NAUDIZ, IHWAZ, ALGIZ, TIWAZ | U29: 7 | V29: ALL, ALL GODDESSES, ALL LUNAR GODDESSES, AMATERASU, AMBERELLA, APHRODITE, ARES, ASTARTE, BALDUR & HATHOR, BUDDHA, CUPID, CUPRA, CYBELE, GAIA, HYGIA, KWAN-YIN AND BUDDHA, LATONA, MAAT, MARS, MINERVA | W29: 36 | X29: Hold | Y29: Hold | Z29: Charm Bag | AA29: Maybe | AB29: Maybe | AC29: Yes | AD29: Carry courage, strength, focus or confidence close to the body. | AE29: App should pull this row's Greenman Energy Mode from the main item sheets. Use Secondary Energy Hint only if a serious/adult spell still needs a Draw/Hold/Release/Open/Transform flavour. | AF29: Carry it close on your person | AG29: Place at a shrine or altar
A30: Power, Strength & Confidence | B30: Truth | C30: Waxing/Dark | D30: Air | E30: Mercury | F30: Wednesday | G30: Yellow | H30: East | I30: Projective | J30: Yellow, white, crimson | K30: 5 | L30: Communication, fulfilment | M30: 1 or 3 | N30: BASIL, BAY LAUREL, CAMPHOR SYNTHETIC, CARAWAY, COLTSFOOT, EYEBRIGHT, GOLDENROD, JASMINE, LAVENDER FLOWERS, LEMON VERBENA, MARIGOLD, MULLEIN, NUTMEG POWDER, OAKBARK RED, ORRIS ROOT POWDER, PEPPERMINT, ROSE BUDS RED, ROSE PETALS, ROSEMARY, THYME, VIOLET LEAVES, VIOLET | O30: 22 | P30: Amethyst, Opal pink, Peridot, Pyrite (Fool's Gold), Sugilite | Q30: 5 | R30: Frankincense, Bergamot, Peppermint, Rosemary | S30: 4 | T30: ANSUZ, PERTH, SOWILO, MANNAZ | U30: 4 | V30: ALL GODDESSES, ALL LUNAR GODDESSES, ARADIA, ARES, ARIANRHOD, BEFANA, CUPRA, DIANA, GOD AND GODDESS IN BALANCE, HECATE, JUTERNA, KWAI-YIN, LUNA, MOTHER GODESS, NUIT, RA, SELENE, SOL, SOPHIA, TITIANA | W30: 25 | X30: Open / Reveal | Y30: Open / Reveal | Z30: Charm Bag | AA30: Maybe | AB30: Maybe | AC30: Yes | AD30: Carry courage, strength, focus or confidence close to the body. | AE30: App should pull this row's Greenman Energy Mode from the main item sheets. Use Secondary Energy Hint only if a serious/adult spell still needs a Draw/Hold/Release/Open/Transform flavour. | AF30: Carry it close on your person | AG30: Place at a shrine or altar
A31: Prosperity, Wealth & Luck | B31: Fortune | C31: Waxing | D31: Earth | E31: Jupiter | F31: Thursday | G31: Green | H31: North | I31: Receptive | J31: Black, green, yellow, brown | K31: 3 | L31: Health, triple aspects, psychism | M31: 3 or 7 | N31: ACORN, AGRIMONY, ANISE, BASIL, CHAMOMILE, CINNAMON STICKS, CLOVES, COMFREY, GARLIC POWDER, LAVENDER FLOWERS, MUSTARD SEED WHITE, MYRRH GUM, PARSLEY, PENNYROYAL, PEPPERMINT, PINE NUT, ROSE BUDS RED, ROSEMARY, RUE, SANDALWOOD WHITE, SEA SALT, VIOLET LEAVES, VIOLET, BLACK SALT, WORMWOOD | O31: 25 | P31: Amazonite, Apache Tears, Aventurine, Bloodstone, chrysophase, Jade (jadeite), Lodestone, Malachite, Onyx, Opal pink, Pyrite (Fool's Gold) | Q31: 11 | R31: Frankincense, Neroli, Orange Bitter, Rose, Sandalwood In. | S31: 5 | T31: FEHU, RAIDO, WUNJO | U31: 3 | V31: ALL GODDESSES, ALL LUNAR GODDESSES, AMATERASU, AMBERELLA, APHRODITE, ARADIA, BAAL, BACCHUS, BALDOR, BALDUR & HATHOR, BEFANA, CUPID, DIONYSUS, ELECTRA, FATHER GOD, GOD AND GODDESS IN BALANCE, GREAT GODDESS. MANASA, JUPITER, KWAN-YIN AND BUDDHA, LUNA | W31: 36 | X31: Draw | Y31: Draw | Z31: Spell Jar | AA31: Yes | AB31: Maybe | AC31: Yes | AD31: Draw wealth, grow luck or move stagnant money energy. | AE31: App should pull this row's Greenman Energy Mode from the main item sheets. Use Secondary Energy Hint only if a serious/adult spell still needs a Draw/Hold/Release/Open/Transform flavour. | AF31: Place where it can be seen | AG31: Bury in the earth | Place in a tree
A32: Prosperity, Wealth & Luck | B32: Increasing wealth | C32: Waxing | D32: Earth | E32: Jupiter | F32: Thursday | G32: Green | H32: North | I32: Receptive | J32: Black, green, yellow, brown | K32: 3 | L32: Health, triple aspects, psychism | M32: 3 or 7 | N32: ACORN, ANISE, BASIL, BENZOIN, BLACK TEA, BLACKBERRY LEAVES, CARAWAY, CHAMOMILE, CINNAMON STICKS, CLOVER, CLOVER RED, CLOVES, COLTSFOOT, COMFREY, DILL, FENNEL (SEED), GARLIC POWDER, GOLDENSEAL ROOT, JASMINE, LADIES MANTLE, LAVENDER FLOWERS, LEMON BALM, LINSEED, MUSTARD SEED WHITE, NUTMEG POWDER, OAK MOSS, OAKBARK RED, PARSLEY, PEPPERMINT, PINE NUT, RUE, SAGE, THYME, VIOLET LEAVES, VIOLET | O32: 35 | P32: agate Botswana , agate Moss , Amazonite, Aventurine, Calcite, chrysophase, Citrine, Goldstone, Jade (jadeite), Lodestone, Pyrite (Fool's Gold), Rhodocrosite, Ruby, Sapphire, Serpentine, Topaz, Tourmalinee Black , Yellow Aventurine | Q32: 18 | R32: Bergamot, Cedarwood, Clove Bud, Geranium, Honeysuckle, Marjoram, Melissa, Neroli, Orange Bitter, Pine, Vanilla, Cinnamon, Ginger, Patchouli | S32: 14 | T32: FEHU, URUZ, WUNJO, JERA, SOWILO, BERKANAN, INGWAZ, OTHILA, DAGAZ | U32: 9 | V32: ALL GODDESSES, ALL LUNAR GODDESSES, ALLAT, AMATERASU, ARADIA, ARIANRHOD, ASTARTE, ATTIS, BAAL, BALDUR & HATHOR, BONA DEA, CERES, CERRIDWEN, CRONOS, CUPRA, EROS, FILDIAS, GAIA, GOD AND GODDESS IN BALANCE, GREAT GODDESS. MANASA | W32: 36 | X32: Draw | Y32: Draw | Z32: Spell Jar | AA32: Yes | AB32: Maybe | AC32: Yes | AD32: Draw wealth, grow luck or move stagnant money energy. | AE32: App should pull this row's Greenman Energy Mode from the main item sheets. Use Secondary Energy Hint only if a serious/adult spell still needs a Draw/Hold/Release/Open/Transform flavour. | AF32: Place where it can be seen | AG32: Hang it in the home | Bury in the earth
A33: Prosperity, Wealth & Luck | B33: Luck | C33: Waxing | D33: Earth | E33: Jupiter | F33: Thursday | G33: Green | H33: North | I33: Receptive | J33: Black, green, yellow, brown | K33: 3 | L33: Health, triple aspects, psychism | M33: 3 or 7 | N33: ACORN, AGRIMONY, ANISE, BASIL, CHAMOMILE, CINNAMON STICKS, CLOVES, COMFREY, GARLIC POWDER, LAVENDER FLOWERS, MUSTARD SEED WHITE, MYRRH GUM, PARSLEY, PENNYROYAL, PEPPERMINT, PINE NUT, ROSE BUDS RED, ROSEMARY, RUE, SANDALWOOD WHITE, SEA SALT, VIOLET LEAVES, VIOLET, BLACK SALT, WORMWOOD | O33: 25 | P33: Amazonite, Apache Tears, Aventurine, Bloodstone, chrysophase, Jade (jadeite), Lodestone, Malachite, Onyx, Opal pink, Pyrite (Fool's Gold) | Q33: 11 | R33: Frankincense, Neroli, Orange Bitter, Rose, Sandalwood In. | S33: 5 | T33: FEHU, RAIDO, WUNJO | U33: 3 | V33: ALL GODDESSES, ALL LUNAR GODDESSES, AMATERASU, AMBERELLA, APHRODITE, ARADIA, BAAL, BACCHUS, BALDOR, BALDUR & HATHOR, BEFANA, CUPID, DIONYSUS, ELECTRA, FATHER GOD, GOD AND GODDESS IN BALANCE, GREAT GODDESS. MANASA, JUPITER, KWAN-YIN AND BUDDHA, LUNA | W33: 36 | X33: Draw | Y33: Draw | Z33: Spell Jar | AA33: Yes | AB33: Maybe | AC33: Yes | AD33: Draw wealth, grow luck or move stagnant money energy. | AE33: App should pull this row's Greenman Energy Mode from the main item sheets. Use Secondary Energy Hint only if a serious/adult spell still needs a Draw/Hold/Release/Open/Transform flavour. | AF33: Carry it close on your person | AG33: Place where it can be seen | Place in a tree
A34: Prosperity, Wealth & Luck | B34: Prosperity | C34: Waxing | D34: Earth | E34: Jupiter | F34: Thursday | G34: Green | H34: North | I34: Receptive | J34: Black, green, yellow, brown | K34: 3 | L34: Health, triple aspects, psychism | M34: 3 or 7 | N34: ACORN, ANISE, BASIL, BENZOIN, BLACK TEA, BLACKBERRY LEAVES, CARAWAY, CHAMOMILE, CINNAMON STICKS, CLOVER, CLOVER RED, CLOVES, COLTSFOOT, COMFREY, DILL, FENNEL (SEED), GARLIC POWDER, GOLDENSEAL ROOT, JASMINE, LADIES MANTLE, LAVENDER FLOWERS, LEMON BALM, LINSEED, MUSTARD SEED WHITE, NUTMEG POWDER, OAK MOSS, OAKBARK RED, PARSLEY, PEPPERMINT, PINE NUT, RUE, SAGE, THYME, VIOLET LEAVES, VIOLET | O34: 35 | P34: agate Botswana , agate Moss , Amazonite, Aventurine, Calcite, chrysophase, Citrine, Goldstone, Jade (jadeite), Lodestone, Pyrite (Fool's Gold), Rhodocrosite, Ruby, Sapphire, Serpentine, Topaz, Tourmalinee Black , Yellow Aventurine | Q34: 18 | R34: Bergamot, Cedarwood, Clove Bud, Geranium, Honeysuckle, Marjoram, Melissa, Neroli, Orange Bitter, Pine, Vanilla, Cinnamon, Ginger, Patchouli | S34: 14 | T34: FEHU, URUZ, WUNJO, JERA, SOWILO, BERKANAN, INGWAZ, OTHILA, DAGAZ | U34: 9 | V34: ALL GODDESSES, ALL LUNAR GODDESSES, ALLAT, AMATERASU, ARADIA, ARIANRHOD, ASTARTE, ATTIS, BAAL, BALDUR & HATHOR, BONA DEA, CERES, CERRIDWEN, CRONOS, CUPRA, EROS, FILDIAS, GAIA, GOD AND GODDESS IN BALANCE, GREAT GODDESS. MANASA | W34: 33 | X34: Draw | Y34: Draw | Z34: Spell Jar | AA34: Yes | AB34: Maybe | AC34: Yes | AD34: Draw wealth, grow luck or move stagnant money energy. | AE34: App should pull this row's Greenman Energy Mode from the main item sheets. Use Secondary Energy Hint only if a serious/adult spell still needs a Draw/Hold/Release/Open/Transform flavour. | AF34: Place where it can be seen | AG34: Hang it in the home | Bury in the earth
A35: Home, Blessings & Daily Magic | B35: House blessing | C35: Waxing | D35: Earth | E35: Moon | F35: Monday | G35: White | H35: North | I35: Receptive | J35: Black, green, yellow, brown | K35: 2 | L35: Duality, balance, couples, partnerships | M35: 1 or 3 | N35: ANISE, APPLE BLOSSOM, APPLEWOOD CHIPS, BASIL, BAY LAUREL, BENZOIN, BLACK TEA, BLACKBERRY LEAVES, CALAMUS ROOT, CARAWAY, CEDARWOOD (HIMALAYAN), CHAMOMILE, CHRYSANTHEMUM, CINNAMON STICKS, CLOVER, CLOVER RED, CLOVES, COLTSFOOT, COMFREY, DILL, DRAGON'S BLOOD, ELDERFLOWER, FENNEL (SEED), FRANKINCENSE, GARDENIA FRUIT, GINGER ROOT, GOLDENROD, HEARTSEASE, HIBISCUS, HOREHOUND, HYSSOP, JASMINE, JUNIPER BERRIES, LADIES MANTLE, LAVENDER FLOWERS, LEMON BALM, LEMON VERBENA, LEMONGRASS, LINDEN, MEADOW SWEET, HONESTY, MULLEIN, MUSTARD SEED WHITE, MYRRH GUM, NUTMEG POWDER, OAKBARK RED, SWEET MYRRH, OREGANO, ORRIS ROOT POWDER, PARSLEY, PENNYROYAL, PEPPERMINT, PINE NUT, RASPBERRY LEAF, ROSE BUDS PINK, ROSE BUDS RED, ROSE HIP, ROSE PETALS, ROSEMARY, RUE, SAGE, SANDALWOOD RED, SANDALWOOD WHITE, THYME, VALERIAN ROOT, VIOLET LEAVES, VIOLET, WHEAT GRAINS | O35: 68 | P35: agate Blue Lace , Amethyst, Apache Tears, Calcite, Carnelian, Chrysocolla, Quartz Clear , Copper flakes, Emerald, Flourite, Hematite, Howlite, Jet, Lapis Lazuli, Lepidolite, Lodestone, Moonstone, Peridot, quartz Rose , quartz smokey , quartz snow , Red Jasper, Rhodonite, Ruby, Sapphire, Seraphinite, Serpentine, Sodalite, Tanzanite, Tiger Eye gold, Unakite, Yellow Aventurine | Q35: 32 | R35: Apple, Bergamot, Clove Bud, Frankincense, Geranium, Juniper, Lavender, Lemon, Lemon Grass, Marjoram, Melissa, Neroli, Orange Bitter, Pine, Rose, Rosemary, Thyme, Vanilla, Ylang Ylang, Cinnamon, Ginger, Patchouli, Sandalwood In. | S35: 23 | T35: FEHU, ANSUZ, RAIDO, GEBO, WUNJO, PERTH, SOWILO, TIWAZ, EHWAZ, INGWAZ, OTHILA | U35: 11 | V35: AESCULAPUS, ALL, ALL GODDESSES, ALL LUNAR GODDESSES, ALLAT, AMATERASU, AMBERELLA, APHRODITE, ARADIA, ARES, ARIANRHOD, ARTEMIS, ASTARTE, ATTIS, BAAL, BACCHUS, BALDOR, BALDUR & HATHOR, BEFANA, BONA DEA | W35: 89 | X35: Hold | Y35: Hold | Z35: Spell Jar | AA35: Yes | AB35: Maybe | AC35: Yes | AD35: Bless, hold, consecrate and settle magic into place or tool. | AE35: App should pull this row's Greenman Energy Mode from the main item sheets. Use Secondary Energy Hint only if a serious/adult spell still needs a Draw/Hold/Release/Open/Transform flavour. | AF35: Hang it in the home | AG35: Place at a shrine or altar | Place where it can be seen
A36: Home, Blessings & Daily Magic | B36: Consecration | C36: Full | D36: Fire | E36: Sun | F36: Sunday | G36: White | H36: South | I36: Projective | J36: Red, gold, crimson, orange, white | K36: 1 | L36: Developing the self, the All, wholeness, unity, beginnings | M36: 1 or 3 | N36: AGRIMONY, ANISE, BASIL, BAY LAUREL, BENZOIN, BLACKBERRY LEAVES, CAMPHOR SYNTHETIC, CARAWAY, CEDARWOOD (HIMALAYAN), CHAMOMILE, CHRYSANTHEMUM, CINNAMON STICKS, CLEAVERS, CLOVER RED, CLOVES, DEVILS CLAW ROOT, DRAGON'S BLOOD, FENNEL (SEED), GARLIC POWDER, HYSSOP, JUNIPER BERRIES, LADIES MANTLE, LAVENDER FLOWERS, MYRRH GUM, MYRRH GUM POWDER, OAKLEAF, SWEET MYRRH, PARSLEY, PENNYROYAL, PEPPERMINT, PINE NUT, ROSE BUDS RED, ROSE HIP, ROSEMARY, RUE, SAGE, SANDALWOOD WHITE, SEA SALT, THYME, TONKA BEANS, VALERIAN ROOT, WITCH HAZEL LEAVES, BLACK SALT | O36: 43 | P36: Aquamarine, Quartz Clear , quartz snow , Seraphinite | Q36: 4 | R36: Cedarwood, Clove Bud, Fir Needle, Lavender, Lemon, Neroli, Peppermint, Pine, Rosemary, Tea Tree, Thyme, Cinnamon, Sandalwood In. | S36: 13 | T36: ALGIZ, OTHILA, TIWAZ, BERKANAN | U36: 4 | V36: GAIA, HYGIA, JUTERNA, BALDUR | W36: 4 | X36: Hold | Y36: Hold | Z36: Spell Jar | AA36: Yes | AB36: Maybe | AC36: Yes | AD36: Bless, hold, consecrate and settle magic into place or tool. | AE36: App should pull this row's Greenman Energy Mode from the main item sheets. Use Secondary Energy Hint only if a serious/adult spell still needs a Draw/Hold/Release/Open/Transform flavour. | AF36: Place at a shrine or altar | AG36: Hang it in the home
A37: Home, Blessings & Daily Magic | B37: Wand making | C37: Full | D37: Air | E37: Mercury | F37: Wednesday | G37: Yellow | H37: East | I37: Projective | J37: Yellow, white, crimson | K37: 5 | L37: Communication, fulfilment | M37: 1 or 3 | N37: SAGE, ROSEMARY, FRANKINCENSE, BAY LAUREL, OAK MOSS, OAKBARK RED, CEDARWOOD (HIMALAYAN) | O37: 7 | P37: Quartz Clear, Amethyst, Labradorite, quartz rutilated | Q37: 4 | R37: Frankincense, Cedarwood, Sandalwood In., Lavender | S37: 4 | T37: ANSUZ, ALGIZ, TIWAZ, BERKANAN | U37: 4 | V37: BRIGID, HECATE, ISIS, CERRIDWEN, ODIN, MERCURY, THOR, ZEUS | W37: 8 | X37: Transform / Turn | Y37: Transform / Turn | Z37: Spell Jar | AA37: Yes | AB37: Maybe | AC37: Yes | AD37: Bless, hold, consecrate and settle magic into place or tool. | AE37: App should pull this row's Greenman Energy Mode from the main item sheets. Use Secondary Energy Hint only if a serious/adult spell still needs a Draw/Hold/Release/Open/Transform flavour. | AF37: Place at a shrine or altar | AG37: Hang it in the home
A38: Spirit Work, Otherworld & Planes | B38: Attracting good spirits | C38: Waxing | D38: Air | E38: Mercury | F38: Wednesday | G38: Purple | H38: East | I38: Projective | J38: Yellow, white, crimson | K38: 5 | L38: Communication, fulfilment | M38: 3 or 7 | N38: ANISE, APPLE BLOSSOM, APPLEWOOD CHIPS, BASIL, BAY LAUREL, BENZOIN, BLACK TEA, BLACKBERRY LEAVES, CALAMUS ROOT, CARAWAY, CEDARWOOD (HIMALAYAN), CHAMOMILE, CHRYSANTHEMUM, CINNAMON STICKS, CLOVER, CLOVER RED, CLOVES, COLTSFOOT, COMFREY, DILL, DRAGON'S BLOOD, ELDERFLOWER, FENNEL (SEED), FRANKINCENSE, GARDENIA FRUIT, GINGER ROOT, GOLDENROD, HEARTSEASE, HIBISCUS, HOREHOUND, HYSSOP, JASMINE, JUNIPER BERRIES, LADIES MANTLE, LAVENDER FLOWERS, LEMON BALM, LEMON VERBENA, LEMONGRASS, LINDEN, MEADOW SWEET, HONESTY, MULLEIN, MUSTARD SEED WHITE, MYRRH GUM, NUTMEG POWDER, OAKBARK RED, SWEET MYRRH, OREGANO, ORRIS ROOT POWDER, PARSLEY, PENNYROYAL, PEPPERMINT, PINE NUT, RASPBERRY LEAF, ROSE BUDS PINK, ROSE BUDS RED, ROSE HIP, ROSE PETALS, ROSEMARY, RUE, SAGE, SANDALWOOD RED, SANDALWOOD WHITE, THYME, VALERIAN ROOT, VIOLET LEAVES, VIOLET, WHEAT GRAINS | O38: 68 | P38: agate Blue Lace , Amethyst, Apache Tears, Calcite, Carnelian, Chrysocolla, Quartz Clear , Copper flakes, Emerald, Flourite, Hematite, Howlite, Jet, Lapis Lazuli, Lepidolite, Lodestone, Moonstone, Peridot, quartz Rose , quartz smokey , quartz snow , Red Jasper, Rhodonite, Ruby, Sapphire, Seraphinite, Serpentine, Sodalite, Tanzanite, Tiger Eye gold, Unakite, Yellow Aventurine | Q38: 32 | R38: Apple, Bergamot, Clove Bud, Frankincense, Geranium, Juniper, Lavender, Lemon, Lemon Grass, Marjoram, Melissa, Neroli, Orange Bitter, Pine, Rose, Rosemary, Thyme, Vanilla, Ylang Ylang, Cinnamon, Ginger, Patchouli, Sandalwood In. | S38: 23 | T38: FEHU, ANSUZ, RAIDO, GEBO, WUNJO, PERTH, SOWILO, TIWAZ, EHWAZ, INGWAZ, OTHILA | U38: 11 | V38: AESCULAPUS, ALL, ALL GODDESSES, ALL LUNAR GODDESSES, ALLAT, AMATERASU, AMBERELLA, APHRODITE, ARADIA, ARES, ARIANRHOD, ARTEMIS, ASTARTE, ATTIS, BAAL, BACCHUS, BALDOR, BALDUR & HATHOR, BEFANA, BONA DEA | W38: 89 | X38: Draw | Y38: Draw | Z38: Smoke and Flame | AA38: Maybe | AB38: Yes | AC38: Maybe | AD38: Open roads, make offerings, contact spirit paths, or transform thresholds. | AE38: App should pull this row's Greenman Energy Mode from the main item sheets. Use Secondary Energy Hint only if a serious/adult spell still needs a Draw/Hold/Release/Open/Transform flavour. | AF38: Place in a tree | AG38: Place at a shrine or altar | Bury in the earth
A39: Spirit Work, Otherworld & Planes | B39: Contacting planes | C39: Full/Dark | D39: Air | E39: Mercury | F39: Wednesday | G39: Purple | H39: East | I39: Projective | J39: Yellow, white, crimson | K39: 5 | L39: Communication, fulfilment | M39: 3 or 7 | N39: ANISE, APPLEWOOD CHIPS, BASIL, CHRYSANTHEMUM, CLOVER, COLTSFOOT, LEMON BALM, MULLEIN, PARSLEY, PENNYROYAL, SAGE, SANDALWOOD RED, SANDALWOOD WHITE, TANSY, THYME, BLACK SALT, YARROW | O39: 17 | P39: Jet, obsidian snowflake, Onyx, Petrified Wood, Serpentine | Q39: 5 | R39: Frankincense, Sandalwood w.i. | S39: 2 | T39: PERTH, ANSUZ, LAGUZ, ALGIZ | U39: 4 | V39: ALL, AMATERASU, AMBERELLA, ARTEMIS, BEFANA, BUDDHA, DIANA, EREYR, FLIDAIS, GAIA, HATHOR, HECATE, HEL, ISIS, JANA, KWAN-YIN AND BUDDHA, LOKI, MADAME PELE, MARY MAGDALENE, MERCURY | W39: 34 | X39: Open / Reveal | Y39: Open / Reveal | Z39: Smoke and Flame | AA39: Maybe | AB39: Yes | AC39: Maybe | AD39: Open roads, make offerings, contact spirit paths, or transform thresholds. | AE39: App should pull this row's Greenman Energy Mode from the main item sheets. Use Secondary Energy Hint only if a serious/adult spell still needs a Draw/Hold/Release/Open/Transform flavour. | AF39: Place at a shrine or altar | AG39: Carry it close on your person
A40: Spirit Work, Otherworld & Planes | B40: Crone magic | C40: Full/Dark | D40: Earth | E40: Saturn | F40: Saturday | G40: Black | H40: North | I40: Receptive | J40: Black, green, yellow, brown | K40: 8 | L40: Material aspects, travel, protection, discipline | M40: 3 or 7 | N40: ANISE, APPLEWOOD CHIPS, BASIL, CHRYSANTHEMUM, CLOVER, COLTSFOOT, LEMON BALM, MULLEIN, PARSLEY, PENNYROYAL, SAGE, SANDALWOOD RED, SANDALWOOD WHITE, TANSY, THYME, BLACK SALT, YARROW | O40: 17 | P40: Jet, obsidian snowflake, Onyx, Petrified Wood, Serpentine | Q40: 5 | R40: Frankincense, Sandalwood w.i. | S40: 2 | T40: PERTH, HAGALAZ, ISA, OTHILA | U40: 4 | V40: ALL, AMATERASU, AMBERELLA, ARTEMIS, BEFANA, BUDDHA, DIANA, EREYR, FLIDAIS, GAIA, HATHOR, HECATE, HEL, ISIS, JANA, KWAN-YIN AND BUDDHA, LOKI, MADAME PELE, MARY MAGDALENE, MERCURY | W40: 34 | X40: Transform / Turn | Y40: Transform / Turn | Z40: Smoke and Flame | AA40: Maybe | AB40: Yes | AC40: Maybe | AD40: Open roads, make offerings, contact spirit paths, or transform thresholds. | AE40: App should pull this row's Greenman Energy Mode from the main item sheets. Use Secondary Energy Hint only if a serious/adult spell still needs a Draw/Hold/Release/Open/Transform flavour. | AF40: Place at a shrine or altar | AG40: Place in a tree | Bury in the earth
A41: Spirit Work, Otherworld & Planes | B41: Fairy portals | C41: Full | D41: Air | E41: Mercury | F41: Wednesday | G41: Green | H41: East | I41: Projective | J41: Yellow, white, crimson | K41: 5 | L41: Communication, fulfilment | M41: 3 or 7 | N41: ELDERFLOWER, THYME, CLOVER, HEATHER, ELDERFLOWER, LAVENDER FLOWERS, CHAMOMILE | O41: 7 | P41: Flourite, Moonstone, Labradorite, Aventurine | Q41: 4 | R41: Lavender, Frankincense, Cedarwood, Neroli | S41: 4 | T41: PERTH, ALGIZ, EHWAZ, DAGAZ | U41: 4 | V41: DIANA, TITIANA, FREYJA, HOLDA, PAN, FREY, MERCURY, LOKI | W41: 8 | X41: Open / Reveal | Y41: Open / Reveal | Z41: Smoke and Flame | AA41: Maybe | AB41: Yes | AC41: Maybe | AD41: Open roads, make offerings, contact spirit paths, or transform thresholds. | AE41: App should pull this row's Greenman Energy Mode from the main item sheets. Use Secondary Energy Hint only if a serious/adult spell still needs a Draw/Hold/Release/Open/Transform flavour. | AF41: Place in a tree | AG41: Place at a shrine or altar | Carry it close on your person
A42: Spirit Work, Otherworld & Planes | B42: Otherworld travel | C42: Full/Dark | D42: Air | E42: Mercury | F42: Wednesday | G42: Purple | H42: East | I42: Projective | J42: Yellow, white, crimson | K42: 5 | L42: Communication, fulfilment | M42: 3 or 7 | N42: ANISE, APPLE BLOSSOM, APPLEWOOD CHIPS, BASIL, BAY LAUREL, BENZOIN, BLACK TEA, BLACKBERRY LEAVES, CALAMUS ROOT, CARAWAY, CEDARWOOD (HIMALAYAN), CHAMOMILE, CHRYSANTHEMUM, CINNAMON STICKS, CLOVER, CLOVER RED, CLOVES, COLTSFOOT, COMFREY, DILL, DRAGON'S BLOOD, ELDERFLOWER, FENNEL (SEED), FRANKINCENSE, GARDENIA FRUIT, GINGER ROOT, GOLDENROD, HEARTSEASE, HIBISCUS, HOREHOUND, HYSSOP, JASMINE, JUNIPER BERRIES, LADIES MANTLE, LAVENDER FLOWERS, LEMON BALM, LEMON VERBENA, LEMONGRASS, LINDEN, MEADOW SWEET, HONESTY, MULLEIN, MUSTARD SEED WHITE, MYRRH GUM, NUTMEG POWDER, OAKBARK RED, SWEET MYRRH, OREGANO, ORRIS ROOT POWDER, PARSLEY, PENNYROYAL, PEPPERMINT, PINE NUT, RASPBERRY LEAF, ROSE BUDS PINK, ROSE BUDS RED, ROSE HIP, ROSE PETALS, ROSEMARY, RUE, SAGE, SANDALWOOD RED, SANDALWOOD WHITE, THYME, VALERIAN ROOT, VIOLET LEAVES, VIOLET, WHEAT GRAINS | O42: 68 | P42: agate Blue Lace , Amethyst, Apache Tears, Calcite, Carnelian, Chrysocolla, Quartz Clear , Copper flakes, Emerald, Flourite, Hematite, Howlite, Jet, Lapis Lazuli, Lepidolite, Lodestone, Moonstone, Peridot, quartz Rose , quartz smokey , quartz snow , Red Jasper, Rhodonite, Ruby, Sapphire, Seraphinite, Serpentine, Sodalite, Tanzanite, Tiger Eye gold, Unakite, Yellow Aventurine | Q42: 32 | R42: Apple, Bergamot, Clove Bud, Frankincense, Geranium, Juniper, Lavender, Lemon, Lemon Grass, Marjoram, Melissa, Neroli, Orange Bitter, Pine, Rose, Rosemary, Thyme, Vanilla, Ylang Ylang, Cinnamon, Ginger, Patchouli, Sandalwood In. | S42: 23 | T42: FEHU, ANSUZ, RAIDO, GEBO, WUNJO, PERTH, SOWILO, TIWAZ, EHWAZ, INGWAZ, OTHILA | U42: 11 | V42: AESCULAPUS, ALL, ALL GODDESSES, ALL LUNAR GODDESSES, ALLAT, AMATERASU, AMBERELLA, APHRODITE, ARADIA, ARES, ARIANRHOD, ARTEMIS, ASTARTE, ATTIS, BAAL, BACCHUS, BALDOR, BALDUR & HATHOR, BEFANA, BONA DEA | W42: 89 | X42: Open / Reveal | Y42: Open / Reveal | Z42: Smoke and Flame | AA42: Maybe | AB42: Yes | AC42: Maybe | AD42: Open roads, make offerings, contact spirit paths, or transform thresholds. | AE42: App should pull this row's Greenman Energy Mode from the main item sheets. Use Secondary Energy Hint only if a serious/adult spell still needs a Draw/Hold/Release/Open/Transform flavour. | AF42: Carry it close on your person | AG42: Place at a shrine or altar | Place in a tree
A43: Spirit Work, Otherworld & Planes | B43: Spirit offerings | C43: Waxing/Full | D43: Earth | E43: Saturn | F43: Saturday | G43: White | H43: North | I43: Receptive | J43: Black, green, yellow, brown | K43: 8 | L43: Material aspects, travel, protection, discipline | M43: 3 or 7 | N43: ANISE, APPLE BLOSSOM, APPLEWOOD CHIPS, BASIL, BAY LAUREL, BENZOIN, BLACK TEA, BLACKBERRY LEAVES, CALAMUS ROOT, CARAWAY, CEDARWOOD (HIMALAYAN), CHAMOMILE, CHRYSANTHEMUM, CINNAMON STICKS, CLOVER, CLOVER RED, CLOVES, COLTSFOOT, COMFREY, DILL, DRAGON'S BLOOD, ELDERFLOWER, FENNEL (SEED), FRANKINCENSE, GARDENIA FRUIT, GINGER ROOT, GOLDENROD, HEARTSEASE, HIBISCUS, HOREHOUND, HYSSOP, JASMINE, JUNIPER BERRIES, LADIES MANTLE, LAVENDER FLOWERS, LEMON BALM, LEMON VERBENA, LEMONGRASS, LINDEN, MEADOW SWEET, HONESTY, MULLEIN, MUSTARD SEED WHITE, MYRRH GUM, NUTMEG POWDER, OAKBARK RED, SWEET MYRRH, OREGANO, ORRIS ROOT POWDER, PARSLEY, PENNYROYAL, PEPPERMINT, PINE NUT, RASPBERRY LEAF, ROSE BUDS PINK, ROSE BUDS RED, ROSE HIP, ROSE PETALS, ROSEMARY, RUE, SAGE, SANDALWOOD RED, SANDALWOOD WHITE, THYME, VALERIAN ROOT, VIOLET LEAVES, VIOLET, WHEAT GRAINS | O43: 68 | P43: agate Blue Lace , Amethyst, Apache Tears, Calcite, Carnelian, Chrysocolla, Quartz Clear , Copper flakes, Emerald, Flourite, Hematite, Howlite, Jet, Lapis Lazuli, Lepidolite, Lodestone, Moonstone, Peridot, quartz Rose , quartz smokey , quartz snow , Red Jasper, Rhodonite, Ruby, Sapphire, Seraphinite, Serpentine, Sodalite, Tanzanite, Tiger Eye gold, Unakite, Yellow Aventurine | Q43: 32 | R43: Apple, Bergamot, Clove Bud, Frankincense, Geranium, Juniper, Lavender, Lemon, Lemon Grass, Marjoram, Melissa, Neroli, Orange Bitter, Pine, Rose, Rosemary, Thyme, Vanilla, Ylang Ylang, Cinnamon, Ginger, Patchouli, Sandalwood In. | S43: 23 | T43: FEHU, ANSUZ, RAIDO, GEBO, WUNJO, PERTH, SOWILO, TIWAZ, EHWAZ, INGWAZ, OTHILA | U43: 11 | V43: AESCULAPUS, ALL, ALL GODDESSES, ALL LUNAR GODDESSES, ALLAT, AMATERASU, AMBERELLA, APHRODITE, ARADIA, ARES, ARIANRHOD, ARTEMIS, ASTARTE, ATTIS, BAAL, BACCHUS, BALDOR, BALDUR & HATHOR, BEFANA, BONA DEA | W43: 89 | X43: Open / Reveal | Y43: Open / Reveal | Z43: Smoke and Flame | AA43: Maybe | AB43: Yes | AC43: Maybe | AD43: Open roads, make offerings, contact spirit paths, or transform thresholds. | AE43: App should pull this row's Greenman Energy Mode from the main item sheets. Use Secondary Energy Hint only if a serious/adult spell still needs a Draw/Hold/Release/Open/Transform flavour. | AF43: Place at a shrine or altar | AG43: Place in a tree | Leave in running water
A44: Happiness, Harmony & Peace | B44: Happiness | C44: Waxing | D44: Air | E44: Venus | F44: Friday | G44: Yellow | H44: East | I44: Projective | J44: Yellow, white, crimson | K44: 6 | L44: Emotions, magnetism, gods/goddesses, cats | M44: 1 or 3 | N44: ANISE, APPLE BLOSSOM, BASIL, CINNAMON STICKS, EYEBRIGHT, LAVENDER FLOWERS, LEMON BALM, OREGANO, PARSLEY, PEPPERMINT, ROSEMARY, SAGE, THYME | O44: 13 | P44: agate Botswana , chrysophase, Citrine, Lodestone, quartz Rose , Ruby | Q44: 6 | R44: Apple, Bergamot, Lavender, Marjoram, Neroli, Pine, Vanilla | S44: 7 | T44: WUNJO, INGWAZ | U44: 2 | V44: ALL GODDESSES, ALL LUNAR GODDESSES, AMATERASU, AMBERELLA, APHRODITE, ARADIA, BAAL, BACCHUS, BALDOR, BALDUR & HATHOR, BEFANA, CUPID, DIONYSUS, ELECTRA, FATHER GOD, GOD AND GODDESS IN BALANCE, JUPITER, KWAN-YIN AND BUDDHA, LUNA, MAAT | W44: 34 | X44: Hold | Y44: Hold | Z44: Charm Bag | AA44: Maybe | AB44: Maybe | AC44: Yes | AD44: Carry peace, happiness and harmony as a quiet working. | AE44: App should pull this row's Greenman Energy Mode from the main item sheets. Use Secondary Energy Hint only if a serious/adult spell still needs a Draw/Hold/Release/Open/Transform flavour. | AF44: Carry it close on your person | AG44: Place where it can be seen | Hang it in the home
A45: Happiness, Harmony & Peace | B45: Harmony | C45: Waxing | D45: Water | E45: Venus | F45: Friday | G45: Pink | H45: West | I45: Receptive | J45: Blue, turquoise, green, grey, indigo, black | K45: 6 | L45: Emotions, magnetism, gods/goddesses, cats | M45: 1 or 3 | N45: ANISE, APPLE BLOSSOM, APPLEWOOD CHIPS, BASIL, BAY LAUREL, BENZOIN, BLACK TEA, BLACKBERRY LEAVES, CALAMUS ROOT, CARAWAY, CEDARWOOD (HIMALAYAN), CHAMOMILE, CHRYSANTHEMUM, CINNAMON STICKS, CLOVER, CLOVER RED, CLOVES, COLTSFOOT, COMFREY, DILL, DRAGON'S BLOOD, ELDERFLOWER, FENNEL (SEED), FRANKINCENSE, GARDENIA FRUIT, GINGER ROOT, GOLDENROD, HEARTSEASE, HIBISCUS, HOREHOUND, HYSSOP, JASMINE, JUNIPER BERRIES, LADIES MANTLE, LAVENDER FLOWERS, LEMON BALM, LEMON VERBENA, LEMONGRASS, LINDEN, MEADOW SWEET, HONESTY, MULLEIN, MUSTARD SEED WHITE, MYRRH GUM, NUTMEG POWDER, OAKBARK RED, SWEET MYRRH, OREGANO, ORRIS ROOT POWDER, PARSLEY, PENNYROYAL, PEPPERMINT, PINE NUT, RASPBERRY LEAF, ROSE BUDS PINK, ROSE BUDS RED, ROSE HIP, ROSE PETALS, ROSEMARY, RUE, SAGE, SANDALWOOD RED, SANDALWOOD WHITE, THYME, VALERIAN ROOT, VIOLET LEAVES, VIOLET, WHEAT GRAINS | O45: 68 | P45: agate Blue Lace , Amethyst, Apache Tears, Calcite, Carnelian, Chrysocolla, Quartz Clear , Copper flakes, Emerald, Flourite, Hematite, Howlite, Jet, Lapis Lazuli, Lepidolite, Lodestone, Moonstone, Peridot, quartz Rose , quartz smokey , quartz snow , Red Jasper, Rhodonite, Ruby, Sapphire, Seraphinite, Serpentine, Sodalite, Tanzanite, Tiger Eye gold, Unakite, Yellow Aventurine | Q45: 32 | R45: Apple, Bergamot, Clove Bud, Frankincense, Geranium, Juniper, Lavender, Lemon, Lemon Grass, Marjoram, Melissa, Neroli, Orange Bitter, Pine, Rose, Rosemary, Thyme, Vanilla, Ylang Ylang, Cinnamon, Ginger, Patchouli, Sandalwood In. | S45: 23 | T45: FEHU, ANSUZ, RAIDO, GEBO, WUNJO, PERTH, SOWILO, TIWAZ, EHWAZ, INGWAZ, OTHILA | U45: 11 | V45: AESCULAPUS, ALL, ALL GODDESSES, ALL LUNAR GODDESSES, ALLAT, AMATERASU, AMBERELLA, APHRODITE, ARADIA, ARES, ARIANRHOD, ARTEMIS, ASTARTE, ATTIS, BAAL, BACCHUS, BALDOR, BALDUR & HATHOR, BEFANA, BONA DEA | W45: 89 | X45: Hold | Y45: Hold | Z45: Charm Bag | AA45: Maybe | AB45: Maybe | AC45: Yes | AD45: Carry peace, happiness and harmony as a quiet working. | AE45: App should pull this row's Greenman Energy Mode from the main item sheets. Use Secondary Energy Hint only if a serious/adult spell still needs a Draw/Hold/Release/Open/Transform flavour. | AF45: Hang it in the home | AG45: Carry it close on your person | Place where it can be seen
A46: Happiness, Harmony & Peace | B46: Peace | C46: Waxing | D46: Water | E46: Venus | F46: Friday | G46: Blue | H46: West | I46: Receptive | J46: Blue, turquoise, green, grey, indigo, black | K46: 6 | L46: Emotions, magnetism, gods/goddesses, cats | M46: 1 or 3 | N46: ANISE, APPLE BLOSSOM, APPLEWOOD CHIPS, BASIL, BAY LAUREL, BENZOIN, BLACK TEA, BLACKBERRY LEAVES, CALAMUS ROOT, CARAWAY, CEDARWOOD (HIMALAYAN), CHAMOMILE, CHRYSANTHEMUM, CINNAMON STICKS, CLOVER, CLOVER RED, CLOVES, COLTSFOOT, COMFREY, DILL, DRAGON'S BLOOD, ELDERFLOWER, FENNEL (SEED), FRANKINCENSE, GARDENIA FRUIT, GINGER ROOT, GOLDENROD, HEARTSEASE, HIBISCUS, HOREHOUND, HYSSOP, JASMINE, JUNIPER BERRIES, LADIES MANTLE, LAVENDER FLOWERS, LEMON BALM, LEMON VERBENA, LEMONGRASS, HONESTY, MULLEIN, MUSTARD SEED WHITE, MYRRH GUM, NUTMEG POWDER, OAKBARK RED, SWEET MYRRH, OREGANO, ORRIS ROOT POWDER, PARSLEY, PENNYROYAL, PEPPERMINT, PINE NUT, RASPBERRY LEAF, ROSE BUDS PINK, ROSE BUDS RED, ROSE HIP, ROSE PETALS, ROSEMARY, RUE, SAGE, SANDALWOOD RED, SANDALWOOD WHITE, THYME, VALERIAN ROOT, VIOLET LEAVES, VIOLET, WHEAT GRAINS | O46: 66 | P46: agate Blue Lace , Amethyst, Apache Tears, Calcite, Carnelian, Chrysocolla, Quartz Clear , Copper flakes, Emerald, Flourite, Hematite, Howlite, Jet, Lapis Lazuli, Lepidolite, Lodestone, Moonstone, Peridot, quartz Rose , quartz smokey , quartz snow , Red Jasper, Rhodonite, Ruby, Sapphire, Seraphinite, Serpentine, Sodalite, Tanzanite, Tiger Eye gold, Unakite, Yellow Aventurine | Q46: 32 | R46: Apple, Bergamot, Clove Bud, Frankincense, Geranium, Juniper, Lavender, Lemon, Lemon Grass, Marjoram, Melissa, Neroli, Orange Bitter, Pine, Rose, Rosemary, Thyme, Vanilla, Ylang Ylang, Cinnamon, Ginger, Patchouli, Sandalwood In. | S46: 23 | T46: FEHU, ANSUZ, RAIDO, GEBO, WUNJO, PERTH, SOWILO, TIWAZ, EHWAZ, INGWAZ, OTHILA | U46: 11 | V46: AESCULAPUS, ALL, ALL GODDESSES, ALL LUNAR GODDESSES, ALLAT, AMATERASU, AMBERELLA, APHRODITE, ARADIA, ARES, ARIANRHOD, ARTEMIS, ASTARTE, ATTIS, BAAL, BACCHUS, BALDOR, BALDUR & HATHOR, BEFANA, BONA DEA | W46: 89 | X46: Hold | Y46: Hold | Z46: Charm Bag | AA46: Maybe | AB46: Maybe | AC46: Yes | AD46: Carry peace, happiness and harmony as a quiet working. | AE46: App should pull this row's Greenman Energy Mode from the main item sheets. Use Secondary Energy Hint only if a serious/adult spell still needs a Draw/Hold/Release/Open/Transform flavour. | AF46: Hang it in the home | AG46: Carry it close on your person | Place at a shrine or altar
A47: Change, Beginnings & Habit Work | B47: Breaking habits | C47: Waning | D47: Fire | E47: Mars | F47: Tuesday | G47: Black | H47: South | I47: Projective | J47: Red, gold, crimson, orange, white | K47: 9 | L47: Aggression, conflict, dominance | M47: 3 or 7 | N47: ACORN, CAMPHOR SYNTHETIC, CEDARWOOD (HIMALAYAN), CHIVE, CLOVES, COMFREY, HEATHER, JASMINE, LEMON VERBENA, PEPPERMINT, ROSEMARY, THYME, VALERIAN ROOT | O47: 13 | P47: agate Botswana , Citrine, Rhodocrosite | Q47: 3 | R47: Peppermint, Frankincense, Lavender, Cedarwood | S47: 4 | T47: FEHU, RAIDO, IHWAZ, BERKANAN, MANNAZ, LAGUZ, DAGAZ | U47: 7 | V47: AESCULAPUS, ALL GODDESSES, ALL LUNAR GODDESSES, ALLAT, AMBERELLA, ARADIA, ARIANRHOD, ARTEMIS, ASTARTE, ATTIS, BAAL, BACCHUS, BALDUR & HATHOR, BEFANA, BONA DEA, BRIGID, BUDDHA, CEBELE, CERES, CERRIDWEN | W47: 71 | X47: Release | Y47: Release | Z47: Smoke and Flame | AA47: Maybe | AB47: Yes | AC47: Yes | AD47: Turn the old pattern, release what binds, or open the next path. | AE47: App should pull this row's Greenman Energy Mode from the main item sheets. Use Secondary Energy Hint only if a serious/adult spell still needs a Draw/Hold/Release/Open/Transform flavour. | AF47: Bury in the earth | AG47: Burn and release, no remains | Leave in running water
A48: Change, Beginnings & Habit Work | B48: New beginnings | C48: Dark | D48: Earth | E48: Moon | F48: Monday | G48: White | H48: North | I48: Receptive | J48: Black, green, yellow, brown | K48: 2 | L48: Duality, balance, couples, partnerships | M48: 3 or 7 | N48: ACORN, CAMPHOR SYNTHETIC, CEDARWOOD (HIMALAYAN), CHIVE, CLOVES, COMFREY, HEATHER, JASMINE, LEMON VERBENA, PEPPERMINT, ROSEMARY, THYME, VALERIAN ROOT | O48: 13 | P48: agate Botswana , Citrine, Rhodocrosite | Q48: 3 | R48: Neroli, Frankincense, Lavender, Pine | S48: 4 | T48: FEHU, RAIDO, IHWAZ, BERKANAN, MANNAZ, LAGUZ, DAGAZ | U48: 7 | V48: AESCULAPUS, ALL GODDESSES, ALL LUNAR GODDESSES, ALLAT, AMBERELLA, ARADIA, ARIANRHOD, ARTEMIS, ASTARTE, ATTIS, BAAL, BACCHUS, BALDUR & HATHOR, BEFANA, BONA DEA, BRIGID, BUDDHA, CEBELE, CERES, CERRIDWEN | W48: 70 | X48: Transform / Turn | Y48: Transform / Turn | Z48: Smoke and Flame | AA48: Maybe | AB48: Yes | AC48: Yes | AD48: Turn the old pattern, release what binds, or open the next path. | AE48: App should pull this row's Greenman Energy Mode from the main item sheets. Use Secondary Energy Hint only if a serious/adult spell still needs a Draw/Hold/Release/Open/Transform flavour. | AF48: Place in a tree | AG48: Bury in the earth | Place where it can be seen
A49: Sabbat & Solar Observance | B49: Beltane | C49: Waxing | D49: Fire | E49: Sun | F49: Sunday | G49: Red | H49: South | I49: Projective | J49: Red, gold, crimson, orange, white | K49: 1 | L49: Developing the self, the All, wholeness, unity, beginnings | M49: 3 or 7 | N49: COLTSFOOT, FENNEL (SEED), HEARTSEASE, LAVENDER FLOWERS, THYME | O49: 5 | P49: Carnelian, Garnet, quartz Rose, Aventurine | Q49: 4 | R49: Rose, Ylang Ylang, Frankincense, Patchouli | S49: 4 | T49: BERKANAN, INGWAZ, WUNJO, FEHU | U49: 4 | V49: APHRODITE, BRIGID, FREYJA, VENUS, PAN, FREY, EROS, DIONYSUS | W49: 2 | X49: Transform / Turn | Y49: Transform / Turn | Z49: Smoke and Flame | AA49: Maybe | AB49: Yes | AC49: Maybe | AD49: Mark seasonal turning, solar fire, ancestral gates or festival rites. | AE49: App should pull this row's Greenman Energy Mode from the main item sheets. Use Secondary Energy Hint only if a serious/adult spell still needs a Draw/Hold/Release/Open/Transform flavour. | AF49: Place in a tree | AG49: Place at a shrine or altar | Bury in the earth
A50: Sabbat & Solar Observance | B50: Imbolc/Ostara | C50: Waxing | D50: Earth | E50: Moon | F50: Monday | G50: White | H50: North | I50: Receptive | J50: Black, green, yellow, brown | K50: 2 | L50: Duality, balance, couples, partnerships | M50: 3 or 7 | N50: CLEAVERS, COLTSFOOT, LEMON VERBENA, TANSY | O50: 4 | P50: Amethyst, quartz Rose, Moonstone, Aventurine | Q50: 4 | R50: Lavender, Frankincense, Neroli, Rose | S50: 4 | T50: BERKANAN, DAGAZ, JERA, INGWAZ | U50: 4 | V50: BRIGID, EOSTRE, FREYJA, ISIS, FREY, ING, ODIN, THOR | W50: 1 | X50: Transform / Turn | Y50: Transform / Turn | Z50: Smoke and Flame | AA50: Maybe | AB50: Yes | AC50: Maybe | AD50: Mark seasonal turning, solar fire, ancestral gates or festival rites. | AE50: App should pull this row's Greenman Energy Mode from the main item sheets. Use Secondary Energy Hint only if a serious/adult spell still needs a Draw/Hold/Release/Open/Transform flavour. | AF50: Place in a tree | AG50: Place at a shrine or altar | Place where it can be seen
A51: Sabbat & Solar Observance | B51: Mabon/Samhain | C51: Waning | D51: Earth | E51: Saturn | F51: Saturday | G51: Orange | H51: North | I51: Receptive | J51: Black, green, yellow, brown | K51: 8 | L51: Material aspects, travel, protection, discipline | M51: 3 or 7 | N51: ANISE, APPLEWOOD CHIPS, BASIL, CHRYSANTHEMUM, CLOVER, COLTSFOOT, LEMON BALM, MULLEIN, PARSLEY, PENNYROYAL, SAGE, SANDALWOOD RED, SANDALWOOD WHITE, TANSY, THYME, BLACK SALT, YARROW | O51: 17 | P51: Jet, obsidian snowflake, Onyx, Petrified Wood, Serpentine | Q51: 5 | R51: Frankincense, Sandalwood w.i. | S51: 2 | T51: JERA, OTHILA, DAGAZ, IHWAZ | U51: 4 | V51: ALL, AMATERASU, AMBERELLA, ARTEMIS, BEFANA, BUDDHA, DIANA, EREYR, FLIDAIS, GAIA, HATHOR, HECATE, HEL, ISIS, JANA, KWAN-YIN AND BUDDHA, LOKI, MADAME PELE, MARY MAGDALENE, MERCURY | W51: 34 | X51: Transform / Turn | Y51: Transform / Turn | Z51: Smoke and Flame | AA51: Maybe | AB51: Yes | AC51: Maybe | AD51: Mark seasonal turning, solar fire, ancestral gates or festival rites. | AE51: App should pull this row's Greenman Energy Mode from the main item sheets. Use Secondary Energy Hint only if a serious/adult spell still needs a Draw/Hold/Release/Open/Transform flavour. | AF51: Place at a shrine or altar | AG51: Bury in the earth | Place in a tree
A52: Sabbat & Solar Observance | B52: Midsummer | C52: Full | D52: Fire | E52: Sun | F52: Sunday | G52: Gold | H52: South | I52: Projective | J52: Red, gold, crimson, orange, white | K52: 1 | L52: Developing the self, the All, wholeness, unity, beginnings | M52: 3 or 7 | N52: COLTSFOOT, FENNEL (SEED), HEARTSEASE, LAVENDER FLOWERS, THYME | O52: 5 | P52: Citrine, Carnelian, Garnet, Quartz Clear | Q52: 4 | R52: Frankincense, Rose, Lavender, Orange Bitter | S52: 4 | T52: SOWILO, TIWAZ, DAGAZ, FEHU | U52: 4 | V52: BRIGID, DIANA, FREYJA, ISIS, SOL, RA, ODIN, THOR | W52: 2 | X52: Transform / Turn | Y52: Transform / Turn | Z52: Smoke and Flame | AA52: Maybe | AB52: Yes | AC52: Maybe | AD52: Mark seasonal turning, solar fire, ancestral gates or festival rites. | AE52: App should pull this row's Greenman Energy Mode from the main item sheets. Use Secondary Energy Hint only if a serious/adult spell still needs a Draw/Hold/Release/Open/Transform flavour. | AF52: Place in a tree | AG52: Place at a shrine or altar | Place where it can be seen
A53: Sabbat & Solar Observance | B53: Sabbat rituals | C53: Various | D53: Earth | E53: Moon | F53: Monday | G53: White | H53: North | I53: Receptive | J53: Black, green, yellow, brown | K53: 2 | L53: Duality, balance, couples, partnerships | M53: 3 or 7 | N53: ROSEMARY, SAGE, FRANKINCENSE, WORMWOOD, ELDERFLOWER, LAVENDER FLOWERS, THYME | O53: 7 | P53: Quartz Clear, Amethyst, Moonstone, Labradorite | Q53: 4 | R53: Frankincense, Sandalwood w.i., Lavender, Cedarwood | S53: 4 | T53: JERA, IHWAZ, DAGAZ, OTHILA | U53: 4 | V53: BRIGID, CERRIDWEN, HECATE, THE GREAT MOTHER, ODIN, PAN, PAN, SATURN | W53: 8 | X53: Transform / Turn | Y53: Transform / Turn | Z53: Smoke and Flame | AA53: Maybe | AB53: Yes | AC53: Maybe | AD53: Mark seasonal turning, solar fire, ancestral gates or festival rites. | AE53: App should pull this row's Greenman Energy Mode from the main item sheets. Use Secondary Energy Hint only if a serious/adult spell still needs a Draw/Hold/Release/Open/Transform flavour. | AF53: Place at a shrine or altar | AG53: Place in a tree
A54: Sabbat & Solar Observance | B54: Samhain/ancestral altars | C54: Dark | D54: Earth | E54: Saturn | F54: Saturday | G54: Black | H54: North | I54: Receptive | J54: Black, green, yellow, brown | K54: 8 | L54: Material aspects, travel, protection, discipline | M54: 3 or 7 | N54: ANISE, APPLEWOOD CHIPS, BASIL, CHRYSANTHEMUM, CLOVER, COLTSFOOT, LEMON BALM, MULLEIN, PARSLEY, PENNYROYAL, SAGE, SANDALWOOD RED, SANDALWOOD WHITE, TANSY, THYME, BLACK SALT, YARROW | O54: 17 | P54: Jet, obsidian snowflake, Onyx, Petrified Wood, Serpentine | Q54: 5 | R54: Frankincense, Sandalwood w.i. | S54: 2 | T54: OTHILA, PERTH, ISA, HAGALAZ | U54: 4 | V54: ALL, AMATERASU, AMBERELLA, ARTEMIS, BEFANA, BUDDHA, DIANA, EREYR, FLIDAIS, GAIA, HATHOR, HECATE, HEL, ISIS, JANA, KWAN-YIN AND BUDDHA, LOKI, MADAME PELE, MARY MAGDALENE, MERCURY | W54: 34 | X54: Open / Reveal | Y54: Open / Reveal | Z54: Smoke and Flame | AA54: Maybe | AB54: Yes | AC54: Maybe | AD54: Mark seasonal turning, solar fire, ancestral gates or festival rites. | AE54: App should pull this row's Greenman Energy Mode from the main item sheets. Use Secondary Energy Hint only if a serious/adult spell still needs a Draw/Hold/Release/Open/Transform flavour. | AF54: Place at a shrine or altar | AG54: Bury in the earth
A55: Sabbat & Solar Observance | B55: Spring/Imbolc/Ostara/Beltane | C55: Waxing | D55: Earth | E55: Moon | F55: Monday | G55: White | H55: North | I55: Receptive | J55: Black, green, yellow, brown | K55: 2 | L55: Duality, balance, couples, partnerships | M55: 3 or 7 | N55: CLEAVERS, COLTSFOOT, LEMON VERBENA, TANSY | O55: 4 | P55: Amethyst, quartz Rose, Aventurine, Moonstone | Q55: 4 | R55: Lavender, Rose, Neroli, Frankincense | S55: 4 | T55: BERKANAN, DAGAZ, INGWAZ, WUNJO | U55: 4 | V55: BRIGID, EOSTRE, FREYJA, ISIS, FREY, ING, ODIN, PAN | W55: 1 | X55: Transform / Turn | Y55: Transform / Turn | Z55: Smoke and Flame | AA55: Maybe | AB55: Yes | AC55: Maybe | AD55: Mark seasonal turning, solar fire, ancestral gates or festival rites. | AE55: App should pull this row's Greenman Energy Mode from the main item sheets. Use Secondary Energy Hint only if a serious/adult spell still needs a Draw/Hold/Release/Open/Transform flavour. | AF55: Place in a tree | AG55: Place at a shrine or altar | Place where it can be seen
A56: Sabbat & Solar Observance | B56: Sun God offerings | C56: Waxing | D56: Fire | E56: Sun | F56: Sunday | G56: Gold | H56: South | I56: Projective | J56: Red, gold, crimson, orange, white | K56: 1 | L56: Developing the self, the All, wholeness, unity, beginnings | M56: 3 or 7 | N56: ANISE, APPLE BLOSSOM, APPLEWOOD CHIPS, BASIL, BAY LAUREL, BENZOIN, BLACK TEA, BLACKBERRY LEAVES, CALAMUS ROOT, CARAWAY, CEDARWOOD (HIMALAYAN), CHAMOMILE, CHRYSANTHEMUM, CINNAMON STICKS, CLOVER, CLOVER RED, CLOVES, COLTSFOOT, COMFREY, DILL, DRAGON'S BLOOD, ELDERFLOWER, FENNEL (SEED), FRANKINCENSE, GARDENIA FRUIT, GINGER ROOT, GOLDENROD, HEARTSEASE, HIBISCUS, HOREHOUND, HYSSOP, JASMINE, JUNIPER BERRIES, LADIES MANTLE, LAVENDER FLOWERS, LEMON BALM, LEMON VERBENA, LEMONGRASS, LINDEN, MEADOW SWEET, HONESTY, MULLEIN, MUSTARD SEED WHITE, MYRRH GUM, NUTMEG POWDER, OAKBARK RED, SWEET MYRRH, OREGANO, ORRIS ROOT POWDER, PARSLEY, PENNYROYAL, PEPPERMINT, PINE NUT, RASPBERRY LEAF, ROSE BUDS PINK, ROSE BUDS RED, ROSE HIP, ROSE PETALS, ROSEMARY, RUE, SAGE, SANDALWOOD RED, SANDALWOOD WHITE, THYME, VALERIAN ROOT, VIOLET LEAVES, VIOLET, WHEAT GRAINS | O56: 68 | P56: agate Blue Lace , Amethyst, Apache Tears, Calcite, Carnelian, Chrysocolla, Quartz Clear , Copper flakes, Emerald, Flourite, Hematite, Howlite, Jet, Lapis Lazuli, Lepidolite, Lodestone, Moonstone, Peridot, quartz Rose , quartz smokey , quartz snow , Red Jasper, Rhodonite, Ruby, Sapphire, Seraphinite, Serpentine, Sodalite, Tanzanite, Tiger Eye gold, Unakite, Yellow Aventurine | Q56: 32 | R56: Apple, Bergamot, Clove Bud, Frankincense, Geranium, Juniper, Lavender, Lemon, Lemon Grass, Marjoram, Melissa, Neroli, Orange Bitter, Pine, Rose, Rosemary, Thyme, Vanilla, Ylang Ylang, Cinnamon, Ginger, Patchouli, Sandalwood In. | S56: 23 | T56: FEHU, ANSUZ, RAIDO, GEBO, WUNJO, PERTH, SOWILO, TIWAZ, EHWAZ, INGWAZ, OTHILA | U56: 11 | V56: AESCULAPUS, ALL, ALL GODDESSES, ALL LUNAR GODDESSES, ALLAT, AMATERASU, AMBERELLA, APHRODITE, ARADIA, ARES, ARIANRHOD, ARTEMIS, ASTARTE, ATTIS, BAAL, BACCHUS, BALDOR, BALDUR & HATHOR, BEFANA, BONA DEA | W56: 89 | X56: Draw | Y56: Draw | Z56: Smoke and Flame | AA56: Maybe | AB56: Yes | AC56: Maybe | AD56: Mark seasonal turning, solar fire, ancestral gates or festival rites. | AE56: App should pull this row's Greenman Energy Mode from the main item sheets. Use Secondary Energy Hint only if a serious/adult spell still needs a Draw/Hold/Release/Open/Transform flavour. | AF56: Place at a shrine or altar | AG56: Place in a tree | Place where it can be seen
A57: Sabbat & Solar Observance | B57: Yule | C57: Full | D57: Earth | E57: Saturn | F57: Saturday | G57: Red | H57: North | I57: Receptive | J57: Black, green, yellow, brown | K57: 8 | L57: Material aspects, travel, protection, discipline | M57: 3 or 7 | N57: FRANKINCENSE, ROSEMARY, SAGE, CINNAMON STICKS, PINE NUT, OAKBARK RED, MYRRH GUM | O57: 7 | P57: Quartz Clear, Garnet, Ruby, Citrine | Q57: 4 | R57: Frankincense, Sandalwood w.i., Cinnamon, Cedarwood | S57: 4 | T57: JERA, DAGAZ, SOWILO, IHWAZ | U57: 4 | V57: BRIGID, FREYJA, HEL, HOLDA, ODIN, THOR, SATURN, FREY | W57: 8 | X57: Transform / Turn | Y57: Transform / Turn | Z57: Smoke and Flame | AA57: Maybe | AB57: Yes | AC57: Maybe | AD57: Mark seasonal turning, solar fire, ancestral gates or festival rites. | AE57: App should pull this row's Greenman Energy Mode from the main item sheets. Use Secondary Energy Hint only if a serious/adult spell still needs a Draw/Hold/Release/Open/Transform flavour. | AF57: Hang it in the home | AG57: Place at a shrine or altar | Place in a tree
A58: Miscellaneous | B58: Amulets/talismans | C58: Waxing | D58: Earth | E58: Saturn | F58: Saturday | G58: Black | H58: North | I58: Receptive | J58: Black, green, yellow, brown | K58: 8 | L58: Material aspects, travel, protection, discipline | M58: 1 or 3 | N58: AGRIMONY, ANISE, BASIL, BAY LAUREL, BENZOIN, BLACKBERRY LEAVES, CAMPHOR SYNTHETIC, CARAWAY, CEDARWOOD (HIMALAYAN), CHAMOMILE, CHRYSANTHEMUM, CINNAMON STICKS, CLEAVERS, CLOVER RED, CLOVES, DEVILS CLAW ROOT, DRAGON'S BLOOD, FENNEL (SEED), GARLIC POWDER, HYSSOP, JUNIPER BERRIES, LADIES MANTLE, LAVENDER FLOWERS, MYRRH GUM, MYRRH GUM POWDER, OAKLEAF, SWEET MYRRH, PARSLEY, PENNYROYAL, PEPPERMINT, PINE NUT, ROSE BUDS RED, ROSE HIP, ROSEMARY, RUE, SAGE, SANDALWOOD WHITE, SEA SALT, THYME, TONKA BEANS, VALERIAN ROOT, WITCH HAZEL LEAVES, BLACK SALT | O58: 43 | P58: Aquamarine, Quartz Clear , quartz snow , Seraphinite | Q58: 4 | R58: Cedarwood, Clove Bud, Fir Needle, Lavender, Lemon, Neroli, Peppermint, Pine, Rosemary, Tea Tree, Thyme, Cinnamon, Sandalwood In. | S58: 13 | T58: ALGIZ, OTHILA, TIWAZ, BERKANAN | U58: 4 | V58: GAIA, HYGIA, JUTERNA, BALDUR | W58: 4 | X58: Hold | Y58: Hold | Z58: Charm Bag | AA58: Maybe | AB58: Maybe | AC58: Yes | AD58: General working: usually best carried, held, or kept close. | AE58: App should pull this row's Greenman Energy Mode from the main item sheets. Use Secondary Energy Hint only if a serious/adult spell still needs a Draw/Hold/Release/Open/Transform flavour. | AF58: Carry it close on your person | AG58: Hang it in the home | Place at a shrine or altar
A59: Miscellaneous | B59: Fruitfulness | C59: Waxing | D59: Earth | E59: Moon | F59: Monday | G59: Green | H59: North | I59: Receptive | J59: Black, green, yellow, brown | K59: 2 | L59: Duality, balance, couples, partnerships | M59: 1 or 3 | N59: ACORN, ANISE, BASIL, BENZOIN, BLACK TEA, BLACKBERRY LEAVES, CARAWAY, CHAMOMILE, CINNAMON STICKS, CLOVER, CLOVER RED, CLOVES, COLTSFOOT, COMFREY, DILL, FENNEL (SEED), GARLIC POWDER, GOLDENSEAL ROOT, JASMINE, LADIES MANTLE, LAVENDER FLOWERS, LEMON BALM, LINSEED, MUSTARD SEED WHITE, NUTMEG POWDER, OAK MOSS, OAKBARK RED, PARSLEY, PEPPERMINT, PINE NUT, RUE, SAGE, THYME, VIOLET LEAVES, VIOLET | O59: 35 | P59: agate Botswana , agate Moss , Amazonite, Aventurine, Calcite, chrysophase, Citrine, Goldstone, Jade (jadeite), Lodestone, Pyrite (Fool's Gold), Rhodocrosite, Ruby, Sapphire, Serpentine, Topaz, Tourmalinee Black , Yellow Aventurine | Q59: 18 | R59: Bergamot, Cedarwood, Clove Bud, Geranium, Honeysuckle, Marjoram, Melissa, Neroli, Orange Bitter, Pine, Vanilla, Cinnamon, Ginger, Patchouli | S59: 14 | T59: FEHU, URUZ, WUNJO, JERA, SOWILO, BERKANAN, INGWAZ, OTHILA, DAGAZ | U59: 9 | V59: ALL GODDESSES, ALL LUNAR GODDESSES, ALLAT, AMATERASU, ARADIA, ARIANRHOD, ASTARTE, ATTIS, BAAL, BALDUR & HATHOR, BONA DEA, CERES, CERRIDWEN, CRONOS, CUPRA, EROS, FILDIAS, GAIA, GOD AND GODDESS IN BALANCE, GREAT GODDESS. MANASA | W59: 36 | X59: Draw | Y59: Draw | Z59: Charm Bag | AA59: Maybe | AB59: Maybe | AC59: Yes | AD59: General working: usually best carried, held, or kept close. | AE59: App should pull this row's Greenman Energy Mode from the main item sheets. Use Secondary Energy Hint only if a serious/adult spell still needs a Draw/Hold/Release/Open/Transform flavour. | AF59: Place in a tree | AG59: Bury in the earth | Place where it can be seen
A60: Miscellaneous | B60: Musk | C60: Waxing | D60: Earth | E60: Venus | F60: Friday | G60: Brown | H60: North | I60: Receptive | J60: Black, green, yellow, brown | K60: 6 | L60: Emotions, magnetism, gods/goddesses, cats | M60: 1 or 3 | N60: TONKA BEANS, TONKA BEANS, VIOLET LEAVES, ROSE PETALS, OAK MOSS, TONKA BEANS, MYRRH GUM | O60: 7 | P60: quartz Rose, Carnelian, Moonstone, Amber | Q60: 4 | R60: Patchouli, Ylang Ylang, Vanilla, Rose | S60: 4 | T60: FEHU, GEBO, BERKANAN, INGWAZ | U60: 4 | V60: APHRODITE, VENUS, HATHOR, DIANA, EROS, FREY, DIONYSUS, PAN | W60: 8 | X60: Draw | Y60: Draw | Z60: Charm Bag | AA60: Maybe | AB60: Maybe | AC60: Yes | AD60: General working: usually best carried, held, or kept close. | AE60: App should pull this row's Greenman Energy Mode from the main item sheets. Use Secondary Energy Hint only if a serious/adult spell still needs a Draw/Hold/Release/Open/Transform flavour. | AF60: Carry it close on your person | AG60: Place where it can be seen
A61: Miscellaneous | B61: Star magick | C61: Waxing | D61: Air | E61: Mercury | F61: Wednesday | G61: Purple | H61: East | I61: Projective | J61: Yellow, white, crimson | K61: 5 | L61: Communication, fulfilment | M61: 1 or 3 | N61: ANISE, APPLE BLOSSOM, APPLEWOOD CHIPS, BASIL, BAY LAUREL, BENZOIN, BLACK TEA, BLACKBERRY LEAVES, CALAMUS ROOT, CARAWAY, CEDARWOOD (HIMALAYAN), CHAMOMILE, CHRYSANTHEMUM, CINNAMON STICKS, CLOVER, CLOVER RED, CLOVES, COLTSFOOT, COMFREY, DILL, DRAGON'S BLOOD, ELDERFLOWER, FENNEL (SEED), FRANKINCENSE, GARDENIA FRUIT, GINGER ROOT, GOLDENROD, HEARTSEASE, HIBISCUS, HOREHOUND, HYSSOP, JASMINE, JUNIPER BERRIES, LADIES MANTLE, LAVENDER FLOWERS, LEMON BALM, LEMON VERBENA, LEMONGRASS, LINDEN, MEADOW SWEET, HONESTY, MULLEIN, MUSTARD SEED WHITE, MYRRH GUM, NUTMEG POWDER, OAKBARK RED, SWEET MYRRH, OREGANO, ORRIS ROOT POWDER, PARSLEY, PENNYROYAL, PEPPERMINT, PINE NUT, RASPBERRY LEAF, ROSE BUDS PINK, ROSE BUDS RED, ROSE HIP, ROSE PETALS, ROSEMARY, RUE, SAGE, SANDALWOOD RED, SANDALWOOD WHITE, THYME, VALERIAN ROOT, VIOLET LEAVES, VIOLET, WHEAT GRAINS | O61: 68 | P61: agate Blue Lace , Amethyst, Apache Tears, Calcite, Carnelian, Chrysocolla, Quartz Clear , Copper flakes, Emerald, Flourite, Hematite, Howlite, Jet, Lapis Lazuli, Lepidolite, Lodestone, Moonstone, Peridot, quartz Rose , quartz smokey , quartz snow , Red Jasper, Rhodonite, Ruby, Sapphire, Seraphinite, Serpentine, Sodalite, Tanzanite, Tiger Eye gold, Unakite, Yellow Aventurine | Q61: 32 | R61: Apple, Bergamot, Clove Bud, Frankincense, Geranium, Juniper, Lavender, Lemon, Lemon Grass, Marjoram, Melissa, Neroli, Orange Bitter, Pine, Rose, Rosemary, Thyme, Vanilla, Ylang Ylang, Cinnamon, Ginger, Patchouli, Sandalwood In. | S61: 23 | T61: FEHU, ANSUZ, RAIDO, GEBO, WUNJO, PERTH, SOWILO, TIWAZ, EHWAZ, INGWAZ, OTHILA | U61: 11 | V61: AESCULAPUS, ALL, ALL GODDESSES, ALL LUNAR GODDESSES, ALLAT, AMATERASU, AMBERELLA, APHRODITE, ARADIA, ARES, ARIANRHOD, ARTEMIS, ASTARTE, ATTIS, BAAL, BACCHUS, BALDOR, BALDUR & HATHOR, BEFANA, BONA DEA | W61: 89 | X61: Open / Reveal | Y61: Open / Reveal | Z61: Charm Bag | AA61: Maybe | AB61: Maybe | AC61: Yes | AD61: General working: usually best carried, held, or kept close. | AE61: App should pull this row's Greenman Energy Mode from the main item sheets. Use Secondary Energy Hint only if a serious/adult spell still needs a Draw/Hold/Release/Open/Transform flavour. | AF61: Place in a tree | AG61: Place at a shrine or altar | Carry it close on your person
A62: Over 18 🔞 | B62: Solving marital problems | C62: Waxing | D62: Water | E62: Venus | F62: Friday | G62: Green | H62: West | I62: Receptive | J62: Blue, silver, grey, black, white | K62: 6 | L62: Emotions, magnetism, gods/goddesses, cats | M62: 1, 3 or 7 | N62: LAVENDER FLOWERS, ROSE PETALS, CHAMOMILE, LEMON BALM, CARAWAY, VIOLET LEAVES, YARROW | O62: 7 | P62: quartz Rose, Rhodocrosite, Lepidolite, Moonstone | Q62: 4 | R62: Rose, Lavender, Geranium, Ylang Ylang | S62: 4 | T62: GEBO, WUNJO, LAGUZ, INGWAZ | U62: 4 | V62: APHRODITE, VENUS, HATHOR, FREYJA, EROS, FREY, JUPITER, ODIN | W62: 8 | X62: Over 18 | Y62: Draw | Z62: All Three / User Choice | AA62: Yes | AB62: Yes | AC62: Yes | AD62: Adult / serious working: let the user choose Jar, Smoke and Flame, or Charm after reading the method notes. | AE62: App should pull this row's Greenman Energy Mode from the main item sheets. Use Secondary Energy Hint only if a serious/adult spell still needs a Draw/Hold/Release/Open/Transform flavour. | AF62: Hang it in the home | AG62: Keep it hidden and safe | Place at a shrine or altar
A63: Over 18 🔞 | B63: Spell-breaking | C63: Waning | D63: Fire | E63: Mars | F63: Tuesday | G63: Black | H63: South | I63: Projective | J63: Red, gold, crimson, orange, white | K63: 9 | L63: Aggression, conflict, dominance | M63: 1, 3 or 7 | N63: ACORN, AGRIMONY, ANISE, BASIL, CHAMOMILE, CINNAMON STICKS, CLOVES, COMFREY, GARLIC POWDER, LAVENDER FLOWERS, MUSTARD SEED WHITE, MYRRH GUM, PARSLEY, PENNYROYAL, PEPPERMINT, PINE NUT, ROSE BUDS RED, ROSEMARY, RUE, SANDALWOOD WHITE, SEA SALT, VIOLET LEAVES, VIOLET, BLACK SALT, WORMWOOD | O63: 25 | P63: Amazonite, Apache Tears, Aventurine, Bloodstone, chrysophase, Jade (jadeite), Lodestone, Malachite, Onyx, Opal pink, Pyrite (Fool's Gold) | Q63: 11 | R63: Frankincense, Neroli, Orange Bitter, Rose, Sandalwood In. | S63: 5 | T63: FEHU, RAIDO, WUNJO | U63: 3 | V63: ALL GODDESSES, ALL LUNAR GODDESSES, AMATERASU, AMBERELLA, APHRODITE, ARADIA, BAAL, BACCHUS, BALDOR, BALDUR & HATHOR, BEFANA, CUPID, DIONYSUS, ELECTRA, FATHER GOD, GOD AND GODDESS IN BALANCE, GREAT GODDESS. MANASA, JUPITER, KWAN-YIN AND BUDDHA, LUNA | W63: 36 | X63: Over 18 | Y63: Release | Z63: All Three / User Choice | AA63: Yes | AB63: Yes | AC63: Yes | AD63: Adult / serious working: let the user choose Jar, Smoke and Flame, or Charm after reading the method notes. | AE63: App should pull this row's Greenman Energy Mode from the main item sheets. Use Secondary Energy Hint only if a serious/adult spell still needs a Draw/Hold/Release/Open/Transform flavour. | AF63: Burn and release, no remains | AG63: Bury in the earth | Leave in running water
A64: Over 18 🔞 | B64: Removing curses | C64: Waning | D64: Fire | E64: Mars | F64: Tuesday | G64: Black | H64: South | I64: Projective | J64: Red, gold, crimson, orange, white | K64: 9 | L64: Aggression, conflict, dominance | M64: 1, 3 or 7 | N64: ACORN, AGRIMONY, ANISE, BASIL, CHAMOMILE, CINNAMON STICKS, CLOVES, COMFREY, GARLIC POWDER, LAVENDER FLOWERS, MUSTARD SEED WHITE, MYRRH GUM, PARSLEY, PENNYROYAL, PEPPERMINT, PINE NUT, ROSE BUDS RED, ROSEMARY, RUE, SANDALWOOD WHITE, SEA SALT, VIOLET LEAVES, VIOLET, BLACK SALT, WORMWOOD | O64: 25 | P64: Amazonite, Apache Tears, Aventurine, Bloodstone, chrysophase, Jade (jadeite), Lodestone, Malachite, Onyx, Opal pink, Pyrite (Fool's Gold) | Q64: 11 | R64: Frankincense, Neroli, Orange Bitter, Rose, Sandalwood In. | S64: 5 | T64: FEHU, RAIDO, WUNJO | U64: 3 | V64: ALL GODDESSES, ALL LUNAR GODDESSES, AMATERASU, AMBERELLA, APHRODITE, ARADIA, BAAL, BACCHUS, BALDOR, BALDUR & HATHOR, BEFANA, CUPID, DIONYSUS, ELECTRA, FATHER GOD, GOD AND GODDESS IN BALANCE, GREAT GODDESS. MANASA, JUPITER, KWAN-YIN AND BUDDHA, LUNA | W64: 36 | X64: Over 18 | Y64: Release | Z64: All Three / User Choice | AA64: Yes | AB64: Yes | AC64: Yes | AD64: Adult / serious working: let the user choose Jar, Smoke and Flame, or Charm after reading the method notes. | AE64: App should pull this row's Greenman Energy Mode from the main item sheets. Use Secondary Energy Hint only if a serious/adult spell still needs a Draw/Hold/Release/Open/Transform flavour. | AF64: Burn and release, no remains | AG64: Bury in the earth | Leave in running water
A65: Over 18 🔞 | B65: Evil eye warding | C65: Waning | D65: Fire | E65: Mars | F65: Tuesday | G65: Red | H65: South | I65: Projective | J65: Red, gold, crimson, orange, white | K65: 9 | L65: Aggression, conflict, dominance | M65: 1, 3 or 7 | N65: VERVAIN, GARLIC POWDER, ROSEMARY, RUE, ST JOHN'S WORT, ELDERFLOWER, BASIL | O65: 7 | P65: Jet, Obsidian, Tiger Eye gold, Amber | Q65: 4 | R65: Frankincense, Cedarwood, Rosemary, Lavender | S65: 4 | T65: ALGIZ, THURISAZ, TIWAZ, OTHILA | U65: 4 | V65: HECATE, ISIS, BRIGID, DIANA, ODIN, THOR, MARS, ZEUS | W65: 8 | X65: Over 18 | Y65: Release | Z65: All Three / User Choice | AA65: Yes | AB65: Yes | AC65: Yes | AD65: Adult / serious working: let the user choose Jar, Smoke and Flame, or Charm after reading the method notes. | AE65: App should pull this row's Greenman Energy Mode from the main item sheets. Use Secondary Energy Hint only if a serious/adult spell still needs a Draw/Hold/Release/Open/Transform flavour. | AF65: Hang it in the home | AG65: Carry it close on your person | Keep it hidden and safe
A66: Over 18 🔞 | B66: Gambling / Casino luck | C66: Waxing | D66: Earth | E66: Jupiter | F66: Thursday | G66: Gold | H66: North | I66: Receptive | J66: Green, brown, black, white | K66: 3 | L66: Health, triple aspects, psychism | M66: 1, 3 or 7 | N66: CHAMOMILE, GOLDENSEAL ROOT, OAK MOSS, CLOVER, CLOVER RED, NUTMEG POWDER, BASIL | O66: 7 | P66: Aventurine, Citrine, Pyrite (Fool's Gold), Goldstone | Q66: 4 | R66: Bergamot, Cinnamon, Orange Bitter, Frankincense | S66: 4 | T66: FEHU, WUNJO, JERA, SOWILO | U66: 4 | V66: MERCURY, JUPITER, GAIA, JUPITER, ZEUS, ODIN, FREY, THOR | W66: 8 | X66: Over 18 | Y66: Draw | Z66: All Three / User Choice | AA66: Yes | AB66: Yes | AC66: Yes | AD66: Adult / serious working: let the user choose Jar, Smoke and Flame, or Charm after reading the method notes. | AE66: App should pull this row's Greenman Energy Mode from the main item sheets. Use Secondary Energy Hint only if a serious/adult spell still needs a Draw/Hold/Release/Open/Transform flavour. | AF66: Carry it close on your person | AG66: Place where it can be seen
A67: Over 18 🔞 | B67: Shapeshifting | C67: Full | D67: Air | E67: Mercury | F67: Wednesday | G67: Violet/Purple | H67: East | I67: Projective | J67: Yellow, white, crimson | K67: 5 | L67: Communication, fulfilment | M67: 1, 3 or 7 | N67: HEATHER, WORMWOOD, WORMWOOD, VERVAIN, HYSSOP, ELDERFLOWER, SAGE | O67: 7 | P67: Labradorite, Obsidian, Hematite, Moonstone | Q67: 4 | R67: Patchouli, Frankincense, Sandalwood w.i., Cedarwood | S67: 4 | T67: EHWAZ, PERTH, DAGAZ, IHWAZ | U67: 4 | V67: HECATE, CERRIDWEN, FREYJA, HEL, ODIN, LOKI, PAN, MERCURY | W67: 8 | X67: Over 18 | Y67: Transform / Turn | Z67: All Three / User Choice | AA67: Yes | AB67: Yes | AC67: Yes | AD67: Adult / serious working: let the user choose Jar, Smoke and Flame, or Charm after reading the method notes. | AE67: App should pull this row's Greenman Energy Mode from the main item sheets. Use Secondary Energy Hint only if a serious/adult spell still needs a Draw/Hold/Release/Open/Transform flavour. | AF67: Carry it close on your person | AG67: Place at a shrine or altar | Place in a tree
A68: Over 18 🔞 | B68: Virility | C68: Waxing | D68: Fire | E68: Mars | F68: Tuesday | G68: Red | H68: South | I68: Projective | J68: Red, gold, crimson, orange, white | K68: 9 | L68: Aggression, conflict, dominance | M68: 1, 3 or 7 | N68: ACORN, ANISE, BASIL, BENZOIN, BLACK TEA, BLACKBERRY LEAVES, CARAWAY, CHAMOMILE, CINNAMON STICKS, CLOVER, CLOVER RED, CLOVES, COLTSFOOT, COMFREY, DILL, FENNEL (SEED), GARLIC POWDER, GOLDENSEAL ROOT, JASMINE, LADIES MANTLE, LAVENDER FLOWERS, LEMON BALM, LINSEED, MUSTARD SEED WHITE, NUTMEG POWDER, OAK MOSS, OAKBARK RED, PARSLEY, PEPPERMINT, PINE NUT, RUE, SAGE, THYME, VIOLET LEAVES, VIOLET | O68: 35 | P68: agate Botswana , agate Moss , Amazonite, Aventurine, Calcite, chrysophase, Citrine, Goldstone, Jade (jadeite), Lodestone, Pyrite (Fool's Gold), Rhodocrosite, Ruby, Sapphire, Serpentine, Topaz, Tourmalinee Black , Yellow Aventurine | Q68: 18 | R68: Bergamot, Cedarwood, Clove Bud, Geranium, Honeysuckle, Marjoram, Melissa, Neroli, Orange Bitter, Pine, Vanilla, Cinnamon, Ginger, Patchouli | S68: 14 | T68: FEHU, URUZ, WUNJO, JERA, SOWILO, BERKANAN, INGWAZ, OTHILA, DAGAZ | U68: 9 | V68: ALL GODDESSES, ALL LUNAR GODDESSES, ALLAT, AMATERASU, ARADIA, ARIANRHOD, ASTARTE, ATTIS, BAAL, BALDUR & HATHOR, BONA DEA, CERES, CERRIDWEN, CRONOS, CUPRA, EROS, FILDIAS, GAIA, GOD AND GODDESS IN BALANCE, GREAT GODDESS. MANASA | W68: 35 | X68: Over 18 | Y68: Draw | Z68: All Three / User Choice | AA68: Yes | AB68: Yes | AC68: Yes | AD68: Adult / serious working: let the user choose Jar, Smoke and Flame, or Charm after reading the method notes. | AE68: App should pull this row's Greenman Energy Mode from the main item sheets. Use Secondary Energy Hint only if a serious/adult spell still needs a Draw/Hold/Release/Open/Transform flavour. | AF68: Carry it close on your person | AG68: Place where it can be seen | Gift to the intended
A69: Over 18 🔞 | B69: Sacred Union | C69: Full | D69: Water | E69: Venus | F69: Friday | G69: Pink | H69: West | I69: Receptive | J69: Blue, silver, grey, black, white | K69: 6 | L69: Emotions, magnetism, gods/goddesses, cats | M69: 1, 3 or 7 | N69: HIBISCUS, ROSE PETALS, LAVENDER FLOWERS, JASMINE, HIBISCUS, ROSE BUDS RED, CARAWAY | O69: 7 | P69: quartz Rose, Emerald, Ruby, Garnet | Q69: 4 | R69: Ylang Ylang, Rose, Patchouli, Sandalwood In. | S69: 4 | T69: GEBO, INGWAZ, EHWAZ, BERKANAN | U69: 4 | V69: APHRODITE, VENUS, HATHOR, FREYJA, EROS, FREY, DIONYSUS, SHIVA | W69: 8 | X69: Over 18 | Y69: Draw | Z69: All Three / User Choice | AA69: Yes | AB69: Yes | AC69: Yes | AD69: Adult / serious working: let the user choose Jar, Smoke and Flame, or Charm after reading the method notes. | AE69: App should pull this row's Greenman Energy Mode from the main item sheets. Use Secondary Energy Hint only if a serious/adult spell still needs a Draw/Hold/Release/Open/Transform flavour. | AF69: Place at a shrine or altar | AG69: Place where it can be seen | Gift to the intended
A70: Over 18 🔞 | B70: Binding | C70: Waning | D70: Earth | E70: Saturn | F70: Saturday | G70: Black | H70: North | I70: Receptive | J70: Green, brown, black, white | K70: 8 | L70: Material aspects, travel, protection, discipline | M70: 1, 3 or 7 | N70: VERVAIN, ROSEMARY, SAGE, WORMWOOD, BLACK SALT, AGRIMONY, VALERIAN ROOT | O70: 7 | P70: Obsidian, Jet, Malachite, Onyx | Q70: 4 | R70: Frankincense, Cedarwood, Patchouli, Sandalwood w.i. | S70: 4 | T70: ISA, NAUDIZ, ALGIZ, OTHILA | U70: 4 | V70: HECATE, ISIS, CERRIDWEN, HEL, ODIN, SATURN, PLUTO, MARS | W70: 8 | X70: Over 18 | Y70: Release | Z70: All Three / User Choice | AA70: Yes | AB70: Yes | AC70: Yes | AD70: Adult / serious working: let the user choose Jar, Smoke and Flame, or Charm after reading the method notes. | AE70: App should pull this row's Greenman Energy Mode from the main item sheets. Use Secondary Energy Hint only if a serious/adult spell still needs a Draw/Hold/Release/Open/Transform flavour. | AF70: Keep it hidden and safe | AG70: Bury in the earth | Place at a shrine or altar
A71: Attraction, Love & Relationships | B71: Weddings / Handfastings | C71: Full | D71: Water | E71: Venus | F71: Friday | G71: Pink | H71: West | I71: Receptive | J71: Blue, silver, grey, black, white | K71: 6 | L71: Emotions, magnetism, gods/goddesses, cats | M71: 1, 3 or 7 | N71: CARAWAY, LAVENDER FLOWERS, ROSE PETALS, ROSE BUDS PINK, MEADOW SWEET, JASMINE, CHAMOMILE | O71: 7 | P71: quartz Rose, Emerald, Moonstone, Jade (jadeite) | Q71: 4 | R71: Rose, Lavender, Ylang Ylang, Neroli | S71: 4 | T71: GEBO, INGWAZ, WUNJO, BERKANAN | U71: 4 | V71: APHRODITE, VENUS, FRIGG, BRIGID, EROS, FREY, PAN, JUPITER | W71: 8 | X71: Draw | Y71: Draw | Z71: Spell Jar | AA71: Yes | AB71: Maybe | AC71: Yes | AD71: Draw, grow, sweeten, settle or carry relationship energy. | AE71: App should pull this row's Greenman Energy Mode from the main item sheets. Use Secondary Energy Hint only if a serious/adult spell still needs a Draw/Hold/Release/Open/Transform flavour. | AF71: Place at a shrine or altar | AG71: Place where it can be seen | Hang it in the home
A72: Attraction, Love & Relationships | B72: Soul Mate drawing | C72: Waxing | D72: Water | E72: Venus | F72: Friday | G72: Pink | H72: West | I72: Receptive | J72: Blue, silver, grey, black, white | K72: 6 | L72: Emotions, magnetism, gods/goddesses, cats | M72: 1, 3 or 7 | N72: JASMINE, ROSE PETALS, LAVENDER FLOWERS, VIOLET LEAVES, ROSE BUDS RED, YARROW, ORRIS ROOT POWDER | O72: 7 | P72: quartz Rose, Moonstone, Lapis Lazuli, Emerald | Q72: 4 | R72: Rose, Neroli, Ylang Ylang | S72: 3 | T72: GEBO, WUNJO, LAGUZ, FEHU | U72: 4 | V72: APHRODITE, VENUS, HATHOR, EROS, FREY, CUPID, DIANA | W72: 7 | X72: Draw | Y72: Draw | Z72: Spell Jar | AA72: Yes | AB72: Maybe | AC72: Yes | AD72: Draw, grow, sweeten, settle or carry relationship energy. | AE72: App should pull this row's Greenman Energy Mode from the main item sheets. Use Secondary Energy Hint only if a serious/adult spell still needs a Draw/Hold/Release/Open/Transform flavour. | AF72: Carry it close on your person | AG72: Place in a tree | Place at a shrine or altar | Bury in the earth
A73: Attraction, Love & Relationships | B73: Friendship | C73: Waxing | D73: Air | E73: Venus | F73: Friday | G73: Pink | H73: East | I73: Projective | J73: Yellow, white, crimson | K73: 6 | L73: Emotions, magnetism, gods/goddesses, cats | M73: 1, 3 or 7 | N73: ROSE BUDS PINK, LAVENDER FLOWERS, CHAMOMILE, LEMON BALM, MEADOW SWEET, VIOLET LEAVES | O73: 6 | P73: quartz Rose, Turquoise, Chrysocolla, chrysophase | Q73: 4 | R73: Rose, Lavender, Lemon | S73: 3 | T73: GEBO, WUNJO, FEHU | U73: 3 | V73: BRIGID, VENUS, APHRODITE, FREY, MERCURY, JUPITER | W73: 6 | X73: Draw | Y73: Draw | Z73: Spell Jar | AA73: Yes | AB73: Maybe | AC73: Yes | AD73: Draw, grow, sweeten, settle or carry relationship energy. | AE73: App should pull this row's Greenman Energy Mode from the main item sheets. Use Secondary Energy Hint only if a serious/adult spell still needs a Draw/Hold/Release/Open/Transform flavour. | AF73: Gift to the intended | AG73: Place where it can be seen | Hang it in the home | Carry it close on your person
A74: Attraction, Love & Relationships | B74: Passion | C74: Waxing | D74: Fire | E74: Mars | F74: Tuesday | G74: Red | H74: South | I74: Projective | J74: Red, gold, crimson, orange, white | K74: 9 | L74: Aggression, conflict, dominance | M74: 1, 3 or 7 | N74: BASIL, GINGER ROOT, CINNAMON STICKS, ROSEMARY, HIBISCUS, ROSE BUDS RED, NETTLE | O74: 7 | P74: Carnelian, Garnet, Ruby, Red Jasper | Q74: 4 | R74: Ylang Ylang, Cinnamon, Ginger, Rose | S74: 4 | T74: FEHU, URUZ, TIWAZ, EHWAZ | U74: 4 | V74: APHRODITE, VENUS, HATHOR, ARES, MARS, EROS, DIONYSUS, SHIVA | W74: 8 | X74: Draw | Y74: Draw | Z74: Spell Jar | AA74: Yes | AB74: Maybe | AC74: Yes | AD74: Draw, grow, sweeten, settle or carry relationship energy. | AE74: App should pull this row's Greenman Energy Mode from the main item sheets. Use Secondary Energy Hint only if a serious/adult spell still needs a Draw/Hold/Release/Open/Transform flavour. | AF74: Carry it close on your person | AG74: Gift to the intended | Place where it can be seen
A75: Protection, Banishing & Warding | B75: Travel protection | C75: Waxing | D75: Air | E75: Mercury | F75: Wednesday | G75: Yellow | H75: East | I75: Projective | J75: Yellow, white, crimson | K75: 5 | L75: Communication, fulfilment | M75: 1, 3 or 7 | N75: COMFREY, ROSEMARY, LAVENDER FLOWERS, COMFREY ROOT, FENNEL (SEED), ST JOHN'S WORT, GARLIC POWDER | O75: 7 | P75: Turquoise, Aquamarine, Moonstone, Tiger Eye gold | Q75: 4 | R75: Frankincense, Lavender, Cedarwood, Rosemary | S75: 4 | T75: ALGIZ, OTHILA, RAIDO, EHWAZ | U75: 4 | V75: ARTEMIS, DIANA, FLIDAIS, MERCURY, ODIN, THOR, HEIMDALL | W75: 7 | X75: Hold | Y75: Hold | Z75: Spell Jar | AA75: Yes | AB75: Maybe | AC75: Yes | AD75: Hold boundaries, guard, ward and keep protection steady. | AE75: App should pull this row's Greenman Energy Mode from the main item sheets. Use Secondary Energy Hint only if a serious/adult spell still needs a Draw/Hold/Release/Open/Transform flavour. | AF75: Carry it close on your person | AG75: Keep it hidden and safe
A76: Protection, Banishing & Warding | B76: Protection of children | C76: Waxing | D76: Earth | E76: Moon | F76: Monday | G76: White | H76: North | I76: Receptive | J76: Green, brown, black, white | K76: 2 | L76: Duality, balance, couples, partnerships | M76: 1, 3 or 7 | N76: ELDERFLOWER, LAVENDER FLOWERS, ROSEMARY, CHAMOMILE, VERVAIN, MULLEIN, ST JOHN'S WORT | O76: 7 | P76: Amethyst, quartz Rose, Turquoise, Amber | Q76: 4 | R76: Lavender, Frankincense, Cedarwood, Rose | S76: 4 | T76: ALGIZ, BERKANAN, THURISAZ, OTHILA | U76: 4 | V76: BRIGID, ARTEMIS, DIANA, ISIS, THOR, ODIN, JUPITER, THE GREAT MOTHER | W76: 8 | X76: Hold | Y76: Hold | Z76: Spell Jar | AA76: Yes | AB76: Maybe | AC76: Yes | AD76: Hold boundaries, guard, ward and keep protection steady. | AE76: App should pull this row's Greenman Energy Mode from the main item sheets. Use Secondary Energy Hint only if a serious/adult spell still needs a Draw/Hold/Release/Open/Transform flavour. | AF76: Keep it hidden and safe | AG76: Hang it in the home | Carry it close on your person
A77: Divination, Dreams & Psychic Work | B77: Scrying | C77: Full | D77: Water | E77: Moon | F77: Monday | G77: Silver or grey | H77: West | I77: Receptive | J77: Blue, silver, grey, black, white | K77: 2 | L77: Duality, balance, couples, partnerships | M77: 1 or 3 | N77: ANISE, BASIL, BAY LAUREL, BLACK TEA, CAMPHOR SYNTHETIC, CARAWAY, CINNAMON STICKS, CLOVES, COLTSFOOT, COMFREY, EYEBRIGHT, FENNEL (SEED), GARLIC POWDER, GOLDENROD, JASMINE, LAVENDER FLOWERS, LEMON VERBENA, MARIGOLD, MULLEIN, NUTMEG POWDER, OAKBARK RED, ORRIS ROOT POWDER, PARSLEY, PEPPERMINT, PINE NUT, ROSE BUDS PINK, ROSE BUDS RED, ROSE PETALS, ROSEMARY, SAGE, SANDALWOOD WHITE, THYME, VIOLET LEAVES, VIOLET, YARROW | O77: 35 | P77: Amethyst, Emerald, Jet, Moonstone, obsidian snowflake, Onyx, Opal pink, Peridot, Pyrite (Fool's Gold), Sapphire, Sugilite, Tanzanite | Q77: 12 | R77: Lemon Grass, Orange Bitter | S77: 2 | T77: ANSUZ, PERTH, SOWILO, MANNAZ, LAGUZ | U77: 5 | V77: ALL GODDESSES, ALL LUNAR GODDESSES, ARADIA, ARES, ARIANRHOD, BEFANA, CUPRA, DIANA, GOD AND GODDESS IN BALANCE, HECATE, JUTERNA, KWAI-YIN, LUNA, MOTHER GODESS, NUIT, RA, SELENE, SOL, SOPHIA, TITIANA | W77: 29 | X77: Open / Reveal | Y77: Open / Reveal | Z77: Smoke and Flame | AA77: Maybe | AB77: Yes | AC77: Yes | AD77: Open sight, smoke, dream roads and hidden knowledge. | AE77: App should pull this row's Greenman Energy Mode from the main item sheets. Use Secondary Energy Hint only if a serious/adult spell still needs a Draw/Hold/Release/Open/Transform flavour. | AF77: Place at a shrine or altar | AG77: Carry it close on your person
A78: Divination, Dreams & Psychic Work | B78: Lucid dreaming | C78: Full | D78: Water | E78: Moon | F78: Monday | G78: Silver or grey | H78: West | I78: Receptive | J78: Blue, silver, grey, black, white | K78: 2 | L78: Duality, balance, couples, partnerships | M78: 1 or 3 | N78: WORMWOOD, JASMINE, LAVENDER FLOWERS, CHAMOMILE, VALERIAN ROOT, ROSE BUDS PINK, COLTSFOOT | O78: 7 | P78: Amethyst, Moonstone, Labradorite, Sugilite | Q78: 4 | R78: Lavender, Sandalwood In., Neroli, Peppermint | S78: 4 | T78: PERTH, LAGUZ, ANSUZ, MANNAZ | U78: 4 | V78: SELENE, LUNA, HECATE, DIANA, SELENE, MERCURY, ODIN, MERCURY | W78: 8 | X78: Open / Reveal | Y78: Open / Reveal | Z78: Smoke and Flame | AA78: Maybe | AB78: Yes | AC78: Yes | AD78: Open sight, smoke, dream roads and hidden knowledge. | AE78: App should pull this row's Greenman Energy Mode from the main item sheets. Use Secondary Energy Hint only if a serious/adult spell still needs a Draw/Hold/Release/Open/Transform flavour. | AF78: Keep it hidden and safe | AG78: Carry it close on your person | Place at a shrine or altar
A79: Divination, Dreams & Psychic Work | B79: Past lives | C79: Dark | D79: Water | E79: Saturn | F79: Saturday | G79: Black | H79: West | I79: Receptive | J79: Blue, silver, grey, black, white | K79: 8 | L79: Material aspects, travel, protection, discipline | M79: 1 or 3 | N79: ANISE, APPLEWOOD CHIPS, BASIL, CHRYSANTHEMUM, CLOVER, COLTSFOOT, LEMON BALM, MULLEIN, PARSLEY, PENNYROYAL, SAGE, SANDALWOOD RED, SANDALWOOD WHITE, TANSY, THYME, BLACK SALT, YARROW | O79: 17 | P79: Jet, obsidian snowflake, Onyx, Petrified Wood, Serpentine | Q79: 5 | R79: Frankincense, Sandalwood w.i. | S79: 2 | T79: PERTH, OTHILA, MANNAZ, LAGUZ | U79: 4 | V79: ALL, AMATERASU, AMBERELLA, ARTEMIS, BEFANA, BUDDHA, DIANA, EREYR, FLIDAIS, GAIA, HATHOR, HECATE, HEL, ISIS, JANA, KWAN-YIN AND BUDDHA, LOKI, MADAME PELE, MARY MAGDALENE, MERCURY | W79: 34 | X79: Open / Reveal | Y79: Open / Reveal | Z79: Smoke and Flame | AA79: Maybe | AB79: Yes | AC79: Yes | AD79: Open sight, smoke, dream roads and hidden knowledge. | AE79: App should pull this row's Greenman Energy Mode from the main item sheets. Use Secondary Energy Hint only if a serious/adult spell still needs a Draw/Hold/Release/Open/Transform flavour. | AF79: Place at a shrine or altar | AG79: Carry it close on your person
A80: Divination, Dreams & Psychic Work | B80: Psychic development | C80: Full | D80: Air | E80: Mercury | F80: Wednesday | G80: Violet/Purple | H80: East | I80: Projective | J80: Yellow, white, crimson | K80: 5 | L80: Communication, fulfilment | M80: 1 or 3 | N80: ANISE, BASIL, BAY LAUREL, CAMPHOR SYNTHETIC, CINNAMON STICKS, CLEAVERS, CLOVES, COLTSFOOT, GARLIC POWDER, GINGER ROOT, JUNIPER BERRIES, LAVENDER FLOWERS, LEMON BALM, NUTMEG POWDER, OAKBARK RED, OREGANO, PARSLEY, PEPPERMINT, ROSE BUDS RED, ROSEMARY, SAGE, SANDALWOOD RED, SANDALWOOD WHITE, SEA SALT, THYME | O80: 25 | P80: agate Blue Lace , agate Moss , Amazonite, Amethyst, Apache Tears, Aquamarine, Calcite, Carnelian, Quartz Clear , Emerald, Flourite, Fuchsite, Howlite, Iolite, Jet, Kyanite, Labradorite, Lapis Lazuli, Moonstone, obsidian snowflake, Opal pink, Peridot, Petrified Wood, quartz rutilated , Sapphire, Seraphinite, Serpentine, Sodalite, Sugilite, Sunstone, Tanzanite, Tiger Eye gold, Topaz, Turquoise, Yellow Aventurine | Q80: 35 | R80: Bergamot, Honeysuckle, Lavender, Neroli, Peppermint, Sandalwood In. | S80: 6 | T80: ANSUZ, PERTH, SOWILO, TIWAZ, LAGUZ, DAGAZ | U80: 6 | V80: ALL GODDESSES, ALL LUNAR GODDESSES, ARADIA, ARES, ARIANRHOD, BEFANA, CUPRA, DIANA, GOD AND GODDESS IN BALANCE, HECATE, KWAI-YIN, LOKI, LUNA, MOTHER GODESS, NUIT, RA, SELENE, SOL, SOPHIA, TITIANA | W80: 26 | X80: Open / Reveal | Y80: Open / Reveal | Z80: Smoke and Flame | AA80: Maybe | AB80: Yes | AC80: Yes | AD80: Open sight, smoke, dream roads and hidden knowledge. | AE80: App should pull this row's Greenman Energy Mode from the main item sheets. Use Secondary Energy Hint only if a serious/adult spell still needs a Draw/Hold/Release/Open/Transform flavour. | AF80: Carry it close on your person | AG80: Place at a shrine or altar
A81: Divination, Dreams & Psychic Work | B81: Visions | C81: Full | D81: Air | E81: Mercury | F81: Wednesday | G81: Violet/Purple | H81: East | I81: Projective | J81: Yellow, white, crimson | K81: 5 | L81: Communication, fulfilment | M81: 1 or 3 | N81: BASIL, BAY LAUREL, CAMPHOR SYNTHETIC, CARAWAY, COLTSFOOT, EYEBRIGHT, GOLDENROD, JASMINE, LAVENDER FLOWERS, LEMON VERBENA, MARIGOLD, MULLEIN, NUTMEG POWDER, OAKBARK RED, ORRIS ROOT POWDER, PEPPERMINT, ROSE BUDS RED, ROSE PETALS, ROSEMARY, THYME, VIOLET LEAVES, VIOLET | O81: 22 | P81: Amethyst, Opal pink, Peridot, Pyrite (Fool's Gold), Sugilite | Q81: 5 | R81: Frankincense, Sandalwood In., Lavender, Patchouli | S81: 4 | T81: ANSUZ, PERTH, SOWILO, MANNAZ | U81: 4 | V81: ALL GODDESSES, ALL LUNAR GODDESSES, ARADIA, ARES, ARIANRHOD, BEFANA, CUPRA, DIANA, GOD AND GODDESS IN BALANCE, HECATE, JUTERNA, KWAI-YIN, LUNA, MOTHER GODESS, NUIT, RA, SELENE, SOL, SOPHIA, TITIANA | W81: 25 | X81: Open / Reveal | Y81: Open / Reveal | Z81: Smoke and Flame | AA81: Maybe | AB81: Yes | AC81: Yes | AD81: Open sight, smoke, dream roads and hidden knowledge. | AE81: App should pull this row's Greenman Energy Mode from the main item sheets. Use Secondary Energy Hint only if a serious/adult spell still needs a Draw/Hold/Release/Open/Transform flavour. | AF81: Carry it close on your person | AG81: Place at a shrine or altar
A82: Cleansing, Purification & Healing | B82: Emotional healing | C82: Waning | D82: Water | E82: Moon | F82: Monday | G82: Blue | H82: West | I82: Receptive | J82: Blue, silver, grey, black, white | K82: 2 | L82: Duality, balance, couples, partnerships | M82: 1, 3 or 7 | N82: ROSE PETALS, LAVENDER FLOWERS, CHAMOMILE, LEMON BALM, COMFREY, HEARTSEASE, VIOLET LEAVES | O82: 7 | P82: quartz Rose, Rhodocrosite, Lepidolite, Rhodonite | Q82: 4 | R82: Rose, Lavender, Geranium, Melissa | S82: 4 | T82: BERKANAN, LAGUZ, WUNJO, INGWAZ | U82: 4 | V82: BRIGID, HYGIA, ISIS, VENUS, ODIN, MERCURY, FREY, PAN | W82: 8 | X82: Hold | Y82: Hold | Z82: Smoke and Flame | AA82: Maybe | AB82: Yes | AC82: Yes | AD82: Clear, cleanse, restore or soothe depending on chosen spell. | AE82: App should pull this row's Greenman Energy Mode from the main item sheets. Use Secondary Energy Hint only if a serious/adult spell still needs a Draw/Hold/Release/Open/Transform flavour. | AF82: Carry it close on your person | AG82: Leave in running water | Bury in the earth
A83: Cleansing, Purification & Healing | B83: Grief working | C83: Waning | D83: Water | E83: Moon | F83: Monday | G83: White | H83: West | I83: Receptive | J83: Blue, silver, grey, black, white | K83: 2 | L83: Duality, balance, couples, partnerships | M83: 1, 3 or 7 | N83: ROSE PETALS, VIOLET LEAVES, CHAMOMILE, LEMON BALM, WILLOW BARK, MYRRH GUM, ROSEMARY | O83: 7 | P83: quartz Rose, Apache Tears, Lepidolite, Obsidian | Q83: 4 | R83: Sandalwood w.i., Rose, Lavender, Frankincense | S83: 4 | T83: PERTH, LAGUZ, ISA, MANNAZ | U83: 4 | V83: PERSEPHONE, ISIS, HEL, CERRIDWEN, ODIN, PLUTO, SATURN, URD | W83: 8 | X83: Hold | Y83: Hold | Z83: Smoke and Flame | AA83: Maybe | AB83: Yes | AC83: Yes | AD83: Clear, cleanse, restore or soothe depending on chosen spell. | AE83: App should pull this row's Greenman Energy Mode from the main item sheets. Use Secondary Energy Hint only if a serious/adult spell still needs a Draw/Hold/Release/Open/Transform flavour. | AF83: Leave in running water | AG83: Bury in the earth | Burn and release, no remains
A84: Cleansing, Purification & Healing | B84: Sleep | C84: Waning | D84: Water | E84: Moon | F84: Monday | G84: Blue | H84: West | I84: Receptive | J84: Blue, silver, grey, black, white | K84: 2 | L84: Duality, balance, couples, partnerships | M84: 1, 3 or 7 | N84: LAVENDER FLOWERS, CHAMOMILE, VALERIAN ROOT, LEMON BALM, WORMWOOD, ROSE BUDS PINK, THYME | O84: 7 | P84: Amethyst, Moonstone, Lepidolite, Howlite | Q84: 4 | R84: Lavender, Sandalwood In., Melissa, Melissa | S84: 4 | T84: ISA, LAGUZ, PERTH, MANNAZ | U84: 4 | V84: SELENE, LUNA, HECATE, DIANA, ODIN, MERCURY, SATURN | W84: 7 | X84: Hold | Y84: Hold | Z84: Smoke and Flame | AA84: Maybe | AB84: Yes | AC84: Yes | AD84: Clear, cleanse, restore or soothe depending on chosen spell. | AE84: App should pull this row's Greenman Energy Mode from the main item sheets. Use Secondary Energy Hint only if a serious/adult spell still needs a Draw/Hold/Release/Open/Transform flavour. | AF84: Keep it hidden and safe | AG84: Hang it in the home | Carry it close on your person
A85: Cleansing, Purification & Healing | B85: Aura cleansing | C85: Waning | D85: Air | E85: Moon | F85: Monday | G85: White | H85: East | I85: Projective | J85: Yellow, white, crimson | K85: 2 | L85: Duality, balance, couples, partnerships | M85: 1, 3 or 7 | N85: SAGE, LAVENDER FLOWERS, ROSEMARY, HYSSOP, AGRIMONY, SEA SALT, FRANKINCENSE | O85: 7 | P85: Amethyst, Quartz Clear, Obsidian, quartz smokey | Q85: 4 | R85: Lavender, Frankincense, Rosemary, Lavender | S85: 4 | T85: THURISAZ, ALGIZ, ISA, HAGALAZ | U85: 4 | V85: BRIGID, HYGIA, ISIS, HECATE, THOR, ODIN, MERCURY, MARS | W85: 8 | X85: Release | Y85: Release | Z85: Smoke and Flame | AA85: Maybe | AB85: Yes | AC85: Yes | AD85: Clear, cleanse, restore or soothe depending on chosen spell. | AE85: App should pull this row's Greenman Energy Mode from the main item sheets. Use Secondary Energy Hint only if a serious/adult spell still needs a Draw/Hold/Release/Open/Transform flavour. | AF85: Burn and release, no remains | AG85: Leave in running water | Bury in the earth
A86: Cleansing, Purification & Healing | B86: Dispelling melancholy | C86: Waning | D86: Air | E86: Mercury | F86: Wednesday | G86: Yellow | H86: East | I86: Projective | J86: Yellow, white, crimson | K86: 5 | L86: Communication, fulfilment | M86: 1, 3 or 7 | N86: AGRIMONY, ANISE, BASIL, BAY LAUREL, CHIVE, CLOVES, COLTSFOOT, DILL, DRAGON'S BLOOD, ELDERFLOWER, FENNEL (SEED), GINGER ROOT, HOREHOUND, LAVENDER FLOWERS, LEMONGRASS, LINSEED, MULLEIN, MUSTARD SEED WHITE, MYRRH GUM, OAKLEAF, SWEET MYRRH, PENNYROYAL, PEPPERMINT, PINE NUT, ROSEMARY, RUE, SAGE, SANDALWOOD RED, TANSY, VERVAIN, BLACK SALT | O86: 31 | P86: Obsidian, obsidian snowflake, Tourmalinee Black , Turquoise, Amber | Q86: 5 | R86: Frankincense | S86: 1 | T86: THURISAZ, KAUNO, HAGALAZ, ALGIZ | U86: 4 | V86: AESCULAPUS, AMATERASU, AMBERELLA, ARTEMIS, ASTARTE, BALDOR, BONA DEA, BRIGID, CUPRA, DIANA, DIONYSUS, FLIDAIS, HECATE, HYGIA, ISIS, JUTERNA, KWAI-YIN, KWAN-YIN AND BUDDHA, LUNA, MARS | W86: 28 | X86: Release | Y86: Release | Z86: Smoke and Flame | AA86: Maybe | AB86: Yes | AC86: Yes | AD86: Clear, cleanse, restore or soothe depending on chosen spell. | AE86: App should pull this row's Greenman Energy Mode from the main item sheets. Use Secondary Energy Hint only if a serious/adult spell still needs a Draw/Hold/Release/Open/Transform flavour. | AF86: Burn and release, no remains | AG86: Leave in running water | Bury in the earth
A87: Power, Strength & Confidence | B87: Leadership | C87: Waxing | D87: Fire | E87: Sun | F87: Sunday | G87: Gold | H87: South | I87: Projective | J87: Red, gold, crimson, orange, white | K87: 1 | L87: Developing the self, wholeness, unity, beginnings | M87: 1 or 3 | N87: ACORN, BASIL, CALAMUS ROOT, DILL, FENNEL (SEED), GARLIC POWDER, OAKBARK RED, ROSEMARY, THYME | O87: 9 | P87: Aragonite, Bloodstone, Carnelian, Flourite, Goldstone, Kyanite, Malachite, Rhodonite, Ruby, Sunstone, Tiger Eye gold, Topaz, Unakite, Yellow Aventurine, Amber | Q87: 15 | R87: Bergamot, Neroli, Thyme | S87: 3 | T87: FEHU, URUZ, WUNJO, NAUDIZ, TIWAZ | U87: 5 | V87: ALL, ALL GODDESSES, ALL LUNAR GODDESSES, AMATERASU, AMBERELLA, APHRODITE, ARES, ASTARTE, BALDUR & HATHOR, BUDDHA, CUPID, CUPRA, CYBELE, KWAN-YIN AND BUDDHA, LATONA, MAAT, MARS, MINERVA, MOTHER GODDESS, PARVATI | W87: 30 | X87: Hold | Y87: Hold | Z87: Charm Bag | AA87: Maybe | AB87: Maybe | AC87: Yes | AD87: Carry courage, strength, focus or confidence close to the body. | AE87: App should pull this row's Greenman Energy Mode from the main item sheets. Use Secondary Energy Hint only if a serious/adult spell still needs a Draw/Hold/Release/Open/Transform flavour. | AF87: Carry it close on your person | AG87: Place where it can be seen
A88: Power, Strength & Confidence | B88: Justice / Legal matters | C88: Waxing | D88: Air | E88: Jupiter | F88: Thursday | G88: Blue | H88: East | I88: Projective | J88: Yellow, white, crimson | K88: 3 | L88: Health, triple aspects, psychism | M88: 1 or 3 | N88: MARIGOLD, BASIL, OAKBARK RED, BAY LAUREL, ROSEMARY, GINGER ROOT, MARIGOLD | O88: 7 | P88: Bloodstone, Sapphire, Malachite, Obsidian | Q88: 4 | R88: Frankincense, Bergamot, Cedarwood, Orange Bitter | S88: 4 | T88: TIWAZ, SOWILO, MANNAZ, OTHILA | U88: 4 | V88: MAAT, MINERVA, ISIS, MINERVA, JUPITER, ZEUS, THOR, ODIN | W88: 8 | X88: Hold | Y88: Hold | Z88: Charm Bag | AA88: Maybe | AB88: Maybe | AC88: Yes | AD88: Carry courage, strength, focus or confidence close to the body. | AE88: App should pull this row's Greenman Energy Mode from the main item sheets. Use Secondary Energy Hint only if a serious/adult spell still needs a Draw/Hold/Release/Open/Transform flavour. | AF88: Carry it close on your person | AG88: Place at a shrine or altar | Keep it hidden and safe
A89: Power, Strength & Confidence | B89: Courage | C89: Waxing | D89: Fire | E89: Mars | F89: Tuesday | G89: Red | H89: South | I89: Projective | J89: Red, gold, crimson, orange, white | K89: 9 | L89: Aggression, conflict, dominance | M89: 1 or 3 | N89: ACORN, BASIL, CALAMUS ROOT, DILL, FENNEL (SEED), GARLIC POWDER, OAKBARK RED, ROSEMARY, THYME | O89: 9 | P89: Aragonite, Bloodstone, Carnelian, Flourite, Goldstone, Kyanite, Malachite, Rhodonite, Ruby, Sunstone, Tiger Eye gold, Topaz, Unakite, Yellow Aventurine, Amber | Q89: 15 | R89: Bergamot, Neroli, Thyme | S89: 3 | T89: FEHU, URUZ, WUNJO, NAUDIZ, TIWAZ | U89: 5 | V89: ALL, ALL GODDESSES, ALL LUNAR GODDESSES, AMATERASU, AMBERELLA, APHRODITE, ARES, ASTARTE, BALDUR & HATHOR, BUDDHA, CUPID, CUPRA, CYBELE, KWAN-YIN AND BUDDHA, LATONA, MAAT, MARS, MINERVA, MOTHER GODDESS, PARVATI | W89: 30 | X89: Hold | Y89: Hold | Z89: Charm Bag | AA89: Maybe | AB89: Maybe | AC89: Yes | AD89: Carry courage, strength, focus or confidence close to the body. | AE89: App should pull this row's Greenman Energy Mode from the main item sheets. Use Secondary Energy Hint only if a serious/adult spell still needs a Draw/Hold/Release/Open/Transform flavour. | AF89: Carry it close on your person | AG89: Place where it can be seen
A90: Power, Strength & Confidence | B90: Memory & Focus | C90: Waxing | D90: Air | E90: Mercury | F90: Wednesday | G90: Yellow | H90: East | I90: Projective | J90: Yellow, white, crimson | K90: 5 | L90: Communication, fulfilment | M90: 1 or 3 | N90: ROSEMARY, BASIL, PEPPERMINT, LEMON BALM, FENNEL (SEED), BAY LAUREL, SAGE | O90: 7 | P90: Flourite, Citrine, Quartz Clear, Sodalite | Q90: 4 | R90: Peppermint, Rosemary, Lemon, Bergamot | S90: 4 | T90: ANSUZ, MANNAZ, EHWAZ, TIWAZ | U90: 4 | V90: MERCURY, MINERVA, ISIS, BRIGID, ODIN, MERCURY, MERCURY, SOL | W90: 8 | X90: Hold | Y90: Hold | Z90: Charm Bag | AA90: Maybe | AB90: Maybe | AC90: Yes | AD90: Carry courage, strength, focus or confidence close to the body. | AE90: App should pull this row's Greenman Energy Mode from the main item sheets. Use Secondary Energy Hint only if a serious/adult spell still needs a Draw/Hold/Release/Open/Transform flavour. | AF90: Carry it close on your person | AG90: Place at a shrine or altar
A91: Power, Strength & Confidence | B91: Creativity | C91: Waxing | D91: Air | E91: Mercury | F91: Wednesday | G91: Yellow | H91: East | I91: Projective | J91: Yellow, white, crimson | K91: 5 | L91: Communication, fulfilment | M91: 1 or 3 | N91: LAVENDER FLOWERS, BASIL, ROSEMARY, CHAMOMILE, LEMON VERBENA, JASMINE, BAY LAUREL | O91: 7 | P91: Carnelian, Citrine, Flourite, Labradorite | Q91: 4 | R91: Lavender, Bergamot, Orange Bitter, Frankincense | S91: 4 | T91: ANSUZ, WUNJO, FEHU, DAGAZ | U91: 4 | V91: BRIGID, ISIS, SOPHIA, CERRIDWEN, MERCURY, ODIN, FREY, DIONYSUS | W91: 8 | X91: Transform / Turn | Y91: Transform / Turn | Z91: Charm Bag | AA91: Maybe | AB91: Maybe | AC91: Yes | AD91: Carry courage, strength, focus or confidence close to the body. | AE91: App should pull this row's Greenman Energy Mode from the main item sheets. Use Secondary Energy Hint only if a serious/adult spell still needs a Draw/Hold/Release/Open/Transform flavour. | AF91: Carry it close on your person | AG91: Place where it can be seen | Place at a shrine or altar
A92: Prosperity, Wealth & Luck | B92: Business success | C92: Waxing | D92: Earth | E92: Jupiter | F92: Thursday | G92: Green | H92: North | I92: Receptive | J92: Green, brown, black, white | K92: 3 | L92: Health, triple aspects, psychism | M92: 3 or 7 | N92: BASIL, CINNAMON STICKS, CHAMOMILE, GOLDENSEAL ROOT, LINSEED, CLOVES, MARIGOLD | O92: 7 | P92: Citrine, Aventurine, Pyrite (Fool's Gold), Jade (jadeite) | Q92: 4 | R92: Bergamot, Cinnamon, Orange Bitter, Frankincense | S92: 4 | T92: FEHU, JERA, SOWILO, OTHILA | U92: 4 | V92: MERCURY, JUPITER, GAIA, CERES, ZEUS, ODIN, THOR, FREY | W92: 8 | X92: Draw | Y92: Draw | Z92: Spell Jar | AA92: Yes | AB92: Maybe | AC92: Yes | AD92: Draw wealth, grow luck or move stagnant money energy. | AE92: App should pull this row's Greenman Energy Mode from the main item sheets. Use Secondary Energy Hint only if a serious/adult spell still needs a Draw/Hold/Release/Open/Transform flavour. | AF92: Place where it can be seen | AG92: Hang it in the home | Place at a shrine or altar
A93: Prosperity, Wealth & Luck | B93: Breaking financial stagnation | C93: Waning | D93: Earth | E93: Saturn | F93: Saturday | G93: Brown | H93: North | I93: Receptive | J93: Green, brown, black, white | K93: 8 | L93: Material aspects, travel, protection, discipline | M93: 3 or 7 | N93: ACORN, ANISE, BASIL, BENZOIN, BLACK TEA, BLACKBERRY LEAVES, CARAWAY, CHAMOMILE, CINNAMON STICKS, CLOVER, CLOVER RED, CLOVES, COLTSFOOT, COMFREY, DILL, FENNEL (SEED), GARLIC POWDER, GOLDENSEAL ROOT, JASMINE, LADIES MANTLE, LAVENDER FLOWERS, LEMON BALM, LINSEED, MUSTARD SEED WHITE, NUTMEG POWDER, OAK MOSS, OAKBARK RED, PARSLEY, PEPPERMINT, PINE NUT, RUE, SAGE, THYME, VIOLET LEAVES, VIOLET | O93: 35 | P93: agate Botswana , agate Moss , Amazonite, Aventurine, Calcite, chrysophase, Citrine, Goldstone, Jade (jadeite), Lodestone, Pyrite (Fool's Gold), Rhodocrosite, Ruby, Sapphire, Serpentine, Topaz, Tourmalinee Black , Yellow Aventurine | Q93: 18 | R93: Bergamot, Cedarwood, Clove Bud, Geranium, Honeysuckle, Marjoram, Melissa, Neroli, Orange Bitter, Pine, Vanilla, Cinnamon, Ginger, Patchouli | S93: 14 | T93: FEHU, URUZ, WUNJO, JERA, SOWILO, BERKANAN, INGWAZ, OTHILA, DAGAZ | U93: 9 | V93: ALL GODDESSES, ALL LUNAR GODDESSES, ALLAT, AMATERASU, ARADIA, ARIANRHOD, ASTARTE, ATTIS, BAAL, BALDUR & HATHOR, BONA DEA, CERES, CERRIDWEN, CRONOS, CUPRA, EROS, FILDIAS, GAIA, GOD AND GODDESS IN BALANCE, GREAT GODDESS. MANASA | W93: 36 | X93: Release | Y93: Release | Z93: Spell Jar | AA93: Yes | AB93: Maybe | AC93: Yes | AD93: Draw wealth, grow luck or move stagnant money energy. | AE93: App should pull this row's Greenman Energy Mode from the main item sheets. Use Secondary Energy Hint only if a serious/adult spell still needs a Draw/Hold/Release/Open/Transform flavour. | AF93: Burn and release, no remains | AG93: Bury in the earth | Leave in running water
A94: Prosperity, Wealth & Luck | B94: Wishes | C94: Full | D94: Air | E94: Mercury | F94: Wednesday | G94: Gold | H94: East | I94: Projective | J94: Yellow, white, crimson | K94: 5 | L94: Communication, fulfilment | M94: 3 or 7 | N94: SANDALWOOD WHITE, GOLDENROD, VIOLET LEAVES, SAGE, GOLDENROD, CHAMOMILE, LAVENDER FLOWERS | O94: 7 | P94: Quartz Clear, Moonstone, Citrine, Turquoise | Q94: 4 | R94: Sandalwood In., Frankincense, Lavender, Neroli | S94: 4 | T94: FEHU, WUNJO, DAGAZ, INGWAZ | U94: 4 | V94: BRIGID, DIANA, ISIS, VENUS, JUPITER, MERCURY, ODIN, FREY | W94: 8 | X94: Draw | Y94: Draw | Z94: Spell Jar | AA94: Yes | AB94: Maybe | AC94: Yes | AD94: Draw wealth, grow luck or move stagnant money energy. | AE94: App should pull this row's Greenman Energy Mode from the main item sheets. Use Secondary Energy Hint only if a serious/adult spell still needs a Draw/Hold/Release/Open/Transform flavour. | AF94: Place in a tree | AG94: Bury in the earth | Place at a shrine or altar
A95: Home, Blessings & Daily Magic | B95: Blessing domestic animals | C95: Full | D95: Earth | E95: Moon | F95: Monday | G95: White | H95: North | I95: Receptive | J95: Green, brown, black, white | K95: 2 | L95: Duality, balance, couples, partnerships | M95: 1 or 3 | N95: ANISE, APPLE BLOSSOM, APPLEWOOD CHIPS, BASIL, BAY LAUREL, BENZOIN, BLACK TEA, BLACKBERRY LEAVES, CALAMUS ROOT, CARAWAY, CEDARWOOD (HIMALAYAN), CHAMOMILE, CHRYSANTHEMUM, CINNAMON STICKS, CLOVER, CLOVER RED, CLOVES, COLTSFOOT, COMFREY, DILL, DRAGON'S BLOOD, ELDERFLOWER, FENNEL (SEED), FRANKINCENSE, GARDENIA FRUIT, GINGER ROOT, GOLDENROD, HEARTSEASE, HIBISCUS, HOREHOUND, HYSSOP, JASMINE, JUNIPER BERRIES, LADIES MANTLE, LAVENDER FLOWERS, LEMON BALM, LEMON VERBENA, LEMONGRASS, LINDEN, MEADOW SWEET, HONESTY, MULLEIN, MUSTARD SEED WHITE, MYRRH GUM, NUTMEG POWDER, OAKBARK RED, SWEET MYRRH, OREGANO, ORRIS ROOT POWDER, PARSLEY, PENNYROYAL, PEPPERMINT, PINE NUT, RASPBERRY LEAF, ROSE BUDS PINK, ROSE BUDS RED, ROSE HIP, ROSE PETALS, ROSEMARY, RUE, SAGE, SANDALWOOD RED, SANDALWOOD WHITE, THYME, VALERIAN ROOT, VIOLET LEAVES, VIOLET, WHEAT GRAINS | O95: 68 | P95: agate Blue Lace , Amethyst, Apache Tears, Calcite, Carnelian, Chrysocolla, Quartz Clear , Copper flakes, Emerald, Flourite, Hematite, Howlite, Jet, Lapis Lazuli, Lepidolite, Lodestone, Moonstone, Peridot, quartz Rose , quartz smokey , quartz snow , Red Jasper, Rhodonite, Ruby, Sapphire, Seraphinite, Serpentine, Sodalite, Tanzanite, Tiger Eye gold, Unakite, Yellow Aventurine | Q95: 32 | R95: Apple, Bergamot, Clove Bud, Frankincense, Geranium, Juniper, Lavender, Lemon, Lemon Grass, Marjoram, Melissa, Neroli, Orange Bitter, Pine, Rose, Rosemary, Thyme, Vanilla, Ylang Ylang, Cinnamon, Ginger, Patchouli, Sandalwood In. | S95: 23 | T95: FEHU, ANSUZ, RAIDO, GEBO, WUNJO, PERTH, SOWILO, TIWAZ, EHWAZ, INGWAZ, OTHILA | U95: 11 | V95: AESCULAPUS, ALL, ALL GODDESSES, ALL LUNAR GODDESSES, ALLAT, AMATERASU, AMBERELLA, APHRODITE, ARADIA, ARES, ARIANRHOD, ARTEMIS, ASTARTE, ATTIS, BAAL, BACCHUS, BALDOR, BALDUR & HATHOR, BEFANA, BONA DEA | W95: 89 | X95: Hold | Y95: Hold | Z95: Spell Jar | AA95: Yes | AB95: Maybe | AC95: Yes | AD95: Bless, hold, consecrate and settle magic into place or tool. | AE95: App should pull this row's Greenman Energy Mode from the main item sheets. Use Secondary Energy Hint only if a serious/adult spell still needs a Draw/Hold/Release/Open/Transform flavour. | AF95: Hang it in the home | AG95: Carry it close on your person | Place at a shrine or altar
A96: Home, Blessings & Daily Magic | B96: Tool cleansing | C96: Waning | D96: Fire | E96: Sun | F96: Sunday | G96: White | H96: South | I96: Projective | J96: Red, gold, crimson, orange, white | K96: 1 | L96: Developing the self, wholeness, unity, beginnings | M96: 1 or 3 | N96: SAGE, FRANKINCENSE, LAVENDER FLOWERS, ROSEMARY, SEA SALT, HYSSOP, THYME | O96: 7 | P96: Quartz Clear, Amethyst, Obsidian, quartz smokey | Q96: 4 | R96: Frankincense, Lavender, Rosemary, Cedarwood | S96: 4 | T96: ALGIZ, THURISAZ, ISA, OTHILA | U96: 4 | V96: BRIGID, HECATE, ISIS, DIANA, ODIN, THOR, MERCURY, ZEUS | W96: 8 | X96: Release | Y96: Release | Z96: Spell Jar | AA96: Yes | AB96: Maybe | AC96: Yes | AD96: Bless, hold, consecrate and settle magic into place or tool. | AE96: App should pull this row's Greenman Energy Mode from the main item sheets. Use Secondary Energy Hint only if a serious/adult spell still needs a Draw/Hold/Release/Open/Transform flavour. | AF96: Place at a shrine or altar | AG96: Burn and release, no remains
A97: Home, Blessings & Daily Magic | B97: Charm / Amulet making | C97: Full | D97: Earth | E97: Saturn | F97: Saturday | G97: Black | H97: North | I97: Receptive | J97: Green, brown, black, white | K97: 8 | L97: Material aspects, travel, protection, discipline | M97: 1 or 3 | N97: ROSEMARY, SAGE, LAVENDER FLOWERS, BASIL, ST JOHN'S WORT, VERVAIN, ELDERFLOWER | O97: 7 | P97: Amethyst, Quartz Clear, Jet, Obsidian | Q97: 4 | R97: Frankincense, Cedarwood, Lavender, Rosemary | S97: 4 | T97: ALGIZ, OTHILA, TIWAZ, BERKANAN | U97: 4 | V97: BRIGID, HECATE, ISIS, DIANA, ODIN, THOR, MERCURY, ZEUS | W97: 8 | X97: Hold | Y97: Hold | Z97: Spell Jar | AA97: Yes | AB97: Maybe | AC97: Yes | AD97: Bless, hold, consecrate and settle magic into place or tool. | AE97: App should pull this row's Greenman Energy Mode from the main item sheets. Use Secondary Energy Hint only if a serious/adult spell still needs a Draw/Hold/Release/Open/Transform flavour. | AF97: Carry it close on your person | AG97: Hang it in the home | Place at a shrine or altar
A98: Home, Blessings & Daily Magic | B98: Bless Book of Shadows | C98: Full | D98: Air | E98: Mercury | F98: Wednesday | G98: Violet/Purple | H98: East | I98: Projective | J98: Yellow, white, crimson | K98: 5 | L98: Communication, fulfilment | M98: 1 or 3 | N98: SAGE, FRANKINCENSE, ROSEMARY, LAVENDER FLOWERS, BAY LAUREL, WORMWOOD, THYME | O98: 7 | P98: Amethyst, Quartz Clear, Moonstone, Labradorite | Q98: 4 | R98: Frankincense, Lavender, Sandalwood In., Sandalwood w.i. | S98: 4 | T98: ANSUZ, ALGIZ, OTHILA, PERTH | U98: 4 | V98: BRIGID, HECATE, ISIS, CERRIDWEN, ODIN, MERCURY, THOR, SATURN | W98: 8 | X98: Hold | Y98: Hold | Z98: Spell Jar | AA98: Yes | AB98: Maybe | AC98: Yes | AD98: Bless, hold, consecrate and settle magic into place or tool. | AE98: App should pull this row's Greenman Energy Mode from the main item sheets. Use Secondary Energy Hint only if a serious/adult spell still needs a Draw/Hold/Release/Open/Transform flavour. | AF98: Place at a shrine or altar | AG98: Hang it in the home
A99: Spirit Work, Otherworld & Planes | B99: Ancestor work | C99: Dark | D99: Earth | E99: Saturn | F99: Saturday | G99: Black | H99: North | I99: Receptive | J99: Green, brown, black, white | K99: 8 | L99: Material aspects, travel, protection, discipline | M99: 3 or 7 | N99: ROSEMARY, WORMWOOD, MULLEIN, MYRRH GUM, ELDERFLOWER, CHRYSANTHEMUM, SAGE | O99: 7 | P99: Obsidian, Jet, Onyx, Apache Tears | Q99: 4 | R99: Sandalwood w.i., Frankincense, Sandalwood w.i., Cedarwood | S99: 4 | T99: OTHILA, PERTH, MANNAZ, ISA | U99: 4 | V99: HECATE, PERSEPHONE, ISIS, HEL, ODIN, PLUTO, SATURN, MERCURY | W99: 8 | X99: Open / Reveal | Y99: Open / Reveal | Z99: Smoke and Flame | AA99: Maybe | AB99: Yes | AC99: Maybe | AD99: Open roads, make offerings, contact spirit paths, or transform thresholds. | AE99: App should pull this row's Greenman Energy Mode from the main item sheets. Use Secondary Energy Hint only if a serious/adult spell still needs a Draw/Hold/Release/Open/Transform flavour. | AF99: Place at a shrine or altar | AG99: Carry it close on your person
A100: Spirit Work, Otherworld & Planes | B100: Binding spirits | C100: Waning | D100: Earth | E100: Saturn | F100: Saturday | G100: Black | H100: North | I100: Receptive | J100: Green, brown, black, white | K100: 8 | L100: Material aspects, travel, protection, discipline | M100: 3 or 7 | N100: ROSEMARY, SAGE, WORMWOOD, FRANKINCENSE, VERVAIN, BLACK SALT, AGRIMONY | O100: 7 | P100: Obsidian, Jet, Onyx, Malachite | Q100: 4 | R100: Frankincense, Sandalwood w.i., Cedarwood, Sandalwood w.i. | S100: 4 | T100: ISA, ALGIZ, TIWAZ, THURISAZ | U100: 4 | V100: HECATE, ISIS, HEL, PERSEPHONE, ODIN, SATURN, THOR, PLUTO | W100: 8 | X100: Open / Reveal | Y100: Open / Reveal | Z100: Smoke and Flame | AA100: Maybe | AB100: Yes | AC100: Maybe | AD100: Open roads, make offerings, contact spirit paths, or transform thresholds. | AE100: App should pull this row's Greenman Energy Mode from the main item sheets. Use Secondary Energy Hint only if a serious/adult spell still needs a Draw/Hold/Release/Open/Transform flavour. | AF100: Keep it hidden and safe | AG100: Bury in the earth | Place at a shrine or altar
...

Sheet Herbs
A1: Name | B1: Ye Olde Name | C1: Latin Name | D1: Magical Uses | E1: Association | F1: Planet | G1: Element | H1: Energy | I1: Day | J1: Deity | K1: Sabbat | L1: Folk Lore | M1: Powers | N1: Spiritual Uses | O1: Description | P1: Oil Name | Q1: Geology | R1: Warning | S1: Greenman Energy — Main | T1: Zodiac Sign | U1: Greenman Energy — Draw | V1: Greenman Energy — Hold | W1: Greenman Energy — Release | X1: Greenman Energy — Open / Reveal | Y1: Greenman Energy — Transform / Turn | Z1: Greenman Energy — Over 18
A2: ACORN | B2: FAERY CUPS | C2: Quercus robur | D2: New beginning spells, Sabbat rituals, Invocation of the Lord, Transformation/Evolution, Physical Strength, Will Power, Lust/Sex, Leadership, Wealth/Prosperity, Courage, Good luck, Protection, Wisdom, Personal power, Breaking habits, Breaking bad habits, Ending negative self-talk, Letting go of relationships, Ending guilt, Release, Renewal, New beginnings, Fresh starts, Transformation, Change, rebirth, Breakthrough, Awakening, Growth, New ideas, Assisting transformation, Strength, Fortitude, Vitality, Inner power, and strength, Confidence, Self-confidence, Bravery, Determination, Leadership skills, Commanding, Aphrodisiac, Aphrodisiac tea, Sensuality, Lust, Passionate love-making, LOVING & LUSTFUL ENERGIES, SEX MAGIC, RAISE SEXUAL ENERGY, Sexual energy, Fertility, Female fertility, Fertility magic, Fertility charms, Aiding fertility, Increasing fertility, Fruitfulness, Virility, male virility, Abundant harvest, Prosperity, Wealth, Attracting business, Business dealings, abundance, Financial arrangements, Aiding gain, Gain, PROSPERITY SPELLS, Increasing wealth, Money, Money spells, Attracting money, Drawing money, INCREASE MONEY, Breaking financial stagnation, Money mixtures, Protecting against poverty, Warding off poverty, Spell-breaking, Reversing harmful spells, Breaking spells, Hex breaking, Removing hexes, Removing curses, Removing jinxes, Removing bad luck, Breaking hexes, Returning hexes, hex-breaking, Removing hexes and curses, Removing a jinx, Luck, Good luck in family matters, Fortune, Casino luck, WISHES, Wish magick, Carrying wishes, Transmuting wishes, Protective charm, Protective charms, Protective sachets, Protective wreaths, Protective incense, PROTECT AGAINST NEGATIVITY, Protection from negativity, Circle protection, Knowledge, Intelligence, Intuition, Mental clarity, Sharpening the wits, Sharpening the brain, Mental powers, MEM, Memory, Concentration, Focus, Illumination, Enlightenment | E2: HERMES, GREEN MAN, HORNED ONE | F2: SUN | G2: FIRE | H2: MASCULINE | I2: SUNDAY | J2: FATHER GOD | K2: LITHA, YULE | L2: To Wiccans the Acorn symbolizes the Lord or Great Father. Sacred to the Druids. Can be used as offerings to the Gods. Accepted magickal symbol. | M2: new beginning spells, Sabbat rituals involving the Lord (Father God), invocation of the Lord, transformation/evolution, physical strength, will power, lust/sex, leadership, wealth/prosperity (having enough to share is the key point of this aspect), and courage-enhancing spells. | N2: As a symbol, the acorn is magically used for: new beginning spells, Sabbat rituals involving the Lord (Father God), invocation of the Lord, transformation/evolution, physical strength, will power, lust/sex, leadership, wealth/prosperity (having enough to share is the key point of this aspect), and courage-enhancing spells. | O2: As a symbol, the acorn is magically used for: new beginning spells, Sabbat rituals involving the Lord (Father God), invocation of the Lord, transformation/evolution, physical strength, will power, lust/sex, leadership, wealth/prosperity (having enough to share is the key point of this aspect), and courage-enhancing spells. Acorns can be used in charms or spells for good luck, protection, wisdom, and personal power. | P2: Cedarwood | Q2: Europe, Western Asia, North Africa (Deciduous forests) | R2: Warning: Raw acorns are toxic due to tannins. Do not ingest raw. For magical use only. | S2: The Wiccan's symbol of the Lord himself — small as a cupped palm yet holding the whole forest inside it. Grown from fire and sun, dropped from the midsummer oak at Litha, gathered at Mabon. Where the great turning of the Wheel is called, this is the seed of it. | U2: Carried for luck and new beginnings, placed on the altar at sabbats to call the Lord's energy, drawn toward prosperity and good fortune. | V2: The strength of the oak compressed into a single hard shell — courage, willpower, personal power held steady through what must be endured. | W2: Where transformation and evolution must happen, this is the thing that holds the possibility of it — the acorn before the oak. | X2: Placed on the altar when something must be seen clearly — what new beginning is truly beginning, what invitation from the Lord is being given. | Y2: Beltane and Samhain both — the seed that must die into the earth before the new thing rises. Turns spells of ending and beginning in one movement. | Z2: The seed of the Lord himself — where the sacred masculine is invoked at its most generative and potent, the acorn is placed on the altar. The fire-sun energy of new creation at its most primal, the whole oak compressed into something that fits in a palm.
A3: AGRIMONY | B3: STICKLE WORT | C3: Agrimonia eupatoria | D3: Exploring true feelings, Emotional balance, Protection, Psychic shielding, Reducing negativity, Banishing negative energies, Reversing harmful spells, Protective sachets, Cleansing the aura, Healing magic, Ritual baths, Tool cleansing, Banishing smudge, Exploring feelings, Emotional healing, Protective charm, Protective charms, Protective wreaths, Protective incense, PROTECT AGAINST NEGATIVITY, Protection from negativity, Circle protection, Protection (hexes/evil), Psychic protection, Protection from hexes, Protection from conjure, Protection from evil, Protection from evil spirits, Protection from hauntings, Ju-ju / gris-gris protection, Guarding against sorcery, Guarding against evil, Protection against the evil eye, Warding off the Evil Eye, Warding off hexes, Warding, Warding off evil, Warding off illness, Warding negativity, Bad luck warding, Sickness warding, Warding off evil influences, Warding off sickness, Dispelling sickness, Removing sickness, Removing mental troubles, Keeping illness away, Keeping sickness away, Curing fevers, Dispelling melancholy, Preventing illness, Protection against disease, Banishing, Banishing pesky spirits, Banishing unwanted energies, Casting away evil spirits, Repelling negativity, Driving away negativity, Removing negative spirits, Removing residual energies, Removing negative energy, Clearing negativity, Removing negativity, Keeping away negative forces, Exorcism, Exorcisms, Exorcism herb scattering, Exorcising demons, Exorcising evil ghosts, Exorcising evil entities, EXC, Cleansing, Cleansing baths, Cleansing tools, Cleansing the home, Cleansing space, Pre-ritual cleansing, Removing dark energies, Clearing aura attachments, Cleansing atmospheres, Cleansing objects, Cleansing body and spirit, Sweeping sacred spaces, Cleansing ritual areas, Cleansing negativity, Ritual bath, Cleansing before ritual, Purifying body and mind, Spell-breaking, Breaking spells, Hex breaking, Removing hexes, Removing curses, Removing jinxes, Removing bad luck, Breaking hexes, Returning hexes, hex-breaking, Removing hexes and curses, Removing a jinx, Luck, Good luck, Good luck in family matters, Fortune, Casino luck, WISHES, Wish magick, Carrying wishes, Transmuting wishes, Purification, Purifying ritual areas, Purifying Purifying new homes, Purifying new homes, Purifying the home, Self-purification, Purifying ritual spaces, Purification rituals, Sanctifying an area, Dedicating sacred spaces, Creating sacred spaces, Consecration, Blessing objects, Consecrating altar cloths, Anointing, Anointing tools, Anointing candles, Anointing altars, Anointing the body, Anointing amulets, Anointing talismans, Anointing baths, Anointing charm bags, Anointing mojo bags, Consecrating incense burners, Amulets/talismans, Amulets, Talismans, Charm bags, Mojo bags, Sachets, Healing, Healing spells, Healing sachets, Healing incenses, Healing mixtures, Healing rituals, Healing incense, Healing vibrations, healing after surgery, Aiding recovery, Aiding the ill, Improving health, Speeding recovery, Good health, health | E3: CANCER, SAGITTARIUS, PISCES | F3: JUPITER | G3: AIR | H3: MASCULINE | I3: THURSDAY | J3: ALL | K3: LAMMAS, MABON | L3: Believed to ensure a deep, dreamless sleep if added to pillows. | M3: spell work for those who need to explore their true feelings and to help balance the emotions applied to a situation. | N3: smudge or as a wash to cleanse the aura. | O3: Agrimony is useful for spell work for those who need to explore their true feelings and to help balance the emotions applied to a situation. The plant is also used in protection spells, to help build a psychic shield, to reduce the influence of another's negativity, and to banish negative energies and spirits. It is said to reverse harmful spells cast on you, causing them to rebound on the sender. Use in all protective sachets, spells, and medicine bags. It is useful also as a banishing smudge or as a wash to cleanse the aura. It is useful in healing magic as it enhances the strength of all healing spells, especially at a distance. You could use it in a ritual bath before beginning, as a wash for your tools, in a smudge, or simply decorate your altar with it. | P3: Peppermint | Q3: Europe, Asia (Meadows, hedge-rows) | R3: Generally considered safe for topical and ritual use. Avoid excessive internal use during pregnancy. | S3: The hedge herb of deep sleep and truth — added to the pillow it brings dreamless rest, and in the hand it keeps the psychic field clean. A defender of the mind's quiet places, growing along meadow edges and hedgerows where the wild meets the tended. | T3: Cancer, Sagittarius | U3: Where peace of mind must be drawn — emotional balance, serenity, a settled atmosphere after disruption. | V3: Protection of the aura and the psychic field — shielding against what drains, guarding what is sensitive, holding the boundary at the edge of sleep. | W3: Banishing negative energies and reversing harmful spells — a sweeping herb, clearing what has come in uninvited. | X3: Opens true feelings gently — not forcing what is hidden but creating the calm in which truth can surface without resistance. | Y3: The aura cleanser in ritual baths and cleansing ceremonies — turns the spell through purification, clearing the way for what comes next. | Z3: The deep sleep herb that strips pretence away — where emotional truth must surface without the armour that daylight allows, agrimony creates the conditions in which what is genuinely felt can no longer be avoided.
A4: ANISE | B4: ANISE | C4: Pimpinella anisum | D4: Contacting other planes, Divination, Love, Passion, Preventing nightmares, Protection, Psychic development, Psychic protection, Purification, Clairvoyance, Cleansing, Consecration, Fertility, Gain, Good luck, Happiness, Money, Weddings, Contacting planes, Communion with spirits, Communing with the departed, Communing with otherworldly entities, Spirit work, Nether-realm travel, Walking between worlds, SISM, contacting a specific person, Samhain/ancestral altars, Ancestral altars, Ancestor rituals, Rituals for the dead, Honouring the dead, ancestral magic, ancestral memory, Samhain rituals, death rites, Death and rebirth rites, Necromancy, Peaceful transition for the dead, ancestors, Crone magic, Seeing past lives, Reincarnation, Reincarnation knowledge, Past lives, Mabon/Samhain, Mabon rituals, Samhain, Enhancing divination, Divinatory incense, Foretelling the future, Future divination, Scrying, Dowsing, Prophecy, Love magick, Love drawing, Attracting love, Love-attracting rituals, Inviting love, Inducing love, Love charms, Love enchantment, Finding love, Romantic love ceremonies, PROMOTE LOVE & AFFECTION, LOVE & PEACE, Spiritual love, Love rituals, Star magick, Moon magic, Astral projection, Astral travel, Out-of-body protection, SPIRITUALITY, High spiritual vibrations, Spiritual awareness, Spiritual vibrations, Spirit offerings, Spirit offering, Ritual offerings, Offerings to Sun Gods, Offerings to forest spirits, Offerings to gods, Inviting spirits, Offertory incense, Attracting good spirits, Calling good spirits, Calling spirits, Summoning spirits, Conjuring spirits, Conjuring beneficial spirits, Otherworld travel, Shamanic work, shamanic journeying, Harmony, Domestic harmony, Peace of mind, Tranquillity, PEACE & HAPPINESS, Calming, Soothing, Calm, Calmness, Relaxation, Calming energies, Calming the mind, Calming stormy situations, Serenity, AID MEDITATION, Peace, Inner peace, Peaceful vibrations, Calming stress, Calming household upheaval, FRIENDSHIP, House blessing, Blessing the home, Homestead protection, Sick-room blessings, Home protection, Household protection, Healing altars, Home blessing, Ensuring joy in the home, Tranquillity in the home, Blessing guests, Blessing domestic animals, Meditation, Contemplation, Concentration, Focus, Sun God offerings, Solar spells, Desire, Nightmare prevention, Negating dreams, RID OF BAD DREAMS, Nightmares, Sleep, Rest, Encouraging sound sleep, Protective charm, Protective charms, Protective sachets, Protective wreaths, Protective incense, PROTECT AGAINST NEGATIVITY, Protection from negativity, Circle protection, Enhancing clairvoyance, Psychic powers, INCREASE PSYCHIC ABILITIES, Psychic awareness, Stimulating psychic senses, Disabling psychic phenomena, Psychic communication, communication and psychic abilities, Protection (hexes/evil), Psychic shielding, Protection from hexes, Protection from conjure, Protection from evil, Protection from evil spirits, Protection from hauntings, Ju-ju / gris-gris protection, Guarding against sorcery, Guarding against evil, Protection against the evil eye, Warding off the Evil Eye, Warding off hexes, Warding, Warding off evil, Warding off illness, Warding negativity, Bad luck warding, Sickness warding, Warding off evil influences, Warding off sickness, Dispelling sickness, Removing sickness, Removing mental troubles, Keeping illness away, Keeping sickness away, Curing fevers, Dispelling melancholy, Preventing illness, Protection against disease, Purifying ritual areas, Purifying Purifying new homes, Purifying new homes, Purifying the home, Self-purification, Purifying ritual spaces, Purification rituals, Sanctifying an area, Dedicating sacred spaces, Creating sacred spaces, Blessing objects, Consecrating altar cloths, Anointing, Anointing tools, Anointing candles, Anointing altars, Anointing the body, Anointing amulets, Anointing talismans, Anointing baths, Anointing charm bags, Anointing mojo bags, Consecrating incense burners, Amulets/talismans, Amulets, Talismans, Charm bags, Mojo bags, Sachets, Banishing, Banishing negative energies, Banishing smudge, Banishing pesky spirits, Banishing unwanted energies, Casting away evil spirits, Repelling negativity, Driving away negativity, Removing negative spirits, Removing residual energies, Removing negative energy, Clearing negativity, Removing negativity, Keeping away negative forces, Exorcism, Exorcisms, Exorcism herb scattering, Exorcising demons, Exorcising evil ghosts, Exorcising evil entities, EXC, Cleansing the aura, Cleansing baths, Cleansing tools, Cleansing the home, Cleansing space, Pre-ritual cleansing, Removing dark energies, Clearing aura attachments, Cleansing atmospheres, Cleansing objects, Cleansing body and spirit, Sweeping sacred spaces, Cleansing ritual areas, Cleansing negativity, Ritual baths, Ritual bath, Cleansing before ritual, Purifying body and mind, Female fertility, Fertility magic, Fertility charms, Aiding fertility, Increasing fertility, Fruitfulness, Virility, male virility, Abundant harvest, Prosperity, Wealth, Wealth/Prosperity, Attracting business, Business dealings, abundance, Financial arrangements, Aiding gain, PROSPERITY SPELLS, Increasing wealth, Money spells, Attracting money, Drawing money, INCREASE MONEY, Breaking financial stagnation, Money mixtures, Protecting against poverty, Warding off poverty, Spell-breaking, Reversing harmful spells, Breaking spells, Hex breaking, Removing hexes, Removing curses, Removing jinxes, Removing bad luck, Breaking hexes, Returning hexes, hex-breaking, Removing hexes and curses, Removing a jinx, Luck, Good luck in family matters, Fortune, Casino luck, WISHES, Wish magick, Carrying wishes, Transmuting wishes, Joy, Joyous celebrations, Contentment, Hand-fastings, Sacred union rites | E4: AQUARIUS, GEMINI, SATTITARIUS, PISCES, CANCER | F4: MERCURY, JUPITER | G4: AIR | H4: MASCULINE | I4: MONDAY,THURSDAY | J4: MERCURY, NUIT, LOKI | K4: OSTARA | L4: Believed it should be partnered with amber stones for best effect. | M4: Contacting other planes, divination, love, passion, preventing nightmares, protection, psychic development, psychic protection, purification. Other magical uses: clairvoyance, cleansing, consecration, fertility, gain, good luck, happiness, money, and weddings. | N4: Contacting other planes, divination, love, passion, preventing nightmares, protection, psychic development, psychic protection, purification. | O4: Contacting other planes, divination, love, passion, preventing nightmares, protection, psychic development, psychic protection, purification. Other magical uses: clairvoyance, cleansing, consecration, fertility, gain, good luck, happiness, money, and weddings. It was believed that it should be partnered with amber stones for best effect. | P4: Sandalwood w.i. | Q4: Eastern Mediterranean, Southwest Asia (Cultivated globally) | R4: Generally safe in culinary amounts. Avoid if allergic to anethole. Avoid excessive use during pregnancy. | S4: The sweet-sharp Mediterranean seed that has partnered amber since ancient times. Warded off nightmares, sharpened the dreaming mind, and opened the door between the waking world and the planes beyond. A Moon and Mercury herb both — quick-moving and deep-reaching at once. | T4: Cancer, Leo | U4: Love, passion and happiness drawn gently — the pleasant warmth of anise used in love sachets and celebration cakes. | V4: Protection and psychic shielding — the seed that keeps nightmares out when placed by the bed. | W4: Purification and cleansing — burned to clear a space, used in ritual baths before serious work. | X4: Opens the door to divination and contacting other planes — sharpens clairvoyance and psychic development where the veil needs thinning. | Y4: Turns the spell through cleansing and consecration — prepares what must be made ready before the real working begins. | Z4: The Sacred Union herb of the Mediterranean tradition — used in love rites where the full joining of two people is being blessed and supported.
A5: APPLE BLOSSOM | B5: TREE OF LOVE | C5: Malus domestica | D5: Love spells, Peace, Contentment, Success, Relaxation, Bath magic, Love, Love magick, Love drawing, Attracting love, Love-attracting rituals, Inviting love, Inducing love, Love charms, Love enchantment, Finding love, Romantic love ceremonies, PROMOTE LOVE & AFFECTION, LOVE & PEACE, Spiritual love, Love rituals, Star magick, Moon magic, Astral projection, Astral travel, Out-of-body protection, SPIRITUALITY, High spiritual vibrations, Spiritual awareness, Spiritual vibrations, Spirit offerings, Spirit offering, Ritual offerings, Offerings to Sun Gods, Offerings to forest spirits, Offerings to gods, Inviting spirits, Offertory incense, Attracting good spirits, Calling good spirits, Calling spirits, Summoning spirits, Conjuring spirits, Conjuring beneficial spirits, Otherworld travel, Shamanic work, shamanic journeying, Nether-realm travel, Walking between worlds, Harmony, Domestic harmony, Peace of mind, Tranquillity, PEACE & HAPPINESS, Calming, Soothing, Calm, Calmness, Calming energies, Calming the mind, Calming stormy situations, Serenity, AID MEDITATION, Inner peace, Peaceful vibrations, Calming stress, Calming household upheaval, FRIENDSHIP, House blessing, Blessing the home, Homestead protection, Sick-room blessings, Home protection, Household protection, Healing altars, Home blessing, Ensuring joy in the home, Tranquillity in the home, Blessing guests, Blessing domestic animals, Meditation, Contemplation, Concentration, Focus, Sun God offerings, Solar spells, Happiness, Joy, Joyous celebrations, Victory, victory in battle, Conquest, Overcoming opposition, Courtroom success, Legal matters, Justice | E5: VENUS, APHRODITE | F5: VENUS | G5: AIR | H5: FEMININE | I5: FRIDAY | J5: APHRODITE | K5: OSTARA, BELTANE | L5: Often used in bridal bouquets as a representation of fertility. | M5: peace, general contentment, and success. | N5: Used in love rituals and spring ceremonies. Placed on altars at Ostara and Beltane; offered to Aphrodite and Venus in devotional work. | O5: Apple blossom is used in love spells. It is delicate and faintly seductive, more of an invitation than a proposition. It can also be used for peace, general contentment, and success. Add it to the bath to aid relaxation. | P5: Apple | Q5: Central Asia (Temperate regions globally) | R5: Generally safe for ritual use. Apple seeds contain cyanogenic compounds — do not ingest seeds. | S5: The bridal tree — carried in wedding bouquets for fertility since before written record. Its blossom falls in May when Beltane fires are lit, promising fruit that will ripen by Mabon. Love, contentment and the quiet magic of a life settling into its right shape. | U5: Love spells and the drawing of peace and contentment — apple blossom in a charm draws the warmth of an established love. | V5: None specified — this herb works primarily in drawing and revealing. | W5: None specified. | X5: Opens what is buried in love — dreams of the beloved, the truth of a feeling not yet spoken aloud. | Y5: Turns the spell through the full arc from blossom to fruit — what was begun in love now beginning to ripen into something real. | Z5: The blossom of the bridal tradition in its most honest aspect — carried not just for sentiment but for the full promise of what marriage has always meant. The gateway fruit in its flowering stage, before the veil of innocence becomes the knowledge of what is beyond it.
A6: APPLEWOOD CHIPS | B6: APPLEWOOD CHIPS | C6: Malus domestica | D6: Wand making, Love spells, Mabon rituals, Samhain rituals, Honouring the dead, Ancestral altars, Spirit offerings, Contacting planes, Contacting other planes, Communion with spirits, Communing with the departed, Communing with otherworldly entities, Spirit work, Nether-realm travel, Walking between worlds, SISM, contacting a specific person, Samhain/ancestral altars, Ancestor rituals, Rituals for the dead, ancestral magic, ancestral memory, death rites, Death and rebirth rites, Necromancy, Peaceful transition for the dead, ancestors, Crone magic, Seeing past lives, Reincarnation, Reincarnation knowledge, Past lives, Mabon/Samhain, Samhain, Love, Love magick, Love drawing, Attracting love, Love-attracting rituals, Inviting love, Inducing love, Love charms, Love enchantment, Finding love, Romantic love ceremonies, PROMOTE LOVE & AFFECTION, LOVE & PEACE, Spiritual love, Love rituals, Star magick, Moon magic, Astral projection, Astral travel, Out-of-body protection, SPIRITUALITY, High spiritual vibrations, Spiritual awareness, Spiritual vibrations, Spirit offering, Ritual offerings, Offerings to Sun Gods, Offerings to forest spirits, Offerings to gods, Inviting spirits, Offertory incense, Attracting good spirits, Calling good spirits, Calling spirits, Summoning spirits, Conjuring spirits, Conjuring beneficial spirits, Otherworld travel, Shamanic work, shamanic journeying, Harmony, Domestic harmony, Peace of mind, Tranquillity, PEACE & HAPPINESS, Calming, Soothing, Calm, Calmness, Relaxation, Calming energies, Calming the mind, Calming stormy situations, Serenity, AID MEDITATION, Peace, Inner peace, Peaceful vibrations, Calming stress, Calming household upheaval, FRIENDSHIP, House blessing, Blessing the home, Homestead protection, Sick-room blessings, Home protection, Household protection, Healing altars, Home blessing, Ensuring joy in the home, Tranquillity in the home, Blessing guests, Blessing domestic animals, Meditation, Contemplation, Concentration, Focus, Sun God offerings, Solar spells | E6: VENUS, APHRODITE | F6: VENUS | G6: AIR | H6: FEMININE | I6: FRIDAY | J6: APHRODITE | K6: MABON, SAMHAIN | L6: Eating an apple opens the gateway into other realms. Dreaming of apples symbolizes prosperity and the good life. Symbols of Avalon. | M6: Wand making, Love spells, Mabon rituals, Samhain rituals, Honouring the dead, Ancestral altars, Spirit offerings | N6: in altars — Samhain is sometimes known as the "Feast of Apples". | O6: It is a great wood for a magical wand and is a favourite witch tree. The fruit is used at Mabon and Samhain, and for love spells. The apple is also considered one of the foods of the dead, so they are often piled high on Samhain altars — Samhain is sometimes known as the "Feast of Apples". | P6: Apple | Q6: Central/South Asia, Africa (Warm temperate regions) | R6: Safe for ritual and incense use. Do not ingest. | S6: The wood that opens gateways. To eat an apple is to step between worlds — the Norse knew it, the Celts knew it, the folk who left offerings at Samhain knew it. The chips carry the same doorway energy: used in ancestor work, Mabon rites, wand-making and the quiet honouring of what has passed. | U6: Love spells worked through the apple's long connection to Venus and desire. | V6: None specified. | W6: None specified. | X6: Opens the way to spirit offerings and ancestor work — the wood that burns at Samhain to invite the honoured dead. | Y6: Turns the spell through the seasonal threshold — Mabon's waning light, Samhain's open door. Where an ending must be honoured before a new turning begins. | Z6: The gateway wood of the oldest traditions — where the door between worlds must open for what has been agreed upon in the dark, applewood is the fuel that opens it. The wood of the apple that was always about more than fruit.
A7: BASIL | B7: ST. JOSEPH'S WORT | C7: Ocimum basilicum | D7: Consecration, Divination, Exorcism, Fertility, Fidelity, Good luck, Happiness, Harmony, Love, Money, Passion, Peace, Prosperity, Protection, Psychic development, Psychic protection, Purification, Strength, Success, Tranquillity, Clairvoyance, Commanding, Courage, Grieving, Hatred, Honesty, Initiation, Inspiration, Invocation, Preventing theft, Rituals for the dead, Spell-breaking, Purifying ritual areas, Purifying Purifying new homes, Purifying new homes, Purifying the home, Self-purification, Purifying ritual spaces, Purification rituals, Sanctifying an area, Dedicating sacred spaces, Creating sacred spaces, Blessing objects, Consecrating altar cloths, Anointing, Anointing tools, Anointing candles, Anointing altars, Anointing the body, Anointing amulets, Anointing talismans, Anointing baths, Anointing charm bags, Anointing mojo bags, Consecrating incense burners, Amulets/talismans, Amulets, Talismans, Protective sachets, Charm bags, Mojo bags, Sachets, Enhancing divination, Divinatory incense, Foretelling the future, Future divination, Scrying, Dowsing, Prophecy, Banishing, Banishing negative energies, Banishing smudge, Banishing pesky spirits, Banishing unwanted energies, Casting away evil spirits, Repelling negativity, Driving away negativity, Removing negative spirits, Removing residual energies, Removing negative energy, Clearing negativity, Removing negativity, Keeping away negative forces, Exorcisms, Exorcism herb scattering, Exorcising demons, Exorcising evil ghosts, Exorcising evil entities, EXC, Cleansing, Cleansing the aura, Cleansing baths, Cleansing tools, Cleansing the home, Cleansing space, Pre-ritual cleansing, Removing dark energies, Clearing aura attachments, Cleansing atmospheres, Cleansing objects, Cleansing body and spirit, Sweeping sacred spaces, Cleansing ritual areas, Cleansing negativity, Ritual baths, Ritual bath, Cleansing before ritual, Purifying body and mind, Female fertility, Fertility magic, Fertility charms, Aiding fertility, Increasing fertility, Fruitfulness, Virility, male virility, Abundant harvest, Wealth, Wealth/Prosperity, Attracting business, Business dealings, abundance, Financial arrangements, Aiding gain, Gain, PROSPERITY SPELLS, Increasing wealth, Money spells, Attracting money, Drawing money, INCREASE MONEY, Breaking financial stagnation, Money mixtures, Protecting against poverty, Warding off poverty, Faithfulness, Loyalty, Promoting fidelity, Ensuring a lover returns love, Reversing harmful spells, Breaking spells, Hex breaking, Removing hexes, Removing curses, Removing jinxes, Removing bad luck, Breaking hexes, Returning hexes, hex-breaking, Removing hexes and curses, Removing a jinx, Luck, Good luck in family matters, Fortune, Casino luck, WISHES, Wish magick, Carrying wishes, Transmuting wishes, Joy, Joyous celebrations, Contentment, Serenity, Ensuring joy in the home, PEACE & HAPPINESS, Love magick, Love drawing, Attracting love, Love-attracting rituals, Inviting love, Inducing love, Love charms, Love enchantment, Finding love, Romantic love ceremonies, PROMOTE LOVE & AFFECTION, LOVE & PEACE, Spiritual love, Love rituals, Star magick, Moon magic, Astral projection, Astral travel, Out-of-body protection, SPIRITUALITY, High spiritual vibrations, Spiritual awareness, Spiritual vibrations, Spirit offerings, Spirit offering, Ritual offerings, Offerings to Sun Gods, Offerings to forest spirits, Offerings to gods, Inviting spirits, Offertory incense, Attracting good spirits, Calling good spirits, Calling spirits, Summoning spirits, Conjuring spirits, Conjuring beneficial spirits, Otherworld travel, Shamanic work, shamanic journeying, Nether-realm travel, Walking between worlds, Domestic harmony, Peace of mind, Calming, Soothing, Calm, Calmness, Relaxation, Calming energies, Calming the mind, Calming stormy situations, AID MEDITATION, Inner peace, Peaceful vibrations, Calming stress, Calming household upheaval, FRIENDSHIP, House blessing, Blessing the home, Homestead protection, Sick-room blessings, Home protection, Household protection, Healing altars, Home blessing, Tranquillity in the home, Blessing guests, Blessing domestic animals, Meditation, Contemplation, Concentration, Focus, Sun God offerings, Solar spells, Desire, Protective charm, Protective charms, Protective wreaths, Protective incense, PROTECT AGAINST NEGATIVITY, Protection from negativity, Circle protection, Enhancing clairvoyance, Psychic powers, INCREASE PSYCHIC ABILITIES, Psychic awareness, Stimulating psychic senses, Disabling psychic phenomena, Psychic communication, communication and psychic abilities, Protection (hexes/evil), Psychic shielding, Protection from hexes, Protection from conjure, Protection from evil, Protection from evil spirits, Protection from hauntings, Ju-ju / gris-gris protection, Guarding against sorcery, Guarding against evil, Protection against the evil eye, Warding off the Evil Eye, Warding off hexes, Warding, Warding off evil, Warding off illness, Warding negativity, Bad luck warding, Sickness warding, Warding off evil influences, Warding off sickness, Dispelling sickness, Removing sickness, Removing mental troubles, Keeping illness away, Keeping sickness away, Curing fevers, Dispelling melancholy, Preventing illness, Protection against disease, Physical Strength, Fortitude, Vitality, Inner power, and strength, Victory, victory in battle, Conquest, Overcoming opposition, Courtroom success, Legal matters, Justice, Confidence, Self-confidence, Bravery, Determination, Will Power, Leadership, Leadership skills, Personal power, Prophetic dreams, Invoking dreams, Dream work, Dreams, Visions, Seeing the unseen, Seeing manifestations, Truth, Removing deception, Subconscious work, Digging into the subconscious, Uprooting what is hidden, Treasure seeking, Lost object finding, Anti-theft, Protection against theft, Contacting planes, Contacting other planes, Communion with spirits, Communing with the departed, Communing with otherworldly entities, Spirit work, SISM, contacting a specific person, Samhain/ancestral altars, Ancestral altars, Ancestor rituals, Honouring the dead, ancestral magic, ancestral memory, Samhain rituals, death rites, Death and rebirth rites, Necromancy, Peaceful transition for the dead, ancestors, Crone magic, Seeing past lives, Reincarnation, Reincarnation knowledge, Past lives, Mabon/Samhain, Mabon rituals, Samhain | E7: VISHNU, KRISHNA, IMBOLC | F7: MARS | G7: FIRE | H7: MASCULINE | I7: Tuesday | J7: VISHNU | K7: IMBOLC | L7: Said to be attractive to dragons, salamanders, and other fire-oriented creatures. | M7: consecration, divination (especially about love), exorcism, fertility, fidelity, good luck, happiness, harmony, love, money, passion, peace, prosperity, protection, psychic development, psychic protection, purification, strength, success, tranquillity, clairvoyance, commanding, courage, grieving, ha | N7: for consecration, divination (especially about love), exorcism, fertility, fidelity, good luck, happiness, harmony, love, money, passion, peace, prosperity, protection, psychic development, psychic pr | O7: Use for consecration, divination (especially about love), exorcism, fertility, fidelity, good luck, happiness, harmony, love, money, passion, peace, prosperity, protection, psychic development, psychic protection, purification, strength, success, tranquillity, clairvoyance, commanding, courage, grieving, hatred, honesty, initiation, inspiration, and invocation. It is said to prevent theft. Basil is often used in rituals for the dead and in spell-breaking. | P7: Pine | Q7: Mediterranean region (Coastal forests) | R7: Generally considered safe for culinary and ritual use. Avoid medicinal doses during pregnancy. | S7: The dragon-and-fire herb that attracts salamanders and fire elementals. Sacred to Mars and worked at the crossing points — Beltane, marriage, the ritual hearth. Useful in almost every working from love to exorcism, which is why the Greeks called it the royal herb. The sovereign of the kitchen garden and the magical one both. | T7: Scorpio | U7: Love, passion, happiness, fertility and prosperity drawn through this herb's warm solar fire energy. | V7: Protection and psychic shielding, courage and strength — the herb that guards the home and holds the boundary. | W7: Exorcism, purification and spell-breaking — burned to clear what clings, used to drive out what has overstayed. | X7: Opens the way to divination and clairvoyance — sharpens the sight when burned as incense before a reading. | Y7: Turns through consecration and the crossing of thresholds — used at initiations, invocations and the beginning of new magical commitments. | Z7: The dragon-herb in its most fiercely projective aspect — where the working requires the raw force of Mars without apology, basil is the fire herb that does not temper itself. Used where desire, exorcism and fertility must operate at full strength at once.
